Workbook
Name ArbBidrag: #REF!
Name ArbBidrag: #REF!
Name ArbBidrag: #REF!
Name ArbBidrag: #REF!
Name ArbBidrag: #REF!
Name ArbBidrag: #REF!
Name ArbBidrag: #REF!
Name ArbBidrag: #REF!
Name ArbBidrag: Skattesatser!$H$3
Name BeFradragHojSats: #REF!
Name BeFradragHojSats: #REF!
Name BeFradragHojSats: #REF!
Name BeFradragHojSats: #REF!
Name BeFradragHojSats: #REF!
Name BeFradragHojSats: #REF!
Name BeFradragHojSats: #REF!
Name BeFradragHojSats: #REF!
Name BeFradragHojSats: Skattesatser!$H$4
Name BeFradragKmMax: #REF!
Name BeFradragKmMax: #REF!
Name BeFradragKmMax: #REF!
Name BeFradragKmMax: #REF!
Name BeFradragKmMax: #REF!
Name BeFradragKmMax: #REF!
Name BeFradragKmMax: #REF!
Name BeFradragKmMax: #REF!
Name BeFradragKmMax: Skattesatser!$H$6
Name BeFradragKmMin: #REF!
Name BeFradragKmMin: #REF!
Name BeFradragKmMin: #REF!
Name BeFradragKmMin: #REF!
Name BeFradragKmMin: #REF!
Name BeFradragKmMin: #REF!
Name BeFradragKmMin: #REF!
Name BeFradragKmMin: #REF!
Name BeFradragKmMin: Skattesatser!$H$5
Name BeFradragLavSats: #REF!
Name BeFradragLavSats: #REF!
Name BeFradragLavSats: #REF!
Name BeFradragLavSats: #REF!
Name BeFradragLavSats: #REF!
Name BeFradragLavSats: #REF!
Name BeFradragLavSats: #REF!
Name BeFradragLavSats: #REF!
Name BeFradragLavSats: Skattesatser!$H$7
Name BFradragMax: #REF!
Name BFradragMax: #REF!
Name BFradragMax: #REF!
Name BFradragMax: #REF!
Name BFradragMax: #REF!
Name BFradragMax: #REF!
Name BFradragMax: #REF!
Name BFradragMax: #REF!
Name BFradragMax: Skattesatser!$H$10
Name BFradragProc: #REF!
Name BFradragProc: #REF!
Name BFradragProc: #REF!
Name BFradragProc: #REF!
Name BFradragProc: #REF!
Name BFradragProc: #REF!

Sheet Enlig skat før boligkøb
B1: Skatteberegningsprogram - enlig | C1: År 2025
C2: Person | I2: =C2 -> Person
B3: Privat indskud på ratepension (og ophørende livrente) | C3: 0 | I3: Beregnings-grundlag | J3: Beregnet skat
B4: Privat indskud på livrente | C4: 0 | F4: Beregning af skat | G4: Procent | H4: Fradrag
B5: Alder | C5: 30 | F5: Bundskat | G5: =Bundskat -> 0.1201 | H5: =Personfradrag -> 51600 | I5: =IF(C35>=0,C31+C35-H5,C31-H5) -> 408400 | J5: =+IF(I5>0,G5*I5,0) -> 49048.84
B6: Har fri telefon (ja/nej) | C6: nej | F6: Topskat | G6: =Topskat -> 0.15 | H6: =TopSkatGranse -> 611800 | I6: =MAX((C70-$H$6),0) -> 0 | J6: =G6*I6 -> 0
B7: Fagforening | C7: 0 | F7: Sundhedsbidrag | G7: =Sundhedsbidrag -> 0 | H7: =Personfradrag -> 51600 | I7: =($C$45+AB29)-(H7+AB43) -> 300338.4 | J7: =+IF(I7>0,I7*G7,0) -> 0
B8: A-kasse og efterløn | C8: 0 | F8: Kommuneskat | G8: =C13 -> 0.25 | H8: =Personfradrag -> 51600 | I8: =($C$45+AB29)-(H8+AB44) -> 300338.4 | J8: =+IF(I8>0,$C$13*I8,0) -> 75084.6
B9: Antal km til arbejde (tur/retur) | C9: 130 | F9: Kirkeskat | G9: =C14 -> 0.009 | H9: =Personfradrag -> 51600 | I9: =($C$45+AB29)-(H9+AB45) -> 300338.4 | J9: =+IF(I9>0,$C$14*I9,0) -> 2703.0456
B10: Antal arbejdsdage | C10: 220 | J10: =SUM(J5:J9) -> 126836.49
B11: Medlem af Folkekirken (ja/nej) | C11: ja
B12: Vælg Kommune | C12: Ishøj | F12: Evt skattetillæg af neg. KI under 50.000 | J12: =IF(C35>=0,0,IF(C35>=GranseNegKIEnlig,TillagNegKI*C35,TillagNegKI*GranseNegKIEnlig)) -> 0
B13: Kommuneskattesats | C13: =_xlfn.XLOOKUP(C12,Skattesatser!B6:B103,Skattesatser!C6:C103,2)/100 -> 0.25 | F13: Evt. nedslag i topskatten (lønindkomst) | I13: =IF($C$73>SkraatSkatteloftPI,$C$73-SkraatSkatteloftPI,0) -> 0 | J13: =-I13*C75 -> 0
B14: Kirkeskattesats | C14: =IF(C11="ja",_xlfn.XLOOKUP(C12,Skattesatser!B6:B103,Skattesatser!D6:D103,2)/100,0) -> 0.009 | F14: Evt. nedslag i topskatten (kapitalindkomst) | I14: =IF($C$73>SkraatSkatteloftKI,$C$73-SkraatSkatteloftKI,0) -> 0.1001 | J14: =-I14*C76 -> 0
B15: Grundskyldssats | C15: =_xlfn.XLOOKUP(C12,Skattesatser!B6:B103,Skattesatser!E6:E103,2)/1000 -> 0.0065 | J15: =SUM(J10:J14) -> 126836.49
B16: Ejendomsværdi (offentlig)
B17: Grundværdi (offentlig)
B18: Evt skatterabat (bolig købt før 1.jan.2024) | C18: 0 | F18: Indkomstskat i alt (incl. AM-bidrag) | J18: =J15+C27 -> 166836.49
F19: Ejendomsværdiskat | J19: =+F63 -> 0
B20: Lønindkomst (efter evt. ATP) | C20: 500000 | F20: Grundskyld | J20: =F64 -> 0
B21: arbejdsgiverpensionsordning % (kun eget indskud) | C21: 0 | F21: Skatterabat | J21: =-C18 -> 0
B22: - arbejdsgiverpensionsordning DKK (kun eget indskud) | C22: =C21*C20 -> 0
B23: + anden AM-pligtig indkomst | C23: 0 | F23: Skat i alt | J23: =SUM(J18:J21) -> 166836.49
B24: + fri telefon | C24: =IF(C6="ja",FriTelefon,0) -> 0
B25: = Beregningsgrundlag for AM-bidrag | C25: =C20-C22+C23+C24 -> 500000 | D25: BG 1
F26: Udbetalt efter skat | I26: =C2 -> Person
B27: - AM-bidrag | C27: =ArbBidrag*C25 -> 40000 | I27: Pr. år | J27: Pr. måned
B28: + Ikke AM-pligtig indkomst (SU, dagpenge, pension etc.) | C28: 0 | F28: Lønindkomst | I28: =C20+C23+C28 -> 500000 | J28: =I28/12 -> 41666.667
B29: - Eget indskud på ratepension (husk også at indtaste i budget) | C29: =IF(C3>RatepensionMax,RatepensionMax,C3) -> 0 | F29: - arbejdsgiver pensionsordning | I29: =C22 -> 0 | J29: =I29/12 -> 0
B30: - Eget indskud på livrente (husk også at indtaste i budget) | C30: =+C4 -> 0 | F30: - skat | I30: =J23 -> 166836.49 | J30: =I30/12 -> 13903.04
B31: = Personlig indkomst (PI) | C31: =C25-C27+C28-C29-C30 -> 460000 | D31: BG 2 | F31: Udbetalt efter skat | I31: =I28-I29-I30 -> 333163.51 | J31: =I31/12 -> 27763.626
B33: + Renteindtægter | C33: 0
B34: - Renteudgfter | C34: 0
B35: + Kapitalindkomst (KI) i alt | C35: =+C33-C34 -> 0
B37: Beskæftigelsesfradrag | C37: =MIN(+($C$25+$C$22*3)*BFradragProc,BFradragMax) -> 55600
B38: Jobfradrag | C38: =MAX(0,MIN(+($C$25+$C$22*3-Jfradraggranse)*Jfradragproc,JfradragMax)) -> 2900
B39: Ekstra pensionsfradrag | C39: =IF(C5<=52,MIN(+(C3+C4+C22*3)*EPENfradragProc,EPENfradragMax),MIN(+(C3+C4+C22*3)*EPENSeniorProc,EPENSeniorMax)) -> 0
B40: Fagforening, A-kasse og efterløn | C40: =IF(C7>FagforeningMax,FagforeningMax,C7)+C8 -> 0
B41: Befordring | C41: =+$H$56 -> 49561.6
B42: Andre ligningsmæssige fradrag | C42: 0
B43: - Ligningsmæssige fradrag i alt | C43: =SUM(C37:C42) -> 108061.6
B45: = Skattepligtig indkomst (SI) | C45: =+C31+C35-C43 -> 351938.4 | D45: BG 3
B50: BEREGNINGSOMRÅDE (INDTAST IKKE NOGET)
B52: Person1
C53: sats | D53: dage | E53: km/dag | F53: min. | G53: frad./dag | H53: fradrag i alt
B54: Befordring for km under standardgrænse | C54: =BeFradragHojSats -> 2.23 | D54: =C10 -> 220 | E54: =C9 -> 130 | F54: =BeFradragKmMin -> 24 | G54: =IF(E54>F54,MIN(E54,BeFradragKmMax)-F54,0) -> 96 | H54: =+(D54*G54)*C54 -> 47097.6
B55: Befordring for km over standardgrænse | C55: =BeFradragLavSats -> 1.12 | D55: =C10 -> 220 | E55: =MAX(E54-BeFradragKmMax,0) -> 10 | G55: =MAX(E55,0) -> 10 | H55: =+(D55*G55)*C55 -> 2464
B56: Samlet befordringsfradrag | H56: =SUM(H54:H55) -> 49561.6
B58: Evt. forhøjelser skal laves manuelt
B62: Ejendomsskatter | C62: Sats | D62: Høj sats | E62: Ejendomsværdi | F62: I alt
B63: Ejendomsværdiskat | C63: =EjVSkatMin -> 0.0051 | D63: =EjVSkatMax-C63 -> 0.0089 | E63: =C16 -> 0 | F63: =IF(E63<Skattesatser!H14,C63*E63*Forsigtighed,C63*E63*Forsigtighed+(E63-Skattesatser!H14)*D63*Forsigtighed) -> 0
B64: Grundskyld | C64: =C15 -> 0.0065 | E64: =C17 -> 0 | F64: =E64*C64*Forsigtighed -> 0
B67: Mellemregninger | C67: Person 1
B68: Værdi af personlig indkomst | C68: =+C31 -> 460000
B69: Værdi af personlig indkomst plus positiv kapitalindkomst | C69: =MAX(C35+C31,C31) -> 460000
B70: Værdi af PI plus KI > min grænse | C70: =C68+C72 -> 460000
B71: Positiv kapitalindkomst | C71: =MAX(C35,0) -> 0
B72: Positiv kapitalindkomst over min grænse | C72: =IF((C71+D71)>KItilTopskatEnlig,C71+D71-KItilTopskatEnlig,0) -> 0
B73: Sum af skatteprocenter | C73: =SUM(G5:G8) -> 0.5201
B74: Topskatteberegningsgrundlag | C74: =IF(C70>TopSkatGranse,C70-TopSkatGranse,0) -> 0
B75: - andel som vedrører lønindkomst | C75: =IF(C68>TopSkatGranse,C68-TopSkatGranse,0) -> 0
B76: - andel som vedrører kapitalindkomst | C76: =C74-C75 -> 0

Sheet Ægtepar skat før boligkøb
B1: Skatteberegningsprogram - par | C1: År 2025
B2: Person 1, er den med højest indkomst | C2: Person 1 | D2: Person 2 | I2: =C2 -> Person 1 | K2: =D2 -> Person 2
B3: Privat indskud på ratepension (og ophørende livrente) | C3: 0 | D3: 0 | I3: Beregnings-grundlag | J3: Beregnet skat | K3: Beregnings-grundlag | L3: Beregnet skat
B4: Privat indskud på livrente | C4: 0 | D4: 0 | F4: Beregning af skat | G4: Procent | H4: Fradrag
B5: Alder | C5: 29 | D5: 27 | F5: Bundskat | G5: =Bundskat -> 0.1201 | H5: =Personfradrag -> 51600 | I5: =IF($AC$28=1,($C$31+$AC$29),$C$77)-($H$5+$AB$41) -> -100164 | J5: =+IF(I5>0,G5*I5,0) -> 0 | K5: =IF(AC28=1,(D31+AD29),$D$77)-H5 -> -51600 | L5: =+IF(K5>0,K5*G5,0) -> 0
B6: Har fri telefon (ja/nej) | C6: ja | D6: nej | F6: Topskat | G6: =Topskat -> 0.15 | H6: =TopSkatGranse -> 611800 | I6: =MAX((C78-$H$6),0) -> 0 | J6: =G6*I6 -> 0 | K6: =MAX((D77-$H$6),0) -> 0 | L6: =G6*K6 -> 0
B7: Fagforening | C7: 6000 | D7: 0 | F7: Sundhedsbidrag | G7: =Sundhedsbidrag -> 0 | H7: =Personfradrag -> 51600 | I7: =($C$45+AB29)-(H7+AB43) -> -106569.9 | J7: =+IF(I7>0,I7*G7,0) -> 0 | K7: =($D$45-AB29)-H7 -> -51600 | L7: =+IF(K7>0,G7*K7,0) -> 0
B8: A-kasse og efterløn | C8: 0 | D8: 0 | F8: Kommuneskat | G8: =C13 -> 0.2452 | H8: =Personfradrag -> 51600 | I8: =($C$45+AB29)-(H8+AB44) -> -106569.9 | J8: =+IF(I8>0,$C$13*I8,0) -> 0 | K8: =($D$45-AB29)-H8 -> -51600 | L8: =+IF(K8>0,$D$13*K8,0) -> 0
B9: Antal km til arbejde (tur/retur) | C9: 1 | D9: 0 | F9: Kirkeskat | G9: =C14 -> 0 | H9: =Personfradrag -> 51600 | I9: =($C$45+AB29)-(H9+AB45) -> -106569.9 | J9: =+IF(I9>0,$C$14*I9,0) -> 0 | K9: =($D$45-AB29)-H9 -> -51600 | L9: =+IF(K9>0,$D$14*K9,0) -> 0
B10: Antal arbejdsdage | C10: 216 | D10: 0 | J10: =SUM(J5:J9) -> 0 | L10: =SUM(L5:L9) -> 0
B11: Medlem af Folkekirken (ja/nej) | C11: nej | D11: nej
B12: Vælg Kommune | C12: Aarhus | D12: =C12 -> Aarhus | F12: Evt skattetillæg af neg. KI under 50.000 | J12: =IF(AA29>=0,0,IF(AA29>=GranseNegKIPar,TillagNegKI*AA29,TillagNegKI*GranseNegKIPar)) -> 0
B13: Kommuneskattesats | C13: =_xlfn.XLOOKUP(C12,Skattesatser!B6:B103,Skattesatser!C6:C103,2)/100 -> 0.2452 | D13: =_xlfn.XLOOKUP(D12,Skattesatser!B6:B103,Skattesatser!C6:C103,2)/100 -> 0.2452 | F13: Evt. nedslag i topskatten (lønindkomst) | I13: =IF($C$81>SkraatSkatteloftPI,$C$81-SkraatSkatteloftPI,0) -> 0 | J13: =-I13*C83 -> 0 | K13: =IF($D$81>SkraatSkatteloftPI,$D$81-SkraatSkatteloftPI,0) -> 0 | L13: =-K13*D83 -> 0
B14: Kirkeskattesats | C14: =IF(C11="ja",_xlfn.XLOOKUP(C12,Skattesatser!B6:B103,Skattesatser!D6:D103,2)/100,0) -> 0 | D14: =IF(D11="ja",_xlfn.XLOOKUP(D12,Skattesatser!B6:B103,Skattesatser!D6:D103,2)/100,0) -> 0 | F14: Evt. nedslag i topskatten (kapitalindkomst) | I14: =IF($C$81>SkraatSkatteloftKI,$C$81-SkraatSkatteloftKI,0) -> 0.0953 | J14: =-I14*C84 -> 0
B15: Grundskyldssats | C15: =_xlfn.XLOOKUP(C12,Skattesatser!B6:B103,Skattesatser!E6:E103,2)/1000 -> 0.006 | J15: =SUM(J10:J14) -> 0 | L15: =SUM(L10:L14) -> 0
B16: Ejendomsværdi (offentlig) | C16: 0
B17: Grundværdi (offentlig) | C17: 0
B18: Evt skatterabat (bolig købt før 1.jan.2024) | C18: 0 | F18: Indkomstskat i alt (incl. AM-bidrag) | J18: =J15+C27 -> 264 | L18: =L15+D27 -> 0
F19: Ejendomsværdiskat | J19: =+F71/2 -> 0 | L19: =J19 -> 0
B20: Lønindkomst (efter evt. ATP) | C20: 0 | D20: 0 | F20: Grundskyld | J20: =F72/2 -> 0 | L20: =J20 -> 0
B21: arbejdsgiverpensionsordning % (kun eget indskud) | C21: 0 | D21: 0 | F21: Skatterabat | J21: =-C18/2 -> 0 | L21: =J21 -> 0
B22: - arbejdsgiverpensionsordning DKK (kun eget indskud) | C22: =C21*C20 -> 0 | D22: =D21*D20 -> 0
B23: + anden AM-pligtig indkomst | C23: 0 | D23: 0 | F23: Skat i alt | J23: =SUM(J18:J22) -> 264 | L23: =SUM(L18:L22) -> 0
B24: + fri telefon | C24: =IF(C6="ja",FriTelefon,0) -> 3300 | D24: =IF(D6="ja",FriTelefon,0) -> 0
B25: = Beregningsgrundlag for AM-bidrag | C25: =C20-C22+C23+C24 -> 3300 | D25: =D20-D22+D23+D24 -> 0
F26: Udbetalt efter skat | I26: =C2 -> Person 1 | K26: =D2 -> Person 2 | AB26: Uudnyttet | AC26: Udligning af KI til brug for bundskat
B27: - AM-bidrag | C27: =ArbBidrag*C25 -> 264 | D27: =ArbBidrag*D25 -> 0 | I27: Pr. år | J27: Pr. måned | K27: Pr. år | L27: Pr. måned | AB27: KI | AC27: P1 | AD27: P2
B28: + Ikke AM-pligtig indkomst (SU, dagpenge, pension etc.) | C28: 0 | D28: 0 | F28: Lønindkomst | I28: =C20+C23+C28 -> 0 | J28: =I28/12 -> 0 | K28: =D20+D23+D28 -> 0 | L28: =K28/12 -> 0 | AB28: person 2 | AC28: =IF(AA29<0,0,IF((C35+0.00000001)*(D35+0.0000001)<0,1,0)) -> 0
B29: - Eget indskud på ratepension (husk også at indtaste i budget) | C29: =IF(C3>RatepensionMax,RatepensionMax,C3) -> 0 | D29: =IF(D3>RatepensionMax,RatepensionMax,D3) -> 0 | F29: - arbejdsgiver pensionsordning | I29: =C22 -> 0 | J29: =I29/12 -> 0 | K29: =D22 -> 0 | L29: =K29/12 -> 0 | AA29: =SUM(C35:D35) -> 0 | AB29: =IF(D45<0,IF(D31-D43<0,D35,D35+D31-D43),0) -> 0 | AC29: =IF(AC28=1,C35+D35,0) -> 0 | AD29: =IF(AC28=1,0,D35) -> 0
B30: - Eget indskud på livrente (husk også at indtaste i budget) | C30: =+C4 -> 0 | D30: =+D4 -> 0 | F30: - skat | I30: =J23 -> 264 | J30: =I30/12 -> 22 | K30: =L23 -> 0 | L30: =K30/12 -> 0
B31: = Personlig indkomst (PI) | C31: =C25-C27+C28-C29-C30 -> 3036 | D31: =D25-D27+D28-D29-D30 -> 0 | F31: Udbetalt efter skat | I31: =I28-I29-I30 -> -264 | J31: =I31/12 -> -22 | K31: =K28-K29-K30 -> 0 | L31: =K31/12 -> 0
B33: + Renteindtægter | C33: 0 | D33: 0
B34: - Renteudgfter | C34: 0 | D34: 0
B35: + Kapitalindkomst (KI) i alt | C35: =+C33-C34 -> 0 | D35: =+D33-D34 -> 0
B37: Beskæftigelsesfradrag | C37: =MIN(+(C25+C22*3)*BFradragProc,BFradragMax) -> 405.9 | D37: =MIN(+(D25+D22*3)*BFradragProc,BFradragMax) -> 0
B38: Jobfradrag | C38: =MAX(0,MIN(+($C$25+C22*3-Jfradraggranse)*Jfradragproc,JfradragMax)) -> 0 | D38: =MAX(0,MIN(+($D$25+D22*3-Jfradraggranse)*Jfradragproc,JfradragMax)) -> 0 | AB38: Uudnyttet
B39: Ekstra pensionsfradrag | C39: =IF(C5<=52,MIN(+(C3+C4+C22*3)*EPENfradragProc,EPENfradragMax),MIN(+(C3+C4+C22*3)*EPENSeniorProc,EPENSeniorMax)) -> 0 | D39: =IF(D5<=52,MIN(+(D3+D4+D22*3)*EPENfradragProc,EPENfradragMax),MIN(+(D3+D4+D22*3)*EPENSeniorProc,EPENSeniorMax)) -> 0 | AB39: fradrag
B40: Fagforening, A-kasse og efterløn | C40: =IF(C7>FagforeningMax,FagforeningMax,C7)+C8 -> 6000 | D40: =IF(D7>FagforeningMax,FagforeningMax,D7)+D8 -> 0 | AB40: person 2
B41: Befordring | C41: =+$H$56 -> 0 | D41: =H65 -> 0 | AB41: =IF(D77>H5,0,H5-D77) -> 51600
B42: Andre ligningsmæssige fradrag | C42: 0 | D42: 0
B43: - Ligningsmæssige fradrag i alt | C43: =SUM(C37:C42) -> 6405.9 | D43: =SUM(D37:D42) -> 0 | AB43: =IF($D$45<0,H7,IF($D$45>H7,0,H7-$D$45)) -> 51600
AB44: =IF($D$45<0,H8,IF($D$45>H8,0,H8-$D$45)) -> 51600
B45: = Skattepligtig indkomst (SI) | C45: =+C31+C35-C43 -> -3369.9 | D45: =+D31+D35-D43 -> 0 | AB45: =IF($D$45<0,H9,IF($D$45>H9,0,H9-$D$45)) -> 51600
B50: BEREGNINGSOMRÅDE (INDTAST IKKE NOGET)
B52: Person1
C53: sats | D53: dage | E53: km/dag | F53: min. | G53: frad./dag | H53: fradrag i alt
B54: Befordring for km under standardgrænse | C54: =BeFradragHojSats -> 2.23 | D54: =C10 -> 216 | E54: =C9 -> 1 | F54: =BeFradragKmMin -> 24 | G54: =IF(E54>F54,MIN(E54,BeFradragKmMax)-F54,0) -> 0 | H54: =+(D54*G54)*C54 -> 0
B55: Befordring for km over standardgrænse | C55: =BeFradragLavSats -> 1.12 | D55: =C10 -> 216 | E55: =MAX(E54-BeFradragKmMax,0) -> 0 | G55: =MAX(E55,0) -> 0 | H55: =+(D55*G55)*C55 -> 0
B56: Samlet befordringsfradrag | H56: =SUM(H54:H55) -> 0
B58: Evt. forhøjelser skal laves manuelt
B61: Person2
C62: sats | D62: dage | E62: km/dag | F62: min. | G62: frad./dag | H62: fradrag i alt
B63: Befordring for km under standardgrænse | C63: =C54 -> 2.23 | D63: =D10 -> 0 | E63: =D9 -> 0 | F63: =BeFradragKmMin -> 24 | G63: =IF(E63>F63,MIN(E63,BeFradragKmMax)-F63,0) -> 0 | H63: =+(D63*G63)*C63 -> 0
B64: Befordring for km over standardgrænse | C64: =C55 -> 1.12 | D64: =D10 -> 0 | E64: =MAX(E63-BeFradragKmMax,0) -> 0 | G64: =MAX(E64,0) -> 0 | H64: =+(D64*G64)*C64 -> 0
B65: Samlet befordringsfradrag | H65: =SUM(H63:H64) -> 0
B67: Evt. forhøjelser skal laves manuelt
B70: Ejendomsskatter | C70: Sats | D70: Høj sats | E70: Ejendomsværdi | F70: I alt
B71: Ejendomsværdiskat | C71: =EjVSkatMin -> 0.0051 | D71: =EjVSkatMax-C71 -> 0.0089 | E71: =C16 -> 0 | F71: =IF(E71<Skattesatser!H14,C71*E71*Forsigtighed,C71*E71*Forsigtighed+(E71-Skattesatser!H14)*D71*Forsigtighed) -> 0
B72: Grundskyld | C72: =C15 -> 0.006 | E72: =C17 -> 0 | F72: =E72*C72*Forsigtighed -> 0
B75: Mellemregninger | C75: Person 1 | D75: Person 2
B76: Værdi af personlig indkomst | C76: =+C31 -> 3036 | D76: =+D31 -> 0
B77: Værdi af personlig indkomst plus positiv kapitalindkomst | C77: =MAX(C35+C31,C31) -> 3036 | D77: =MAX(D35+D31,D31) -> 0
B78: Værdi af PI plus KI > min grænse | C78: =C76+C80 -> 3036
B79: Positiv kapitalindkomst | C79: =MAX(C35,0) -> 0 | D79: =D35 -> 0
B80: Positiv kapitalindkomst over fælles min grænse | C80: =IF((C35+D35)>KItilTopskatPar,C79+D79-KItilTopskatPar,0) -> 0
B81: Sum af skatteprocenter | C81: =SUM(G5:G8) -> 0.5153 | D81: =SUM(G5:G8) -> 0.5153
B82: Topskatteberegningsgrundlag | C82: =IF(C78>TopSkatGranse,C78-TopSkatGranse,0) -> 0 | D82: =IF(D76>Skattesatser!H35,D76-Skattesatser!H35,0) -> 0
B83: - andel som vedrører lønindkomst | C83: =IF(C76>TopSkatGranse,C76-TopSkatGranse,0) -> 0 | D83: =IF(D76>TopSkatGranse,D76-TopSkatGranse,0) -> 0
B84: - andel som vedrører kapitalindkomst | C84: =C82-C83 -> 0

Sheet Budget før boligkøb
A1: Privatbudget - Par
A3: Indtægter | B3: jan | C3: feb | D3: mar | E3: apr | F3: maj | G3: juni | H3: juli | I3: aug | J3: sept | K3: okt | L3: nov | M3: dec | N3: TOTAL
A4: Løn, efter skat | B4: 25342.574 | C4: =B4 -> 25342.574 | D4: =C4 -> 25342.574 | E4: =D4 -> 25342.574 | F4: =E4 -> 25342.574 | G4: =F4 -> 25342.574 | H4: =G4 -> 25342.574 | I4: =H4 -> 25342.574 | J4: =I4 -> 25342.574 | ... M4: =L4 -> 25342.574 | N4: =SUM(B4:M4) -> 304110.88
A5: Løn, efter skat | B5: ='Ægtepar skat før boligkøb'!L31 -> 0 | C5: =B5 -> 0 | D5: =C5 -> 0 | E5: =D5 -> 0 | F5: =E5 -> 0 | G5: =F5 -> 0 | H5: =G5 -> 0 | I5: =H5 -> 0 | J5: =I5 -> 0 | ... M5: =L5 -> 0 | N5: =SUM(B5:M5) -> 0
A6: Renter/udbytte | B6: 10000 | C6: 0 | D6: 0 | E6: 0 | F6: 0 | G6: 0 | H6: 0 | I6: 0 | J6: 0 | K6: 0 | L6: 0 | M6: 0 | N6: =SUM(B6:M6) -> 10000
A7: Børne- og ungeydelse | B7: 0 | C7: 0 | D7: 0 | E7: =B7 -> 0 | F7: 0 | G7: 0 | H7: =E7 -> 0 | I7: 0 | J7: 0 | K7: =H7 -> 0 | L7: 0 | M7: 0 | N7: =SUM(B7:M7) -> 0
A8: Børnebidrag | B8: 0 | C8: 0 | D8: 0 | E8: 0 | F8: 0 | G8: 0 | H8: 0 | I8: 0 | J8: 0 | K8: 0 | L8: 0 | M8: 0 | N8: =SUM(B8:M8) -> 0
A9: Børnetilskud | B9: 0 | C9: 0 | D9: 0 | E9: 0 | F9: 0 | G9: 0 | H9: 0 | I9: 0 | J9: 0 | K9: 0 | L9: 0 | M9: 0 | N9: =SUM(B9:M9) -> 0
A10: Indtægter i alt | B10: =SUM(B4:B9) -> 35342.574 | C10: =SUM(C4:C9) -> 25342.574 | D10: =SUM(D4:D9) -> 25342.574 | E10: =SUM(E4:E9) -> 25342.574 | F10: =SUM(F4:F9) -> 25342.574 | G10: =SUM(G4:G9) -> 25342.574 | H10: =SUM(H4:H9) -> 25342.574 | I10: =SUM(I4:I9) -> 25342.574 | ... M10: =SUM(M4:M9) -> 25342.574 | N10: =SUM(B10:M10) -> 314110.88
A13: Udgifter | B13: jan | C13: feb | D13: mar | E13: apr | F13: maj | G13: juni | H13: juli | I13: aug | J13: sept | K13: okt | L13: nov | M13: dec | N13: TOTAL
A14: Bolig
A15: Husleje | B15: 0 | C15: =B15 -> 0 | D15: =C15 -> 0 | E15: =D15 -> 0 | F15: =E15 -> 0 | G15: =F15 -> 0 | H15: =G15 -> 0 | I15: =H15 -> 0 | J15: =I15 -> 0 | ... M15: =L15 -> 0 | N15: =SUM(B15:M15) -> 0
A16: Banklån, ydelse efter skat | B16: 0 | C16: =B16 -> 0 | D16: =C16 -> 0 | E16: =D16 -> 0 | F16: =E16 -> 0 | G16: =F16 -> 0 | H16: =G16 -> 0 | I16: =H16 -> 0 | J16: =I16 -> 0 | ... M16: =L16 -> 0 | N16: =SUM(B16:M16) -> 0
A17: Renovation | B17: 0 | C17: 0 | D17: 0 | E17: 0 | F17: 0 | G17: 0 | H17: 0 | I17: 0 | J17: 0 | K17: 0 | L17: 0 | M17: 0 | N17: =SUM(B17:M17) -> 0
A18: Varme | B18: 0 | C18: 0 | D18: 0 | E18: 0 | F18: 0 | G18: 0 | H18: 0 | I18: 0 | J18: 0 | K18: 0 | L18: 0 | M18: 0 | N18: =SUM(B18:M18) -> 0
A19: Elektricitet | B19: 0 | C19: 0 | D19: 0 | F19: 0 | G19: 0 | I19: 0 | J19: 0 | L19: 0 | M19: 0 | N19: =SUM(B19:M19) -> 0
A20: Vand | B20: 0 | C20: 0 | D20: 0 | E20: 0 | F20: 0 | G20: 0 | H20: 0 | I20: 0 | J20: 0 | K20: 0 | L20: 0 | M20: 0 | N20: =SUM(B20:M20) -> 0
A21: Ejendomsskatter | B21: 0 | C21: 0 | D21: 0 | E21: 0 | F21: 0 | G21: 0 | H21: 0 | I21: 0 | J21: 0 | K21: 0 | L21: 0 | M21: 0 | N21: =SUM(B21:M21) -> 0
A22: Fællesudgifter | B22: 0 | C22: =B22 -> 0 | D22: =C22 -> 0 | E22: =D22 -> 0 | F22: =E22 -> 0 | G22: =F22 -> 0 | H22: =G22 -> 0 | I22: =H22 -> 0 | J22: =I22 -> 0 | ... M22: =L22 -> 0 | N22: =SUM(B22:M22) -> 0
A23: Grundejerforening | B23: 0 | C23: 0 | D23: 0 | E23: 0 | F23: 0 | G23: 0 | H23: 0 | I23: 0 | J23: 0 | K23: 0 | L23: 0 | M23: 0 | N23: =SUM(B23:M23) -> 0
A24: Vedligeholdelse | B24: 0 | C24: 0 | D24: 0 | E24: 0 | F24: 0 | G24: 0 | H24: 0 | I24: 0 | J24: 0 | K24: 0 | L24: 0 | M24: 0 | N24: =SUM(B24:M24) -> 0
A25: Hus forsikring | B25: 0 | C25: 0 | D25: 0 | E25: 0 | F25: 0 | G25: 0 | H25: 0 | I25: 0 | J25: 0 | K25: 0 | L25: 0 | M25: 0 | N25: =SUM(B25:M25) -> 0
A26: Diverse | B26: 0 | C26: 0 | D26: 0 | E26: 0 | F26: 0 | G26: 0 | H26: 0 | I26: 0 | J26: 0 | K26: 0 | L26: 0 | M26: 0 | N26: =SUM(B26:M26) -> 0
A27: Bolig i alt | B27: =SUM(B15:B26) -> 0 | C27: =SUM(C15:C26) -> 0 | D27: =SUM(D15:D26) -> 0 | E27: =SUM(E15:E26) -> 0 | F27: =SUM(F15:F26) -> 0 | G27: =SUM(G15:G26) -> 0 | H27: =SUM(H15:H26) -> 0 | I27: =SUM(I15:I26) -> 0 | ... N27: =SUM(N15:N26) -> 0
A29: Bil
A30: Forsikring | B30: 0 | C30: 0 | D30: 0 | E30: 0 | F30: 0 | G30: 0 | H30: 0 | I30: 0 | J30: 0 | K30: 0 | L30: 0 | M30: 0 | N30: =SUM(B30:M30) -> 0
A31: Vægtafgift | B31: 0 | C31: 0 | D31: 0 | E31: 0 | F31: 0 | G31: 0 | H31: 0 | I31: 0 | J31: 0 | K31: 0 | L31: 0 | M31: 0 | N31: =SUM(B31:M31) -> 0
A32: Benzin | B32: 0 | C32: =B32 -> 0 | D32: =C32 -> 0 | E32: =D32 -> 0 | F32: =E32 -> 0 | G32: =F32 -> 0 | H32: =G32 -> 0 | I32: =H32 -> 0 | J32: =I32 -> 0 | ... M32: =L32 -> 0 | N32: =SUM(B32:M32) -> 0
A33: FDM | B33: 0 | C33: 0 | D33: 0 | E33: 0 | F33: 0 | G33: 0 | H33: 0 | I33: 0 | J33: 0 | K33: 0 | L33: 0 | M33: 0 | N33: =SUM(B33:M33) -> 0
A34: Billån | B34: 0 | C34: =B34 -> 0 | D34: =C34 -> 0 | E34: =D34 -> 0 | F34: =E34 -> 0 | G34: =F34 -> 0 | H34: =G34 -> 0 | I34: =H34 -> 0 | J34: =I34 -> 0 | ... M34: =L34 -> 0 | N34: =SUM(B34:M34) -> 0
A35: Vedligehold/reparation | B35: 0 | C35: 0 | D35: 0 | E35: 0 | F35: 0 | G35: 0 | H35: 0 | I35: 0 | J35: 0 | K35: 0 | L35: 0 | M35: 0 | N35: =SUM(B35:M35) -> 0
A36: Biludgifter i alt | B36: =SUM(B30:B35) -> 0 | C36: =SUM(C30:C35) -> 0 | D36: =SUM(D30:D35) -> 0 | E36: =SUM(E30:E35) -> 0 | F36: =SUM(F30:F35) -> 0 | G36: =SUM(G30:G35) -> 0 | H36: =SUM(H30:H35) -> 0 | I36: =SUM(I30:I35) -> 0 | ... M36: =SUM(M30:M35) -> 0 | N36: =SUM(B36:M36) -> 0
A38: Transport øvrig
A39: Offentlig transport | B39: 0 | C39: =B39 -> 0 | D39: =C39 -> 0 | E39: =D39 -> 0 | F39: =E39 -> 0 | G39: =F39 -> 0 | H39: =G39 -> 0 | I39: =H39 -> 0 | J39: =I39 -> 0 | ... M39: =L39 -> 0 | N39: =SUM(B39:M39) -> 0
A40: Diverse | B40: 0 | C40: 0 | D40: 0 | E40: 0 | F40: 0 | G40: 0 | H40: 0 | I40: 0 | J40: 0 | K40: 0 | L40: 0 | M40: 0 | N40: =SUM(B40:M40) -> 0
A41: Transport i alt | B41: =SUM(B39:B40) -> 0 | C41: =SUM(C39:C40) -> 0 | D41: =SUM(D39:D40) -> 0 | E41: =SUM(E39:E40) -> 0 | F41: =SUM(F39:F40) -> 0 | G41: =SUM(G39:G40) -> 0 | H41: =SUM(H39:H40) -> 0 | I41: =SUM(I39:I40) -> 0 | ... M41: =SUM(M39:M40) -> 0 | N41: =SUM(B41:M41) -> 0
A43: Kommunikation/TV
A44: Fastnettelefon | B44: 0 | C44: =B44 -> 0 | D44: =C44 -> 0 | E44: =D44 -> 0 | F44: =E44 -> 0 | G44: =F44 -> 0 | H44: =G44 -> 0 | I44: =H44 -> 0 | J44: =I44 -> 0 | ... M44: =L44 -> 0 | N44: =SUM(B44:M44) -> 0
A45: Mobiltelefon | B45: 0 | C45: =B45 -> 0 | D45: =C45 -> 0 | E45: =D45 -> 0 | F45: =E45 -> 0 | G45: =F45 -> 0 | H45: =G45 -> 0 | I45: =H45 -> 0 | J45: =I45 -> 0 | ... M45: =L45 -> 0 | N45: =SUM(B45:M45) -> 0
A46: Internet | B46: 0 | C46: =B46 -> 0 | D46: =C46 -> 0 | E46: =D46 -> 0 | F46: =E46 -> 0 | G46: =F46 -> 0 | H46: =G46 -> 0 | I46: =H46 -> 0 | J46: =I46 -> 0 | ... M46: =L46 -> 0 | N46: =SUM(B46:M46) -> 0
A47: Hybridnet/kabel-TV | B47: 0 | C47: =B47 -> 0 | D47: =C47 -> 0 | E47: =D47 -> 0 | F47: =E47 -> 0 | G47: =F47 -> 0 | H47: =G47 -> 0 | I47: =H47 -> 0 | J47: =I47 -> 0 | ... M47: =L47 -> 0 | N47: =SUM(B47:M47) -> 0
A48: Diverse | B48: 0 | C48: 0 | D48: 0 | E48: 0 | F48: 0 | G48: 0 | H48: 0 | I48: 0 | J48: 0 | K48: 0 | L48: 0 | M48: 0 | N48: =SUM(B48:M48) -> 0
A49: Kommun./TV i alt | B49: =SUM(B44:B48) -> 0 | C49: =SUM(C44:C48) -> 0 | D49: =SUM(D44:D48) -> 0 | E49: =SUM(E44:E48) -> 0 | F49: =SUM(F44:F48) -> 0 | G49: =SUM(G44:G48) -> 0 | H49: =SUM(H44:H48) -> 0 | I49: =SUM(I44:I48) -> 0 | ... N49: =SUM(N44:N48) -> 0
A51: Forsikringer
A52: A-kasse | B52: 0 | C52: =B52 -> 0 | D52: =C52 -> 0 | E52: =D52 -> 0 | F52: =E52 -> 0 | G52: =F52 -> 0 | H52: =G52 -> 0 | I52: =H52 -> 0 | J52: =I52 -> 0 | ... M52: =L52 -> 0 | N52: =SUM(B52:M52) -> 0
A53: A-kasse | B53: 0 | C53: =B53 -> 0 | D53: =C53 -> 0 | E53: =D53 -> 0 | F53: =E53 -> 0 | G53: =F53 -> 0 | H53: =G53 -> 0 | I53: =H53 -> 0 | J53: =I53 -> 0 | ... M53: =L53 -> 0 | N53: =SUM(B53:M53) -> 0
A54: Fagforening | B54: 0 | C54: =B54 -> 0 | D54: =C54 -> 0 | E54: =D54 -> 0 | F54: =E54 -> 0 | G54: =F54 -> 0 | H54: =G54 -> 0 | I54: =H54 -> 0 | J54: =I54 -> 0 | ... M54: =L54 -> 0 | N54: =SUM(B54:M54) -> 0
A55: Fagforening | B55: 0 | C55: =B55 -> 0 | D55: =C55 -> 0 | E55: =D55 -> 0 | F55: =E55 -> 0 | G55: =F55 -> 0 | H55: =G55 -> 0 | I55: =H55 -> 0 | J55: =I55 -> 0 | ... M55: =L55 -> 0 | N55: =SUM(B55:M55) -> 0
A56: Familieforsikring | B56: 0 | C56: =B56 -> 0 | D56: =C56 -> 0 | E56: =D56 -> 0 | F56: =E56 -> 0 | G56: =F56 -> 0 | H56: =G56 -> 0 | I56: =H56 -> 0 | J56: =I56 -> 0 | ... M56: =L56 -> 0 | N56: =SUM(B56:M56) -> 0
A57: Ulykkesforsikring | B57: 0 | C57: 0 | D57: 0 | E57: 0 | F57: 0 | G57: 0 | H57: 0 | I57: 0 | J57: 0 | K57: 0 | L57: 0 | M57: 0 | N57: =SUM(B57:M57) -> 0
A58: Sygeforsikring Danmark | B58: 0 | C58: 0 | D58: 0 | E58: 0 | F58: 0 | G58: 0 | H58: 0 | I58: 0 | J58: 0 | K58: 0 | L58: 0 | M58: 0 | N58: =SUM(B58:M58) -> 0
A59: Receptpligtig medecin | B59: 0 | C59: =B59 -> 0 | D59: =C59 -> 0 | E59: =D59 -> 0 | F59: =E59 -> 0 | G59: =F59 -> 0 | H59: =G59 -> 0 | I59: =H59 -> 0 | J59: =I59 -> 0 | ... M59: =L59 -> 0 | N59: =SUM(B59:M59) -> 0
A60: Diverse | B60: 0 | C60: 0 | D60: 0 | E60: 0 | F60: 0 | G60: 0 | H60: 0 | I60: 0 | J60: 0 | K60: 0 | L60: 0 | M60: 0 | N60: =SUM(B60:M60) -> 0
A61: Forsikringer i alt | B61: =SUM(B52:B60) -> 0 | C61: =SUM(C52:C60) -> 0 | D61: =SUM(D52:D60) -> 0 | E61: =SUM(E52:E60) -> 0 | F61: =SUM(F52:F60) -> 0 | G61: =SUM(G52:G60) -> 0 | H61: =SUM(H52:H60) -> 0 | I61: =SUM(I52:I60) -> 0 | ... N61: =SUM(N52:N60) -> 0
A63: Børneudgifter
A64: SFO | B64: 0 | C64: =B64 -> 0 | D64: =C64 -> 0 | E64: =D64 -> 0 | F64: =E64 -> 0 | G64: =F64 -> 0 | H64: =G64 -> 0 | I64: =H64 -> 0 | J64: =I64 -> 0 | ... M64: =L64 -> 0 | N64: =SUM(B64:M64) -> 0
A65: Vuggestue/børnehave | B65: 0 | C65: =B65 -> 0 | D65: =C65 -> 0 | E65: =D65 -> 0 | F65: =E65 -> 0 | G65: =F65 -> 0 | H65: =G65 -> 0 | I65: =H65 -> 0 | J65: =I65 -> 0 | ... M65: =L65 -> 0 | N65: =SUM(B65:M65) -> 0
A66: Transport | B66: 0 | C66: =B66 -> 0 | D66: =C66 -> 0 | E66: =D66 -> 0 | F66: =E66 -> 0 | G66: =F66 -> 0 | H66: =G66 -> 0 | I66: =H66 -> 0 | J66: =I66 -> 0 | ... M66: =L66 -> 0 | N66: =SUM(B66:M66) -> 0
A67: Skoleudgifter | B67: 0 | C67: 0 | D67: 0 | E67: 0 | F67: 0 | G67: 0 | H67: 0 | I67: 0 | J67: 0 | K67: 0 | L67: 0 | M67: 0 | N67: =SUM(B67:M67) -> 0
A68: Diverse | B68: 0 | C68: =B68 -> 0 | D68: =C68 -> 0 | E68: =D68 -> 0 | F68: =E68 -> 0 | G68: =F68 -> 0 | H68: =G68 -> 0 | I68: =H68 -> 0 | J68: =I68 -> 0 | ... M68: =L68 -> 0 | N68: =SUM(B68:M68) -> 0
A69: Børneudgifter i alt | B69: =SUM(B64:B68) -> 0 | C69: =SUM(C64:C68) -> 0 | D69: =SUM(D64:D68) -> 0 | E69: =SUM(E64:E68) -> 0 | F69: =SUM(F64:F68) -> 0 | G69: =SUM(G64:G68) -> 0 | H69: =SUM(H64:H68) -> 0 | I69: =SUM(I64:I68) -> 0 | ... N69: =SUM(N64:N68) -> 0
A71: Gældsforpligtelser
A72: [indsæt kreditor) | B72: 0 | C72: 0 | D72: 0 | E72: 0 | F72: 0 | G72: 0 | H72: 0 | I72: 0 | J72: 0 | K72: 0 | L72: 0 | M72: 0 | N72: =SUM(B72:M72) -> 0
A73: [indsæt kreditor) | B73: 0 | C73: 0 | D73: 0 | E73: 0 | F73: 0 | G73: 0 | H73: 0 | I73: 0 | J73: 0 | K73: 0 | L73: 0 | M73: 0 | N73: =SUM(B73:M73) -> 0
A74: Forpligtelser i alt | B74: =SUM(B72:B73) -> 0 | C74: =SUM(C72:C73) -> 0 | D74: =SUM(D72:D73) -> 0 | E74: =SUM(E72:E73) -> 0 | F74: =SUM(F72:F73) -> 0 | G74: =SUM(G72:G73) -> 0 | H74: =SUM(H72:H73) -> 0 | I74: =SUM(I72:I73) -> 0 | ... N74: =SUM(N72:N73) -> 0
A76: Diverse
A77: Andet | B77: 0 | C77: =B77 -> 0 | D77: =C77 -> 0 | E77: =D77 -> 0 | F77: =E77 -> 0 | G77: =F77 -> 0 | H77: =G77 -> 0 | I77: =H77 -> 0 | J77: =I77 -> 0 | ... M77: =L77 -> 0 | N77: =SUM(B77:M77) -> 0
A78: Andet | B78: 0 | C78: 0 | D78: 0 | E78: 0 | F78: 0 | G78: 0 | H78: 0 | I78: 0 | J78: 0 | K78: 0 | L78: 0 | M78: 0 | N78: =SUM(B78:M78) -> 0
A79: Andet | B79: 0 | C79: 0 | D79: 0 | E79: 0 | F79: 0 | G79: 0 | H79: 0 | I79: 0 | J79: 0 | K79: 0 | L79: 0 | M79: 0 | N79: =SUM(B79:M79) -> 0
A80: Diverse i alt | B80: =SUM(B77:B79) -> 0 | C80: =SUM(C77:C79) -> 0 | D80: =SUM(D77:D79) -> 0 | E80: =SUM(E77:E79) -> 0 | F80: =SUM(F77:F79) -> 0 | G80: =SUM(G77:G79) -> 0 | H80: =SUM(H77:H79) -> 0 | I80: =SUM(I77:I79) -> 0 | ... N80: =SUM(N77:N79) -> 0
A82: Udgifter i alt | B82: =B27+B36+B41+B49+B61+B69+B74+B80 -> 0 | C82: =C27+C36+C41+C49+C61+C69+C74+C80 -> 0 | D82: =D27+D36+D41+D49+D61+D69+D74+D80 -> 0 | E82: =E27+E36+E41+E49+E61+E69+E74+E80 -> 0 | F82: =F27+F36+F41+F49+F61+F69+F74+F80 -> 0 | G82: =G27+G36+G41+G49+G61+G69+G74+G80 -> 0 | H82: =H27+H36+H41+H49+H61+H69+H74+H80 -> 0 | I82: =I27+I36+I41+I49+I61+I69+I74+I80 -> 0 | ... N82: =N27+N36+N41+N49+N61+N69+N74+N80 -> 0
A85: Oversigt | B85: =B3 -> jan | C85: =C3 -> feb | D85: =D3 -> mar | E85: =E3 -> apr | F85: =F3 -> maj | G85: =G3 -> juni | H85: =H3 -> juli | I85: =I3 -> aug | ... N85: =N3 -> TOTAL
A86: Overskud/underskud | B86: =SUM(B10-B82) -> 35342.574 | C86: =SUM(C10-C82) -> 25342.574 | D86: =SUM(D10-D82) -> 25342.574 | E86: =SUM(E10-E82) -> 25342.574 | F86: =SUM(F10-F82) -> 25342.574 | G86: =SUM(G10-G82) -> 25342.574 | H86: =SUM(H10-H82) -> 25342.574 | I86: =SUM(I10-I82) -> 25342.574 | ... N86: =SUM(N10-N82) -> 314110.88
A87: Årligt rådighedsbeløb | N87: =N86 -> 314110.88
A88: Månedligt rådighedsbeløb | B88: =B86 -> 35342.574 | C88: =C86 -> 25342.574 | D88: =D86 -> 25342.574 | E88: =E86 -> 25342.574 | F88: =F86 -> 25342.574 | G88: =G86 -> 25342.574 | H88: =H86 -> 25342.574 | I88: =I86 -> 25342.574 | ... M88: =M86 -> 25342.574 | N88: =N87/12 -> 26175.907

Sheet Skattesatser
B3: Kommuneskattesatser 2025 | G3: Arbejdsmarkedsbidrag | H3: 0.08
G4: Befordringsfradrag høje sats | H4: 2.23
B5: Kommunenavn | C5: Kommune | D5: Kirke | E5: Grundskyld (promille) | G5: Befordringsfradrag min km for høj sats | H5: 24
B6: Albertslund | C6: 25.6 | D6: 0.8 | E6: 9.1 | G6: Befordringsfradrag max km for høj sats | H6: 120
B7: Allerød | C7: 25.3 | D7: 0.58 | E7: 8 | G7: Befordringsfradrag lave sats | H7: 1.12
B8: Assens | C8: 26.1 | D8: 0.98 | E8: 11.2 | G8: Befordringsfradrag Indtægtsgrænse for forhøjet (før AM-bidrag) | H8: 325800
B9: Ballerup | C9: 25.5 | D9: 0.75 | E9: 8.3 | G9: Beskæftigelsesfradrag (%) | H9: 0.123
B10: Billund | C10: 24 | D10: 0.89 | E10: 7.2 | G10: Beskæftigelsesfradrag (max) | H10: 55600
B11: Bornholm | C11: 26.2 | D11: 0 | E11: 10.7 | G11: Bundskat | H11: 0.1201
B12: Brøndby | C12: 24.3 | D12: 0.8 | E12: 4.9 | G12: Ejendomsværdiskat - lave sats | H12: 0.0051
B13: Brønderslev | C13: 26.3 | D13: 1.06 | E13: 17.1 | G13: Ejendomsværdiskat - høje sats | H13: 0.014
B14: Dragør | C14: 24.8 | D14: 0.61 | E14: 8.1 | G14: Ejendomsværdiskat - skillegrænse | H14: 11500000
B15: Egedal | C15: 25.7 | D15: 0.76 | E15: 8.8 | G15: Ekstra pensionsfradrag (%) | H15: 0.12
B16: Esbjerg | C16: 26.1 | D16: 0.81 | E16: 9.9 | G16: Ekstra pensionsfradrag (max) | H16: 10056
B17: Fanø | C17: 26.1 | D17: 1.05 | E17: 8.5 | G17: Ekstra pensionsfradrag (%) Senior | H17: 0.32
... B25: Furesø | C25: 24.88 | D25: 0.96 | E25: 12 | G25: Grøn check | H25: 0
B26: Faaborg-Midtfyn | C26: 26.1 | D26: 0.65 | E26: 7 | G26: Grøn check modregning Start
B27: Gentofte | C27: 24.24 | D27: 0.39 | E27: 5.1 | G27: Grøn check modregning Slut
B28: Gladsaxe | C28: 23.6 | D28: 0.75 | E28: 5.9 | G28: Grøn check modregning Sats
B29: Glostrup | C29: 24.6 | D29: 0.8 | E29: 6.5 | G29: Jobfradrag (%) | H29: 0.045
B30: Greve | C30: 24.59 | D30: 0.81 | E30: 5.5 | G30: Jobfradraggrænse | H30: 224500
B31: Gribskov | C31: 25.4 | D31: 0.85 | E31: 11.1 | G31: Jobfradrag (max) | H31: 2900
B32: Guldborgsund | C32: 25.8 | D32: 1.16 | E32: 15.9 | G32: Kapitalindkomstgrænse til Topskat Par | H32: 104800
B33: Haderslev | C33: 26.3 | D33: 0.95 | E33: 12.7 | G33: Kapitalindkomstgrænse til Topskat Enlig | H33: 52400
B34: Halsnæs | C34: 25.7 | D34: 0.85 | E34: 10.9 | G34: Personfradrag | H34: 51600
B35: Hedensted | C35: 25.52 | D35: 0.98 | E35: 7.9 | G35: Personfradrag topskat | H35: 611800
B36: Helsingør | C36: 25.82 | D36: 0.63 | E36: 9.5 | G36: Ratepension Max indskud | H36: 65500
B37: Herlev | C37: 23.7 | D37: 0.75 | E37: 5.4 | G37: Skrå Skatteloft - personlig indkomst | H37: 0.5207
B38: Herning | C38: 25.4 | D38: 0.99 | E38: 9.9 | G38: Skrå Skatteloft - kapitalindkomst | H38: 0.42
B39: Hillerød | C39: 25.6 | D39: 0.69 | E39: 6.6 | G39: Sundhedsbidrag | H39: 0
B40: Hjørring | C40: 26.21 | D40: 1.19 | E40: 16.5 | G40: Tillæg for negativ kapitalindkomst procent | H40: 0.08
... B43: Horsens | C43: 25.69 | D43: 0.79 | E43: 8.7 | G43: Topskat | H43: 0.15
B44: Hvidovre | C44: 25.4 | D44: 0.72 | E44: 6.5
B45: Høje-Taastrup | C45: 24.6 | D45: 0.8 | E45: 6.3
B46: Hørsholm | C46: 23.7 | D46: 0.62 | E46: 8.5
B47: Ikast-Brande | C47: 25.1 | D47: 0.97 | E47: 9.1
B48: Ishøj | C48: 25 | D48: 0.9 | E48: 6.5
B49: Jammerbugt | C49: 25.7 | D49: 1.2 | E49: 13.2
B50: Kalundborg | C50: 24.2 | D50: 1.01 | E50: 16.6
B51: Kerteminde | C51: 26.1 | D51: 0.98 | E51: 12.4
B52: Kolding | C52: 25.5 | D52: 0.92 | E52: 11.1
B53: København | C53: 23.5 | D53: 0.8 | E53: 5.1
B54: Køge | C54: 25.26 | D54: 0.87 | E54: 5.3
B55: Langeland | C55: 26.3 | D55: 1.14 | E55: 12.2
... B103: Aarhus | C103: 24.52 | D103: 0.74 | E103: 6

Sheet Hvordan finansieres boligen
A2: Hvordan skal boligen finansieres? | G2: Hvordan anvendes pengene?
A5: Kontantpris på boligen | D5: kr. | E5: 6995000 | G5: Sælger skal have | J5: kr. | K5: =E5 -> 6995000
G7: Hvor kommer pengene fra:
A8: Realkreditlån, maks. 80% | D8: kr. | E8: 3000000 | F8: 0.8
A9: Hvad kommer kunden med | D9: kr. | E9: 500000 | G9: Provenu fra realkreditlån | J9: kr. | K9: ='Realkredit finansiering'!E7 -> 2937329.6 | L9: Tinglysning - Låneomkostninger, realkredit er trukket fra
A10: - op af "lommen penge": | G10: Provenu fra banklån | J10: kr. | K10: =IF(K18>0,Banklån!D16,0) -> 0 | L10: Tinglysning - Låneomkostninger, banklån er trukket fra
B11: Skøde | E11: =0.6%*E5+1850 -> 43820 | G11: Egne midler | J11: kr. | K11: =E15 -> 424430
B12: Advokat, anslået | E12: 5000
B13: Halv ejerskifteforsikring | E13: 6750 | G13: I alt | J13: kr. | K13: =K9+K10+K11 -> 3361759.6
B14: Flytteomkostninger/renovering og andet | E14: 20000
A15: Egen udbetaling, min. 5% | E15: =E9-E11-E12-E13-E14 -> 424430 | F15: =E15/E5 -> 0.060676197
G16: Mangler | J16: kr. | K16: =K13-K5 -> -3633240.4 | L16: Skal altid være 0
A17: Restfinansiering (minus = overskud) | D17: kr. | E17: =E5-E8-E15 -> 3570570 | F17: =E17/E5 -> 0.51044603
F18: =F8+F15+F17 -> 1.3711222 | G18: Banklån inkl. omkostninger | K18: 0
A20: Låneomkostninger
A22: Tinglysning - Låneomkostninger, realkredit | D22: kr. | E22: ='Realkredit finansiering'!B9 -> 62670.361
A23: Tinglysning - Låneomkostninger, banklån | D23: kr. | E23: =IF(K18>0,Banklån!D14,0) -> 0
A25: Låneomkostninger i alt | E25: =E22+E23 -> 62670.361
A28: Fremgangsmåde:
A30: 1) Start altid med at udfylde rente og kurs i fanebladet "Realkreditfinansiering" og rente i "Banklån"
A31: 2) Slet altid E8 og K18 inden start
A32: 2) Indtast boligens kontantpris (E5)
A33: 3) Indtast hvor mange penge kunden kommer med (E9)
A34: 4) Indtast ejerskifteforsikring (E13) og flytteomkostninger m.m. (E14)
A38: Er restfinansiering (E17) nu under 80%: | H38: Er restfinansiering (E17) nu over 80%:
A39: 1) Indtast realkreditlånet (E8) med det beløb som fremgår af E17 | H39: 1) Indtast realkreditlånet (E8) som 80% af kontantprisen
A40: 2) Lav en målsøgning så "Mangler" (K16) bliver 0 ved ændring af celle E8 | H40: 2) Lav en målsøgning så "Mangler" (K16) bliver 0 ved ændring af celle K18
A44: Hvis realkreditlånet (E8) bliver mere end 80%:
A45: 1) Gå til "Er restfinansiering (E17) nu over 80%"

Sheet Banklån
D4: Banklån til finasiering af boligen
B6: Lånets størrelse (hovedstol) | D6: ='Hvordan finansieres boligen'!K18 -> 0 | E6: jf. ark "Hvordan finansieres huset…"
B7: Løbetid,år | D7: 30 | E7: en bolig kan godt finansieres over 30 år
B8: Antal terminer pr år | D8: 12
B9: Rente pr år | D9: 0.05 | E9: (tjek rentesatsen på bankernes hjemmesider under bank boliglån - det er ikke et realkreditlån)
B11: Etableringsomkostninger:
B12: Tinglysning af pant | D12: =1825+1.45%*D6 -> 1825
B13: Bankens etableringsomk. | D13: 5690 | E13: (nordea's dokumentgebyr og vurderingsgebyr)
B14: Etableringsomkostninger i alt | D14: =D12+D13 -> 7515
B16: Provenu (hvad får jeg i hånden) | D16: =D6-D14 -> -7515
B19: Ydelse pr termin før skat | D19: =PMT(D9/D8,D7*D8,D6) -> 0
B20: Renteudgifter år 1 | D20: =-CUMIPMT(D9/D8,D8*D7,D6,1,D8,0) -> #NUM!
B21: Skattefar betaler 1/3 af renteudgifterne | D21: =1/3*D20 -> #NUM!
B22: Ydelse pr. termin efter skat | D22: =D19+(D21/D8) -> #NUM! | E22: = Den der anvendes i budgettet, medmindre du skriver renteudgiften ind i skattebegningen
B24: Omkostninger i procent pr termin | D24: =RATE(D7*D8,D19,D16) -> #NUM!
B25: ÅOP | D25: =(1+D24)^D8-1 -> #NUM!

Sheet Realkredit finansiering
D1: Lånetype | E1: Fastforrentet med afdrag | F1: Rentetilpasning med afdrag F5 | G1: Fastforrentet 10 års afdragsfrihed | H1: Rentetilpasning uden afdrag F1
A2: Husets pris | B2: 4000000 | C2: Belåningsgrad (max.80%)
A3: Lånebeløb | B3: ='Hvordan finansieres boligen'!E8 -> 3000000 | C3: 0.8 | D3: Obligationshovedstol | E3: =E5/E4*100 -> 3092783.5 | F3: =F5/F4*100 -> 3000000 | G3: =G5/G4*100 -> 3015075.4 | H3: =H5/H4*100 -> 3000000
D4: kurs på obligation | E4: 97 | F4: 100 | G4: 99.5 | H4: 100
A5: Låneomkostninger ved optagelse af realkreditlån: | D5: Kursværdi | E5: =B3 -> 3000000 | F5: =B3 -> 3000000 | G5: =B3 -> 3000000 | H5: =B3 -> 3000000
A6: Tinglysning af pant | B6: =1.45%*E3+1825 -> 46670.361 | D6: - lånekostninger | E6: =B9 -> 62670.361 | F6: =E6 -> 62670.361 | G6: =F6 -> 62670.361 | H6: =G6 -> 62670.361
A7: Etableringsomkostninger Realkreditinstitut | B7: 10000 | D7: Låneprovenu (det jeg får i hånden) | E7: =E5-E6 -> 2937329.6 | F7: =F5-F6 -> 2937329.6 | G7: =G5-G6 -> 2937329.6 | H7: =H5-H6 -> 2937329.6
A8: Kurtage/kursskæring, 0,2 pct. | B8: =0.2%*B3 -> 6000
A9: I alt | B9: =SUM(B6:B8) -> 62670.361 | D9: Pålydende rente | E9: 0.035 | F9: 0.026 | G9: 0.04 | H9: 0.024292
D10: Bidragssats | E10: 0.006812 | F10: 0.008564 | G10: =E10+0.002752 -> 0.009564 | H10: =0.008564+0.002752 -> 0.011316
D11: Rente + bidragssats | E11: =E10+E9 -> 0.041812 | F11: =F10+F9 -> 0.034564 | G11: =G10+G9 -> 0.049564 | H11: =H10+H9 -> 0.035608
D12: Løbetid, år | E12: 30 | F12: 30 | G12: 30 | H12: 30
D13: Terminer pr. år | E13: 12 | F13: =E13 -> 12 | G13: =F13 -> 12 | H13: =G13 -> 12
D14: Antal terminer i alt | E14: =E13*E12 -> 360 | F14: =F13*F12 -> 360 | G14: =G13*G12 -> 360 | H14: =H13*H12 -> 360
D16: Ydelse pr. termin | E16: =-PMT(E9/E13,E14,E3) -> 13887.98 | F16: =-PMT(F9/F13,F14,F5) -> 12010.191 | G16: =G3*G9/G13 -> 10050.251 | H16: =H5*H9/H13 -> 6073
D17: Ydelse pr. år | E17: =E16*E13 -> 166655.76 | F17: =F16*F13 -> 144122.3 | G17: =G16*G13 -> 120603.02 | H17: =H16*H13 -> 72876
D18: Bidrag 1.år | E18: {=SUMPRODUCT(FV(E9/E13, ROW(INDIRECT("1:" & E13))-1, PMT(E9/E13, E14, -E3, 0, 0), -E3, 0)) * E10/E13} -> 20883.896 | F18: {=SUMPRODUCT(FV(F9/F13, ROW(INDIRECT("1:" & F13))-1, PMT(F9/F13, F14, -F3, 0, 0), -F3, 0)) * F10/F13} -> 25430.575 | G18: =G3*G10/G13*G13 -> 28836.181 | H18: =H5*H10/H13*H13 -> 33948
D19: Bruttoydelse 1.år | E19: =SUM(E17:E18) -> 187539.66 | F19: =SUM(F17:F18) -> 169552.87 | G19: =SUM(G17:G18) -> 149439.2 | H19: =SUM(H17:H18) -> 106824
D21: Akkumuleret rente 1.år | E21: =-CUMIPMT(E9/E13,E14,E3,1,E13,0) -> 107301.29 | F21: =-CUMIPMT(F9/F13,F14,F3,1,F13,0) -> 77206.324 | G21: =G17 -> 120603.02 | H21: =H17 -> 72876
D22: Afdrag på gæld 1.år | E22: =-CUMPRINC(E9/E13,E14,E3,1,1*E13,0) -> 59354.474 | F22: =F17-F21 -> 66915.972 | G22: 0 | H22: 0
D24: Nettoydelse 1.år | E24: =E19-1/3*(E18+E21) -> 144811.26 | F24: =F19-1/3*(F18+F21) -> 135340.57 | G24: =G19-1/3*(G18+G21) -> 99626.131 | H24: =H19-1/3*(H18+H21) -> 71216
D25: Nettoydelse pr. termin (1.år) | E25: =E24/E13 -> 12067.605 | F25: =F24/F13 -> 11278.381 | G25: =G24/G13 -> 8302.1776 | H25: =H24/H13 -> 5934.6667
D27: Bruttoydelse pr. måned (gnsn) | E27: =E19/12 -> 15628.305 | F27: =F19/12 -> 14129.406 | G27: =G19/12 -> 12453.266 | H27: =H19/12 -> 8902
D28: Nettoydelse pr. måned (gnsn) | E28: =E24/12 -> 12067.605 | F28: =F24/12 -> 11278.381 | G28: =G24/12 -> 8302.1776 | H28: =H24/12 -> 5934.6667

Sheet F5
A1: Termin | B1: Restgæld | C1: Rente | D1: Afdrag | E1: Ydelse | F1: Bidrag | G1: Brutto- ydelse
A3: 0 | B3: ='Realkredit finansiering'!F5 -> 3000000
A4: 1 | B4: =B3-D4 -> 2994489.8 | C4: ='Realkredit finansiering'!$F$9/'Realkredit finansiering'!$F$13*'F5'!B3 -> 6500 | D4: =E4-C4 -> 5510.1913 | E4: ='Realkredit finansiering'!$F$16 -> 12010.191 | F4: ='Realkredit finansiering'!$F$10/'Realkredit finansiering'!$F$13*'F5'!B3 -> 2141 | G4: =E4+F4 -> 14151.191
A5: 2 | B5: =B4-D5 -> 2988967.7 | C5: ='Realkredit finansiering'!$F$9/'Realkredit finansiering'!$F$13*'F5'!B4 -> 6488.0613 | D5: =E5-C5 -> 5522.1301 | E5: ='Realkredit finansiering'!$F$16 -> 12010.191 | F5: ='Realkredit finansiering'!$F$10/'Realkredit finansiering'!$F$13*'F5'!B4 -> 2137.0676 | G5: =E5+F5 -> 14147.259
A6: 3 | B6: =B5-D6 -> 2983433.6 | C6: ='Realkredit finansiering'!$F$9/'Realkredit finansiering'!$F$13*'F5'!B5 -> 6476.0966 | D6: =E6-C6 -> 5534.0947 | E6: ='Realkredit finansiering'!$F$16 -> 12010.191 | F6: ='Realkredit finansiering'!$F$10/'Realkredit finansiering'!$F$13*'F5'!B5 -> 2133.1266 | G6: =E6+F6 -> 14143.318
A7: 4 | B7: =B6-D7 -> 2977887.5 | C7: ='Realkredit finansiering'!$F$9/'Realkredit finansiering'!$F$13*'F5'!B6 -> 6464.1061 | D7: =E7-C7 -> 5546.0852 | E7: ='Realkredit finansiering'!$F$16 -> 12010.191 | F7: ='Realkredit finansiering'!$F$10/'Realkredit finansiering'!$F$13*'F5'!B6 -> 2129.1771 | G7: =E7+F7 -> 14139.368
A8: 5 | B8: =B7-D8 -> 2972329.4 | C8: ='Realkredit finansiering'!$F$9/'Realkredit finansiering'!$F$13*'F5'!B7 -> 6452.0896 | D8: =E8-C8 -> 5558.1018 | E8: ='Realkredit finansiering'!$F$16 -> 12010.191 | F8: ='Realkredit finansiering'!$F$10/'Realkredit finansiering'!$F$13*'F5'!B7 -> 2125.219 | G8: =E8+F8 -> 14135.41
A9: 6 | B9: =B8-D9 -> 2966759.3 | C9: ='Realkredit finansiering'!$F$9/'Realkredit finansiering'!$F$13*'F5'!B8 -> 6440.047 | D9: =E9-C9 -> 5570.1443 | E9: ='Realkredit finansiering'!$F$16 -> 12010.191 | F9: ='Realkredit finansiering'!$F$10/'Realkredit finansiering'!$F$13*'F5'!B8 -> 2121.2524 | G9: =E9+F9 -> 14131.444
A10: 7 | B10: =B9-D10 -> 2961177 | C10: ='Realkredit finansiering'!$F$9/'Realkredit finansiering'!$F$13*'F5'!B9 -> 6427.9784 | D10: =E10-C10 -> 5582.213 | E10: ='Realkredit finansiering'!$F$16 -> 12010.191 | F10: ='Realkredit finansiering'!$F$10/'Realkredit finansiering'!$F$13*'F5'!B9 -> 2117.2772 | G10: =E10+F10 -> 14127.469
A11: 8 | B11: =B10-D11 -> 2955582.7 | C11: ='Realkredit finansiering'!$F$9/'Realkredit finansiering'!$F$13*'F5'!B10 -> 6415.8836 | D11: =E11-C11 -> 5594.3078 | E11: ='Realkredit finansiering'!$F$16 -> 12010.191 | F11: ='Realkredit finansiering'!$F$10/'Realkredit finansiering'!$F$13*'F5'!B10 -> 2113.2933 | G11: =E11+F11 -> 14123.485
A12: 9 | B12: =B11-D12 -> 2949976.3 | C12: ='Realkredit finansiering'!$F$9/'Realkredit finansiering'!$F$13*'F5'!B11 -> 6403.7626 | D12: =E12-C12 -> 5606.4288 | E12: ='Realkredit finansiering'!$F$16 -> 12010.191 | F12: ='Realkredit finansiering'!$F$10/'Realkredit finansiering'!$F$13*'F5'!B11 -> 2109.3009 | G12: =E12+F12 -> 14119.492
A13: 10 | B13: =B12-D13 -> 2944357.7 | C13: ='Realkredit finansiering'!$F$9/'Realkredit finansiering'!$F$13*'F5'!B12 -> 6391.6153 | D13: =E13-C13 -> 5618.576 | E13: ='Realkredit finansiering'!$F$16 -> 12010.191 | F13: ='Realkredit finansiering'!$F$10/'Realkredit finansiering'!$F$13*'F5'!B12 -> 2105.2998 | G13: =E13+F13 -> 14115.491
A14: 11 | B14: =B13-D14 -> 2938727 | C14: ='Realkredit finansiering'!$F$9/'Realkredit finansiering'!$F$13*'F5'!B13 -> 6379.4417 | D14: =E14-C14 -> 5630.7496 | E14: ='Realkredit finansiering'!$F$16 -> 12010.191 | F14: ='Realkredit finansiering'!$F$10/'Realkredit finansiering'!$F$13*'F5'!B13 -> 2101.29 | G14: =E14+F14 -> 14111.481
A15: 12 | B15: =B14-D15 -> 2933084 | C15: ='Realkredit finansiering'!$F$9/'Realkredit finansiering'!$F$13*'F5'!B14 -> 6367.2418 | D15: =E15-C15 -> 5642.9496 | E15: ='Realkredit finansiering'!$F$16 -> 12010.191 | F15: ='Realkredit finansiering'!$F$10/'Realkredit finansiering'!$F$13*'F5'!B14 -> 2097.2715 | G15: =E15+F15 -> 14107.463
... A123: 120 | B123: =B122-D123 -> 2245785.3 | C123: ='Realkredit finansiering'!$F$9/'Realkredit finansiering'!$F$13*'F5'!B122 -> 4881.314 | D123: =E123-C123 -> 7128.8773 | E123: ='Realkredit finansiering'!$F$16 -> 12010.191 | F123: ='Realkredit finansiering'!$F$10/'Realkredit finansiering'!$F$13*'F5'!B122 -> 1607.8297 | G123: =E123+F123 -> 13618.021

Sheet Enlig skat efter boligkøb
B1: Skatteberegningsprogram - enlig | C1: År 2025
C2: Person | I2: =C2 -> Person
B3: Privat indskud på ratepension (og ophørende livrente) | C3: 0 | I3: Beregnings-grundlag | J3: Beregnet skat
B4: Privat indskud på livrente | C4: 0 | F4: Beregning af skat | G4: Procent | H4: Fradrag
B5: Alder | C5: 0 | F5: Bundskat | G5: =Bundskat -> 0.1201 | H5: =Personfradrag -> 51600 | I5: =IF(C35>=0,C31+C35-H5,C31-H5) -> -51600 | J5: =+IF(I5>0,G5*I5,0) -> 0
B6: Har fri telefon (ja/nej) | C6: nej | F6: Topskat | G6: =Topskat -> 0.15 | H6: =TopSkatGranse -> 611800 | I6: =MAX((C70-$H$6),0) -> 0 | J6: =G6*I6 -> 0
B7: Fagforening | C7: 0 | F7: Sundhedsbidrag | G7: =Sundhedsbidrag -> 0 | H7: =Personfradrag -> 51600 | I7: =($C$45+AB29)-(H7+AB43) -> -51600 | J7: =+IF(I7>0,I7*G7,0) -> 0
B8: A-kasse og efterløn | C8: 0 | F8: Kommuneskat | G8: =C13 -> 0.256 | H8: =Personfradrag -> 51600 | I8: =($C$45+AB29)-(H8+AB44) -> -51600 | J8: =+IF(I8>0,$C$13*I8,0) -> 0
B9: Antal km til arbejde (tur/retur) | C9: 0 | F9: Kirkeskat | G9: =C14 -> 0 | H9: =Personfradrag -> 51600 | I9: =($C$45+AB29)-(H9+AB45) -> -51600 | J9: =+IF(I9>0,$C$14*I9,0) -> 0
B10: Antal arbejdsdage | C10: 0 | J10: =SUM(J5:J9) -> 0
B11: Medlem af Folkekirken (ja/nej) | C11: nej
B12: Vælg Kommune | C12: Albertslund | F12: Evt skattetillæg af neg. KI under 50.000 | J12: =IF(C35>=0,0,IF(C35>=GranseNegKIEnlig,TillagNegKI*C35,TillagNegKI*GranseNegKIEnlig)) -> 0
B13: Kommuneskattesats | C13: =VLOOKUP($C$12,Skattesatser!$B$6:$E$103,2)/100 -> 0.256 | F13: Evt. nedslag i topskatten (lønindkomst) | I13: =IF($C$73>SkraatSkatteloftPI,$C$73-SkraatSkatteloftPI,0) -> 0.0054 | J13: =-I13*C75 -> 0
B14: Kirkeskattesats | C14: =IF(C11="ja",VLOOKUP($C$12,Skattesatser!$B$6:$E$103,3)/100,0) -> 0 | F14: Evt. nedslag i topskatten (kapitalindkomst) | I14: =IF($C$73>SkraatSkatteloftKI,$C$73-SkraatSkatteloftKI,0) -> 0.1061 | J14: =-I14*C76 -> 0
B15: Grundskyldssats | C15: =VLOOKUP($C$12,Skattesatser!$B$6:$E$103,4)/1000 -> 0.0091 | J15: =SUM(J10:J14) -> 0
B16: Ejendomsværdi (offentlig) | C16: 0
B17: Grundværdi (offentlig) | C17: 0
B18: Evt skatterabat (bolig købt før 1.jan.2024) | C18: 0 | F18: Indkomstskat i alt (incl. AM-bidrag) | J18: =J15+C27 -> 0
F19: Ejendomsværdiskat | J19: =+F63 -> 0
B20: Lønindkomst (efter evt. ATP) | C20: 0 | F20: Grundskyld | J20: =F64 -> 0
B21: arbejdsgiverpensionsordning % (kun eget indskud) | C21: 0 | F21: Skatterabat | J21: =-C18 -> 0
B22: - arbejdsgiverpensionsordning DKK (kun eget indskud) | C22: =C21*C20 -> 0
B23: + anden AM-pligtig indkomst | C23: 0 | F23: Skat i alt | J23: =SUM(J18:J21) -> 0
B24: + fri telefon | C24: =IF(C6="ja",FriTelefon,0) -> 0
B25: = Beregningsgrundlag for AM-bidrag | C25: =C20-C22+C23+C24 -> 0
F26: Udbetalt efter skat | I26: =C2 -> Person
B27: - AM-bidrag | C27: =ArbBidrag*C25 -> 0 | I27: Pr. år | J27: Pr. måned
B28: + Ikke AM-pligtig indkomst (SU, dagpenge, pension etc.) | C28: 0 | F28: Lønindkomst | I28: =C20+C23+C28 -> 0 | J28: =I28/12 -> 0
B29: - Eget indskud på ratepension (husk også at indtaste i budget) | C29: =IF(C3>RatepensionMax,RatepensionMax,C3) -> 0 | F29: - arbejdsgiver pensionsordning | I29: =C22 -> 0 | J29: =I29/12 -> 0
B30: - Eget indskud på livrente (husk også at indtaste i budget) | C30: =+C4 -> 0 | F30: - skat | I30: =J23 -> 0 | J30: =I30/12 -> 0
B31: = Personlig indkomst (PI) | C31: =C25-C27+C28-C29-C30 -> 0 | F31: Udbetalt efter skat | I31: =I28-I29-I30 -> 0 | J31: =I31/12 -> 0
B33: + Renteindtægter | C33: 0
B34: - Renteudgfter | C34: 0
B35: + Kapitalindkomst (KI) i alt | C35: =+C33-C34 -> 0
B37: Beskæftigelsesfradrag | C37: =MIN(+($C$25+$C$22*3)*BFradragProc,BFradragMax) -> 0
B38: Jobfradrag | C38: =MAX(0,MIN(+($C$25+$C$22*3-Jfradraggranse)*Jfradragproc,JfradragMax)) -> 0
B39: Ekstra pensionsfradrag | C39: =IF(C5<=52,MIN(+(C3+C4+C22*3)*EPENfradragProc,EPENfradragMax),MIN(+(C3+C4+C22*3)*EPENSeniorProc,EPENSeniorMax)) -> 0
B40: Fagforening, A-kasse og efterløn | C40: =IF(C7>FagforeningMax,FagforeningMax,C7)+C8 -> 0
B41: Befordring | C41: =+$H$56 -> 0
B42: Andre ligningsmæssige fradrag | C42: 0
B43: - Ligningsmæssige fradrag i alt | C43: =SUM(C37:C42) -> 0
B45: = Skattepligtig indkomst (SI) | C45: =+C31+C35-C43 -> 0
B50: BEREGNINGSOMRÅDE (INDTAST IKKE NOGET)
B52: Person1
C53: sats | D53: dage | E53: km/dag | F53: min. | G53: frad./dag | H53: fradrag i alt
B54: Befordring for km under standardgrænse | C54: =BeFradragHojSats -> 2.23 | D54: =C10 -> 0 | E54: =C9 -> 0 | F54: =BeFradragKmMin -> 24 | G54: =IF(E54>F54,MIN(E54,BeFradragKmMax)-F54,0) -> 0 | H54: =+(D54*G54)*C54 -> 0
B55: Befordring for km over standardgrænse | C55: =BeFradragLavSats -> 1.12 | D55: =C10 -> 0 | E55: =MAX(E54-BeFradragKmMax,0) -> 0 | G55: =MAX(E55,0) -> 0 | H55: =+(D55*G55)*C55 -> 0
B56: Samlet befordringsfradrag | H56: =SUM(H54:H55) -> 0
B58: Evt. forhøjelser skal laves manuelt
B62: Ejendomsskatter | C62: Sats | D62: Høj sats | E62: Ejendomsværdi | F62: I alt
B63: Ejendomsværdiskat | C63: =EjVSkatMin -> 0.0051 | D63: =EjVSkatMax-C63 -> 0.0089 | E63: =C16 -> 0 | F63: =IF(E63<Skattesatser!H14,C63*E63*Forsigtighed,C63*E63*Forsigtighed+(E63-Skattesatser!H14)*D63*Forsigtighed) -> 0
B64: Grundskyld | C64: =C15 -> 0.0091 | E64: =C17 -> 0 | F64: =E64*C64*Forsigtighed -> 0
B67: Mellemregninger | C67: Person 1
B68: Værdi af personlig indkomst | C68: =+C31 -> 0
B69: Værdi af personlig indkomst plus positiv kapitalindkomst | C69: =MAX(C35+C31,C31) -> 0
B70: Værdi af PI plus KI > min grænse | C70: =C68+C72 -> 0
B71: Positiv kapitalindkomst | C71: =MAX(C35,0) -> 0
B72: Positiv kapitalindkomst over min grænse | C72: =IF((C71+D71)>KItilTopskatEnlig,C71+D71-KItilTopskatEnlig,0) -> 0
B73: Sum af skatteprocenter | C73: =SUM(G5:G8) -> 0.5261
B74: Topskatteberegningsgrundlag | C74: =IF(C70>TopSkatGranse,C70-TopSkatGranse,0) -> 0
B75: - andel som vedrører lønindkomst | C75: =IF(C68>TopSkatGranse,C68-TopSkatGranse,0) -> 0
B76: - andel som vedrører kapitalindkomst | C76: =C74-C75 -> 0

Sheet Ægtepar skat efter boligkøb
B1: Skatteberegningsprogram - par | C1: År 2025
B2: Person 1, er den med højest indkomst | C2: Person 1 | D2: Person 2 | I2: =C2 -> Person 1 | K2: =D2 -> Person 2
B3: Privat indskud på ratepension (og ophørende livrente) | C3: 0 | D3: 0 | I3: Beregnings-grundlag | J3: Beregnet skat | K3: Beregnings-grundlag | L3: Beregnet skat
B4: Privat indskud på livrente | C4: 0 | D4: 0 | F4: Beregning af skat | G4: Procent | H4: Fradrag
B5: Alder | C5: 0 | D5: 0 | F5: Bundskat | G5: =Bundskat -> 0.1201 | H5: =Personfradrag -> 51600 | I5: =IF($AC$28=1,($C$31+$AC$29),$C$77)-($H$5+$AB$41) -> -103200 | J5: =+IF(I5>0,G5*I5,0) -> 0 | K5: =IF(AC28=1,(D31+AD29),$D$77)-H5 -> -51600 | L5: =+IF(K5>0,K5*G5,0) -> 0
B6: Har fri telefon (ja/nej) | C6: nej | D6: nej | F6: Topskat | G6: =Topskat -> 0.15 | H6: =TopSkatGranse -> 611800 | I6: =MAX((C78-$H$6),0) -> 0 | J6: =G6*I6 -> 0 | K6: =MAX((D77-$H$6),0) -> 0 | L6: =G6*K6 -> 0
B7: Fagforening | C7: 0 | D7: 0 | F7: Sundhedsbidrag | G7: =Sundhedsbidrag -> 0 | H7: =Personfradrag -> 51600 | I7: =($C$45+AB29)-(H7+AB43) -> -103200 | J7: =+IF(I7>0,I7*G7,0) -> 0 | K7: =($D$45-AB29)-H7 -> -51600 | L7: =+IF(K7>0,G7*K7,0) -> 0
B8: A-kasse og efterløn | C8: 0 | D8: 0 | F8: Kommuneskat | G8: =C13 -> 0.256 | H8: =Personfradrag -> 51600 | I8: =($C$45+AB29)-(H8+AB44) -> -103200 | J8: =+IF(I8>0,$C$13*I8,0) -> 0 | K8: =($D$45-AB29)-H8 -> -51600 | L8: =+IF(K8>0,$D$13*K8,0) -> 0
B9: Antal km til arbejde (tur/retur) | C9: 0 | D9: 0 | F9: Kirkeskat | G9: =C14 -> 0 | H9: =Personfradrag -> 51600 | I9: =($C$45+AB29)-(H9+AB45) -> -103200 | J9: =+IF(I9>0,$C$14*I9,0) -> 0 | K9: =($D$45-AB29)-H9 -> -51600 | L9: =+IF(K9>0,$D$14*K9,0) -> 0
B10: Antal arbejdsdage | C10: 0 | D10: 0 | J10: =SUM(J5:J9) -> 0 | L10: =SUM(L5:L9) -> 0
B11: Medlem af Folkekirken (ja/nej) | C11: nej | D11: nej
B12: Vælg Kommune | C12: Albertslund | D12: =C12 -> Albertslund | F12: Evt skattetillæg af neg. KI under 50.000 | J12: =IF(AA29>=0,0,IF(AA29>=GranseNegKIPar,TillagNegKI*AA29,TillagNegKI*GranseNegKIPar)) -> 0
B13: Kommuneskattesats | C13: =VLOOKUP($C$12,Skattesatser!$B$6:$E$103,2)/100 -> 0.256 | D13: =VLOOKUP($D$12,Skattesatser!$B$6:$E$103,2)/100 -> 0.256 | F13: Evt. nedslag i topskatten (lønindkomst) | I13: =IF($C$81>SkraatSkatteloftPI,$C$81-SkraatSkatteloftPI,0) -> 0.0054 | J13: =-I13*C83 -> 0 | K13: =IF($D$81>SkraatSkatteloftPI,$D$81-SkraatSkatteloftPI,0) -> 0.0054 | L13: =-K13*D83 -> 0
B14: Kirkeskattesats | C14: =IF(C11="ja",VLOOKUP($C$12,Skattesatser!$B$6:$E$103,3)/100,0) -> 0 | D14: =IF(D11="ja",VLOOKUP($C$12,Skattesatser!$B$6:$E$103,3)/100,0) -> 0 | F14: Evt. nedslag i topskatten (kapitalindkomst) | I14: =IF($C$81>SkraatSkatteloftKI,$C$81-SkraatSkatteloftKI,0) -> 0.1061 | J14: =-I14*C84 -> 0
B15: Grundskyldssats | C15: =VLOOKUP($C$12,Skattesatser!$B$6:$E$103,4)/1000 -> 0.0091 | J15: =SUM(J10:J14) -> 0 | L15: =SUM(L10:L14) -> 0
B16: Ejendomsværdi (offentlig) | C16: 0
B17: Grundværdi (offentlig) | C17: 0
B18: Evt skatterabat (bolig købt før 1.jan.2024) | C18: 0 | F18: Indkomstskat i alt (incl. AM-bidrag) | J18: =J15+C27 -> 0 | L18: =L15+D27 -> 0
F19: Ejendomsværdiskat | J19: =+F71/2 -> 0 | L19: =J19 -> 0
B20: Lønindkomst (efter evt. ATP) | C20: 0 | D20: 0 | F20: Grundskyld | J20: =F72/2 -> 0 | L20: =J20 -> 0
B21: arbejdsgiverpensionsordning % (kun eget indskud) | C21: 0 | D21: 0 | F21: Skatterabat | J21: =-C18/2 -> 0 | L21: =J21 -> 0
B22: - arbejdsgiverpensionsordning DKK (kun eget indskud) | C22: =C21*C20 -> 0 | D22: =D21*D20 -> 0
B23: + anden AM-pligtig indkomst | C23: 0 | D23: 0 | F23: Skat i alt | J23: =SUM(J18:J22) -> 0 | L23: =SUM(L18:L22) -> 0
B24: + fri telefon | C24: =IF(C6="ja",FriTelefon,0) -> 0 | D24: =IF(D6="ja",FriTelefon,0) -> 0
B25: = Beregningsgrundlag for AM-bidrag | C25: =C20-C22+C23+C24 -> 0 | D25: =D20-D22+D23+D24 -> 0
F26: Udbetalt efter skat | I26: =C2 -> Person 1 | K26: =D2 -> Person 2 | AB26: Uudnyttet | AC26: Udligning af KI til brug for bundskat
B27: - AM-bidrag | C27: =ArbBidrag*C25 -> 0 | D27: =ArbBidrag*D25 -> 0 | I27: Pr. år | J27: Pr. måned | K27: Pr. år | L27: Pr. måned | AB27: KI | AC27: P1 | AD27: P2
B28: + Ikke AM-pligtig indkomst (SU, dagpenge, pension etc.) | C28: 0 | D28: 0 | F28: Lønindkomst | I28: =C20+C23+C28 -> 0 | J28: =I28/12 -> 0 | K28: =D20+D23+D28 -> 0 | L28: =K28/12 -> 0 | AB28: person 2 | AC28: =IF(AA29<0,0,IF((C35+0.00000001)*(D35+0.0000001)<0,1,0)) -> 0
B29: - Eget indskud på ratepension (husk også at indtaste i budget) | C29: =IF(C3>RatepensionMax,RatepensionMax,C3) -> 0 | D29: =IF(D3>RatepensionMax,RatepensionMax,D3) -> 0 | F29: - arbejdsgiver pensionsordning | I29: =C22 -> 0 | J29: =I29/12 -> 0 | K29: =D22 -> 0 | L29: =K29/12 -> 0 | AA29: =SUM(C35:D35) -> 0 | AB29: =IF(D45<0,IF(D31-D43<0,D35,D35+D31-D43),0) -> 0 | AC29: =IF(AC28=1,C35+D35,0) -> 0 | AD29: =IF(AC28=1,0,D35) -> 0
B30: - Eget indskud på livrente (husk også at indtaste i budget) | C30: =+C4 -> 0 | D30: =+D4 -> 0 | F30: - skat | I30: =J23 -> 0 | J30: =I30/12 -> 0 | K30: =L23 -> 0 | L30: =K30/12 -> 0
B31: = Personlig indkomst (PI) | C31: =C25-C27+C28-C29-C30 -> 0 | D31: =D25-D27+D28-D29-D30 -> 0 | F31: Udbetalt efter skat | I31: =I28-I29-I30 -> 0 | J31: =I31/12 -> 0 | K31: =K28-K29-K30 -> 0 | L31: =K31/12 -> 0
B33: + Renteindtægter | C33: 0 | D33: 0
B34: - Renteudgfter | C34: 0 | D34: 0
B35: + Kapitalindkomst (KI) i alt | C35: =+C33-C34 -> 0 | D35: =+D33-D34 -> 0
B37: Beskæftigelsesfradrag | C37: =MIN(+(C25+C22*3)*BFradragProc,BFradragMax) -> 0 | D37: =MIN(+(D25+D22*3)*BFradragProc,BFradragMax) -> 0
B38: Jobfradrag | C38: =MAX(0,MIN(+($C$25+C22*3-Jfradraggranse)*Jfradragproc,JfradragMax)) -> 0 | D38: =MAX(0,MIN(+($D$25+D22*3-Jfradraggranse)*Jfradragproc,JfradragMax)) -> 0 | AB38: Uudnyttet
B39: Ekstra pensionsfradrag | C39: =IF(C5<=52,MIN(+(C3+C4+C22*3)*EPENfradragProc,EPENfradragMax),MIN(+(C3+C4+C22*3)*EPENSeniorProc,EPENSeniorMax)) -> 0 | D39: =IF(D5<=52,MIN(+(D3+D4+D22*3)*EPENfradragProc,EPENfradragMax),MIN(+(D3+D4+D22*3)*EPENSeniorProc,EPENSeniorMax)) -> 0 | AB39: fradrag
B40: Fagforening, A-kasse og efterløn | C40: =IF(C7>FagforeningMax,FagforeningMax,C7)+C8 -> 0 | D40: =IF(D7>FagforeningMax,FagforeningMax,D7)+D8 -> 0 | AB40: person 2
B41: Befordring | C41: =+$H$56 -> 0 | D41: =H65 -> 0 | AB41: =IF(D77>H5,0,H5-D77) -> 51600
B42: Andre ligningsmæssige fradrag | C42: 0 | D42: 0
B43: - Ligningsmæssige fradrag i alt | C43: =SUM(C37:C42) -> 0 | D43: =SUM(D37:D42) -> 0 | AB43: =IF($D$45<0,H7,IF($D$45>H7,0,H7-$D$45)) -> 51600
AB44: =IF($D$45<0,H8,IF($D$45>H8,0,H8-$D$45)) -> 51600
B45: = Skattepligtig indkomst (SI) | C45: =+C31+C35-C43 -> 0 | D45: =+D31+D35-D43 -> 0 | AB45: =IF($D$45<0,H9,IF($D$45>H9,0,H9-$D$45)) -> 51600
B50: BEREGNINGSOMRÅDE (INDTAST IKKE NOGET)
B52: Person1
C53: sats | D53: dage | E53: km/dag | F53: min. | G53: frad./dag | H53: fradrag i alt
B54: Befordring for km under standardgrænse | C54: =BeFradragHojSats -> 2.23 | D54: =C10 -> 0 | E54: =C9 -> 0 | F54: =BeFradragKmMin -> 24 | G54: =IF(E54>F54,MIN(E54,BeFradragKmMax)-F54,0) -> 0 | H54: =+(D54*G54)*C54 -> 0
B55: Befordring for km over standardgrænse | C55: =BeFradragLavSats -> 1.12 | D55: =C10 -> 0 | E55: =MAX(E54-BeFradragKmMax,0) -> 0 | G55: =MAX(E55,0) -> 0 | H55: =+(D55*G55)*C55 -> 0
B56: Samlet befordringsfradrag | H56: =SUM(H54:H55) -> 0
B58: Evt. forhøjelser skal laves manuelt
B61: Person2
C62: sats | D62: dage | E62: km/dag | F62: min. | G62: frad./dag | H62: fradrag i alt
B63: Befordring for km under standardgrænse | C63: =C54 -> 2.23 | D63: =D10 -> 0 | E63: =D9 -> 0 | F63: =BeFradragKmMin -> 24 | G63: =IF(E63>F63,MIN(E63,BeFradragKmMax)-F63,0) -> 0 | H63: =+(D63*G63)*C63 -> 0
B64: Befordring for km over standardgrænse | C64: =C55 -> 1.12 | D64: =D10 -> 0 | E64: =MAX(E63-BeFradragKmMax,0) -> 0 | G64: =MAX(E64,0) -> 0 | H64: =+(D64*G64)*C64 -> 0
B65: Samlet befordringsfradrag | H65: =SUM(H63:H64) -> 0
B67: Evt. forhøjelser skal laves manuelt
B70: Ejendomsskatter | C70: Sats | D70: Høj sats | E70: Ejendomsværdi | F70: I alt
B71: Ejendomsværdiskat | C71: =EjVSkatMin -> 0.0051 | D71: =EjVSkatMax-C71 -> 0.0089 | E71: =C16 -> 0 | F71: =IF(E71<Skattesatser!H14,C71*E71*Forsigtighed,C71*E71*Forsigtighed+(E71-Skattesatser!H14)*D71*Forsigtighed) -> 0
B72: Grundskyld | C72: =C15 -> 0.0091 | E72: =C17 -> 0 | F72: =E72*C72*Forsigtighed -> 0
B75: Mellemregninger | C75: Person 1 | D75: Person 2
B76: Værdi af personlig indkomst | C76: =+C31 -> 0 | D76: =+D31 -> 0
B77: Værdi af personlig indkomst plus positiv kapitalindkomst | C77: =MAX(C35+C31,C31) -> 0 | D77: =MAX(D35+D31,D31) -> 0
B78: Værdi af PI plus KI > min grænse | C78: =C76+C80 -> 0
B79: Positiv kapitalindkomst | C79: =MAX(C35,0) -> 0 | D79: =D35 -> 0
B80: Positiv kapitalindkomst over fælles min grænse | C80: =IF((C35+D35)>KItilTopskatPar,C79+D79-KItilTopskatPar,0) -> 0
B81: Sum af skatteprocenter | C81: =SUM(G5:G8) -> 0.5261 | D81: =SUM(G5:G8) -> 0.5261
B82: Topskatteberegningsgrundlag | C82: =IF(C78>TopSkatGranse,C78-TopSkatGranse,0) -> 0 | D82: =IF(D76>Skattesatser!H35,D76-Skattesatser!H35,0) -> 0
B83: - andel som vedrører lønindkomst | C83: =IF(C76>TopSkatGranse,C76-TopSkatGranse,0) -> 0 | D83: =IF(D76>TopSkatGranse,D76-TopSkatGranse,0) -> 0
B84: - andel som vedrører kapitalindkomst | C84: =C82-C83 -> 0

Sheet Budget efter boligkøb
A1: Privatbudget - Par
A3: Indtægter | B3: jan | C3: feb | D3: mar | E3: apr | F3: maj | G3: juni | H3: juli | I3: aug | J3: sept | K3: okt | L3: nov | M3: dec | N3: TOTAL
A4: Løn, efter skat | B4: ='Ægtepar skat efter boligkøb'!J31 -> 0 | C4: =B4 -> 0 | D4: =C4 -> 0 | E4: =D4 -> 0 | F4: =E4 -> 0 | G4: =F4 -> 0 | H4: =G4 -> 0 | I4: =H4 -> 0 | J4: =I4 -> 0 | ... M4: =L4 -> 0 | N4: =SUM(B4:M4) -> 0
A5: Løn, efter skat | B5: ='Ægtepar skat efter boligkøb'!L31 -> 0 | C5: =B5 -> 0 | D5: =C5 -> 0 | E5: =D5 -> 0 | F5: =E5 -> 0 | G5: =F5 -> 0 | H5: =G5 -> 0 | I5: =H5 -> 0 | J5: =I5 -> 0 | ... M5: =L5 -> 0 | N5: =SUM(B5:M5) -> 0
A6: Renter/udbytte | B6: 0 | C6: 0 | D6: 0 | E6: 0 | F6: 0 | G6: 0 | H6: 0 | I6: 0 | J6: 0 | K6: 0 | L6: 0 | M6: 0 | N6: =SUM(B6:M6) -> 0
A7: Børne- og ungeydelse | C7: 0 | D7: 0 | E7: =B7 -> 0 | F7: 0 | G7: 0 | H7: =E7 -> 0 | I7: 0 | J7: 0 | K7: =H7 -> 0 | L7: 0 | M7: 0 | N7: =SUM(B7:M7) -> 0
A8: Børnebidrag | B8: 0 | C8: 0 | D8: 0 | E8: 0 | F8: 0 | G8: 0 | H8: 0 | I8: 0 | J8: 0 | K8: 0 | L8: 0 | M8: 0 | N8: =SUM(B8:M8) -> 0
A9: Børnetilskud | B9: 0 | C9: 0 | D9: 0 | E9: 0 | F9: 0 | G9: 0 | H9: 0 | I9: 0 | J9: 0 | K9: 0 | L9: 0 | M9: 0 | N9: =SUM(B9:M9) -> 0
A10: Indtægter i alt | B10: =SUM(B4:B9) -> 0 | C10: =SUM(C4:C9) -> 0 | D10: =SUM(D4:D9) -> 0 | E10: =SUM(E4:E9) -> 0 | F10: =SUM(F4:F9) -> 0 | G10: =SUM(G4:G9) -> 0 | H10: =SUM(H4:H9) -> 0 | I10: =SUM(I4:I9) -> 0 | ... M10: =SUM(M4:M9) -> 0 | N10: =SUM(B10:M10) -> 0
A13: Udgifter | B13: jan | C13: feb | D13: mar | E13: apr | F13: maj | G13: juni | H13: juli | I13: aug | J13: sept | K13: okt | L13: nov | M13: dec | N13: TOTAL
A14: Bolig
A15: Realkreditlån, ydelse efter skat | B15: ='Realkredit finansiering'!E28 -> 12067.605 | C15: =B15 -> 12067.605 | D15: =C15 -> 12067.605 | E15: =D15 -> 12067.605 | F15: =E15 -> 12067.605 | G15: =F15 -> 12067.605 | H15: =G15 -> 12067.605 | I15: =H15 -> 12067.605 | J15: =I15 -> 12067.605 | ... M15: =L15 -> 12067.605 | N15: =SUM(B15:M15) -> 144811.26 | O15: Hvis der ikke er realkreditlån skrives nul
A16: Banklån, ydelse efter skat | B16: =-Banklån!D22 -> #NUM! | C16: =B16 -> #NUM! | D16: =C16 -> #NUM! | E16: =D16 -> #NUM! | F16: =E16 -> #NUM! | G16: =F16 -> #NUM! | H16: =G16 -> #NUM! | I16: =H16 -> #NUM! | J16: =I16 -> #NUM! | ... M16: =L16 -> #NUM! | N16: =SUM(B16:M16) -> #NUM! | O16: Hvis der ikke er banklån skrives nul
A17: Renovation | B17: 0 | C17: 0 | D17: 0 | E17: 0 | F17: 0 | G17: 0 | H17: 0 | I17: 0 | J17: 0 | K17: 0 | L17: 0 | M17: 0 | N17: =SUM(B17:M17) -> 0
A18: Varme | B18: 0 | C18: =B18 -> 0 | D18: =C18 -> 0 | E18: =D18 -> 0 | F18: =E18 -> 0 | G18: =F18 -> 0 | H18: =G18 -> 0 | I18: =H18 -> 0 | J18: =I18 -> 0 | ... M18: =L18 -> 0 | N18: =SUM(B18:M18) -> 0
A19: Elektricitet | B19: 0 | C19: 0 | D19: 0 | E19: 0 | F19: 0 | G19: 0 | H19: 0 | I19: 0 | J19: 0 | K19: 0 | L19: 0 | M19: 0 | N19: =SUM(B19:M19) -> 0
A20: Vand | B20: 0 | C20: =B20 -> 0 | D20: =C20 -> 0 | E20: =D20 -> 0 | F20: =E20 -> 0 | G20: =F20 -> 0 | H20: =G20 -> 0 | I20: =H20 -> 0 | J20: =I20 -> 0 | ... M20: =L20 -> 0 | N20: =SUM(B20:M20) -> 0
A21: Ejendomsskatter | B21: 0 | C21: 0 | D21: 0 | E21: 0 | F21: 0 | G21: 0 | H21: 0 | I21: 0 | J21: 0 | K21: 0 | L21: 0 | M21: 0 | N21: =SUM(B21:M21) -> 0
A22: Fællesudgifter | B22: 0 | C22: =B22 -> 0 | D22: =C22 -> 0 | E22: =D22 -> 0 | F22: =E22 -> 0 | G22: =F22 -> 0 | H22: =G22 -> 0 | I22: =H22 -> 0 | J22: =I22 -> 0 | ... M22: =L22 -> 0 | N22: =SUM(B22:M22) -> 0
A23: Grundejerforening | B23: 0 | C23: 0 | D23: 0 | E23: 0 | F23: 0 | G23: 0 | H23: 0 | I23: 0 | J23: 0 | K23: 0 | L23: 0 | M23: 0 | N23: =SUM(B23:M23) -> 0
A24: Vedligeholdelse | B24: 0 | C24: =B24 -> 0 | D24: =C24 -> 0 | E24: =D24 -> 0 | F24: =E24 -> 0 | G24: =F24 -> 0 | H24: =G24 -> 0 | I24: =H24 -> 0 | J24: =I24 -> 0 | ... M24: =L24 -> 0 | N24: =SUM(B24:M24) -> 0
A25: Hus forsikring | B25: 0 | C25: 0 | D25: 0 | E25: 0 | F25: 0 | G25: 0 | H25: 0 | I25: 0 | J25: 0 | K25: 0 | L25: 0 | M25: 0 | N25: =SUM(B25:M25) -> 0
A26: Ejerudgift | B26: 0 | C26: =B26 -> 0 | D26: =C26 -> 0 | E26: =D26 -> 0 | F26: =E26 -> 0 | G26: =F26 -> 0 | H26: =G26 -> 0 | I26: =H26 -> 0 | J26: =I26 -> 0 | ... M26: =L26 -> 0 | N26: =SUM(B26:M26) -> 0
A27: Bolig i alt | B27: =SUM(B15:B26) -> #NUM! | C27: =SUM(C15:C26) -> #NUM! | D27: =SUM(D15:D26) -> #NUM! | E27: =SUM(E15:E26) -> #NUM! | F27: =SUM(F15:F26) -> #NUM! | G27: =SUM(G15:G26) -> #NUM! | H27: =SUM(H15:H26) -> #NUM! | I27: =SUM(I15:I26) -> #NUM! | ... N27: =SUM(N15:N26) -> #NUM!
A29: Bil
A30: Forsikring | B30: 0 | C30: 0 | D30: 0 | E30: 0 | F30: 0 | G30: 0 | H30: 0 | I30: 0 | J30: 0 | K30: 0 | L30: 0 | M30: 0 | N30: =SUM(B30:M30) -> 0
A31: Vægtafgift | B31: 0 | C31: 0 | D31: 0 | E31: 0 | F31: 0 | G31: 0 | H31: 0 | I31: 0 | J31: 0 | K31: 0 | L31: 0 | M31: 0 | N31: =SUM(B31:M31) -> 0
A32: Benzin | B32: 0 | C32: =B32 -> 0 | D32: =C32 -> 0 | E32: =D32 -> 0 | F32: =E32 -> 0 | G32: =F32 -> 0 | H32: =G32 -> 0 | I32: =H32 -> 0 | J32: =I32 -> 0 | ... M32: =L32 -> 0 | N32: =SUM(B32:M32) -> 0
A33: FDM | B33: 0 | C33: 0 | D33: 0 | E33: 0 | F33: 0 | G33: 0 | H33: 0 | I33: 0 | J33: 0 | K33: 0 | L33: 0 | M33: 0 | N33: =SUM(B33:M33) -> 0
A34: Billån | B34: 0 | C34: =B34 -> 0 | D34: =C34 -> 0 | E34: =D34 -> 0 | F34: =E34 -> 0 | G34: =F34 -> 0 | H34: =G34 -> 0 | I34: =H34 -> 0 | J34: =I34 -> 0 | ... M34: =L34 -> 0 | N34: =SUM(B34:M34) -> 0
A35: Vedligehold/reparation | B35: 0 | C35: 0 | D35: 0 | E35: 0 | F35: 0 | G35: 0 | H35: 0 | I35: 0 | J35: 0 | K35: 0 | L35: 0 | M35: 0 | N35: =SUM(B35:M35) -> 0
A36: Biludgifter i alt | B36: =SUM(B30:B35) -> 0 | C36: =SUM(C30:C35) -> 0 | D36: =SUM(D30:D35) -> 0 | E36: =SUM(E30:E35) -> 0 | F36: =SUM(F30:F35) -> 0 | G36: =SUM(G30:G35) -> 0 | H36: =SUM(H30:H35) -> 0 | I36: =SUM(I30:I35) -> 0 | ... M36: =SUM(M30:M35) -> 0 | N36: =SUM(B36:M36) -> 0
A38: Transport øvrig
A39: Offentlig transport | B39: 0 | C39: =B39 -> 0 | D39: =C39 -> 0 | E39: =D39 -> 0 | F39: =E39 -> 0 | G39: =F39 -> 0 | H39: =G39 -> 0 | I39: =H39 -> 0 | J39: =I39 -> 0 | ... M39: =L39 -> 0 | N39: =SUM(B39:M39) -> 0
A40: Diverse | B40: 0 | C40: 0 | D40: 0 | E40: 0 | F40: 0 | G40: 0 | H40: 0 | I40: 0 | J40: 0 | K40: 0 | L40: 0 | M40: 0 | N40: =SUM(B40:M40) -> 0
A41: Transport i alt | B41: =SUM(B39:B40) -> 0 | C41: =SUM(C39:C40) -> 0 | D41: =SUM(D39:D40) -> 0 | E41: =SUM(E39:E40) -> 0 | F41: =SUM(F39:F40) -> 0 | G41: =SUM(G39:G40) -> 0 | H41: =SUM(H39:H40) -> 0 | I41: =SUM(I39:I40) -> 0 | ... M41: =SUM(M39:M40) -> 0 | N41: =SUM(B41:M41) -> 0
A43: Kommunikation/TV
A44: Fastnettelefon | B44: 0 | C44: =B44 -> 0 | D44: =C44 -> 0 | E44: =D44 -> 0 | F44: =E44 -> 0 | G44: =F44 -> 0 | H44: =G44 -> 0 | I44: =H44 -> 0 | J44: =I44 -> 0 | ... M44: =L44 -> 0 | N44: =SUM(B44:M44) -> 0
A45: Mobiltelefon | B45: 0 | C45: =B45 -> 0 | D45: =C45 -> 0 | E45: =D45 -> 0 | F45: =E45 -> 0 | G45: =F45 -> 0 | H45: =G45 -> 0 | I45: =H45 -> 0 | J45: =I45 -> 0 | ... M45: =L45 -> 0 | N45: =SUM(B45:M45) -> 0
A46: Internet | B46: 0 | C46: =B46 -> 0 | D46: =C46 -> 0 | E46: =D46 -> 0 | F46: =E46 -> 0 | G46: =F46 -> 0 | H46: =G46 -> 0 | I46: =H46 -> 0 | J46: =I46 -> 0 | ... M46: =L46 -> 0 | N46: =SUM(B46:M46) -> 0
A47: Hybridnet/kabel-TV | B47: 0 | C47: =B47 -> 0 | D47: =C47 -> 0 | E47: =D47 -> 0 | F47: =E47 -> 0 | G47: =F47 -> 0 | H47: =G47 -> 0 | I47: =H47 -> 0 | J47: =I47 -> 0 | ... M47: =L47 -> 0 | N47: =SUM(B47:M47) -> 0
A48: Diverse | B48: 0 | C48: 0 | D48: 0 | E48: 0 | F48: 0 | G48: 0 | H48: 0 | I48: 0 | J48: 0 | K48: 0 | L48: 0 | M48: 0 | N48: =SUM(B48:M48) -> 0
A49: Kommun./TV i alt | B49: =SUM(B44:B48) -> 0 | C49: =SUM(C44:C48) -> 0 | D49: =SUM(D44:D48) -> 0 | E49: =SUM(E44:E48) -> 0 | F49: =SUM(F44:F48) -> 0 | G49: =SUM(G44:G48) -> 0 | H49: =SUM(H44:H48) -> 0 | I49: =SUM(I44:I48) -> 0 | ... N49: =SUM(N44:N48) -> 0
A51: Forsikringer
A52: A-kasse | B52: 0 | C52: =B52 -> 0 | D52: =C52 -> 0 | E52: =D52 -> 0 | F52: =E52 -> 0 | G52: =F52 -> 0 | H52: =G52 -> 0 | I52: =H52 -> 0 | J52: =I52 -> 0 | ... M52: =L52 -> 0 | N52: =SUM(B52:M52) -> 0
A53: A-kasse | B53: 0 | C53: =B53 -> 0 | D53: =C53 -> 0 | E53: =D53 -> 0 | F53: =E53 -> 0 | G53: =F53 -> 0 | H53: =G53 -> 0 | I53: =H53 -> 0 | J53: =I53 -> 0 | ... M53: =L53 -> 0 | N53: =SUM(B53:M53) -> 0
A54: Fagforening | B54: 0 | C54: =B54 -> 0 | D54: =C54 -> 0 | E54: =D54 -> 0 | F54: =E54 -> 0 | G54: =F54 -> 0 | H54: =G54 -> 0 | I54: =H54 -> 0 | J54: =I54 -> 0 | ... M54: =L54 -> 0 | N54: =SUM(B54:M54) -> 0
A55: Fagforening | B55: 0 | C55: =B55 -> 0 | D55: =C55 -> 0 | E55: =D55 -> 0 | F55: =E55 -> 0 | G55: =F55 -> 0 | H55: =G55 -> 0 | I55: =H55 -> 0 | J55: =I55 -> 0 | ... M55: =L55 -> 0 | N55: =SUM(B55:M55) -> 0
A56: Familieforsikring | B56: 0 | C56: =B56 -> 0 | D56: =C56 -> 0 | E56: =D56 -> 0 | F56: =E56 -> 0 | G56: =F56 -> 0 | H56: =G56 -> 0 | I56: =H56 -> 0 | J56: =I56 -> 0 | ... M56: =L56 -> 0 | N56: =SUM(B56:M56) -> 0
A57: Ulykkesforsikring | B57: 0 | C57: 0 | D57: 0 | E57: 0 | F57: 0 | G57: 0 | H57: 0 | I57: 0 | J57: 0 | K57: 0 | L57: 0 | M57: 0 | N57: =SUM(B57:M57) -> 0
A58: Sygeforsikring Danmark | B58: 0 | C58: 0 | D58: 0 | E58: 0 | F58: 0 | G58: 0 | H58: 0 | I58: 0 | J58: 0 | K58: 0 | L58: 0 | M58: 0 | N58: =SUM(B58:M58) -> 0
A59: Receptpligtig medecin | B59: 0 | C59: =B59 -> 0 | D59: =C59 -> 0 | E59: =D59 -> 0 | F59: =E59 -> 0 | G59: =F59 -> 0 | H59: =G59 -> 0 | I59: =H59 -> 0 | J59: =I59 -> 0 | ... M59: =L59 -> 0 | N59: =SUM(B59:M59) -> 0
A60: Diverse | B60: 0 | C60: 0 | D60: 0 | E60: 0 | F60: 0 | G60: 0 | H60: 0 | I60: 0 | J60: 0 | K60: 0 | L60: 0 | M60: 0 | N60: =SUM(B60:M60) -> 0
A61: Forsikringer i alt | B61: =SUM(B52:B60) -> 0 | C61: =SUM(C52:C60) -> 0 | D61: =SUM(D52:D60) -> 0 | E61: =SUM(E52:E60) -> 0 | F61: =SUM(F52:F60) -> 0 | G61: =SUM(G52:G60) -> 0 | H61: =SUM(H52:H60) -> 0 | I61: =SUM(I52:I60) -> 0 | ... N61: =SUM(N52:N60) -> 0
A63: Børneudgifter
A64: SFO | B64: 0 | C64: =B64 -> 0 | D64: =C64 -> 0 | E64: =D64 -> 0 | F64: =E64 -> 0 | G64: =F64 -> 0 | H64: =G64 -> 0 | I64: =H64 -> 0 | J64: =I64 -> 0 | ... M64: =L64 -> 0 | N64: =SUM(B64:M64) -> 0
A65: Vuggestue/børnehave | B65: 0 | C65: =B65 -> 0 | D65: =C65 -> 0 | E65: =D65 -> 0 | F65: =E65 -> 0 | G65: =F65 -> 0 | H65: =G65 -> 0 | I65: =H65 -> 0 | J65: =I65 -> 0 | ... M65: =L65 -> 0 | N65: =SUM(B65:M65) -> 0
A66: Transport | B66: 0 | C66: =B66 -> 0 | D66: =C66 -> 0 | E66: =D66 -> 0 | F66: =E66 -> 0 | G66: =F66 -> 0 | H66: =G66 -> 0 | I66: =H66 -> 0 | J66: =I66 -> 0 | ... M66: =L66 -> 0 | N66: =SUM(B66:M66) -> 0
A67: Skoleudgifter | B67: 0 | C67: 0 | D67: 0 | E67: 0 | F67: 0 | G67: 0 | H67: 0 | I67: 0 | J67: 0 | K67: 0 | L67: 0 | M67: 0 | N67: =SUM(B67:M67) -> 0
A68: Diverse | B68: 0 | C68: =B68 -> 0 | D68: =C68 -> 0 | E68: =D68 -> 0 | F68: =E68 -> 0 | G68: =F68 -> 0 | H68: =G68 -> 0 | I68: =H68 -> 0 | J68: =I68 -> 0 | ... M68: =L68 -> 0 | N68: =SUM(B68:M68) -> 0
A69: Børneudgifter i alt | B69: =SUM(B64:B68) -> 0 | C69: =SUM(C64:C68) -> 0 | D69: =SUM(D64:D68) -> 0 | E69: =SUM(E64:E68) -> 0 | F69: =SUM(F64:F68) -> 0 | G69: =SUM(G64:G68) -> 0 | H69: =SUM(H64:H68) -> 0 | I69: =SUM(I64:I68) -> 0 | ... N69: =SUM(N64:N68) -> 0
A71: Gældsforpligtelser
A72: [Indsæt kreditor) | B72: 0 | C72: 0 | D72: 0 | E72: 0 | F72: 0 | G72: 0 | H72: 0 | I72: 0 | J72: 0 | K72: 0 | L72: 0 | M72: 0 | N72: =SUM(B72:M72) -> 0
A73: [Indsæt kreditor) | B73: 0 | C73: 0 | D73: 0 | E73: 0 | F73: 0 | G73: 0 | H73: 0 | I73: 0 | J73: 0 | K73: 0 | L73: 0 | M73: 0 | N73: =SUM(B73:M73) -> 0
A74: Forpligtelser i alt | B74: =SUM(B72:B73) -> 0 | C74: =SUM(C72:C73) -> 0 | D74: =SUM(D72:D73) -> 0 | E74: =SUM(E72:E73) -> 0 | F74: =SUM(F72:F73) -> 0 | G74: =SUM(G72:G73) -> 0 | H74: =SUM(H72:H73) -> 0 | I74: =SUM(I72:I73) -> 0 | ... N74: =SUM(N72:N73) -> 0
A76: Diverse
A77: Andet | B77: 0 | C77: =B77 -> 0 | D77: =C77 -> 0 | E77: =D77 -> 0 | F77: =E77 -> 0 | G77: =F77 -> 0 | H77: =G77 -> 0 | I77: =H77 -> 0 | J77: =I77 -> 0 | ... M77: =L77 -> 0 | N77: =SUM(B77:M77) -> 0
A78: Andet | B78: 0 | C78: 0 | D78: 0 | E78: 0 | F78: 0 | G78: 0 | H78: 0 | I78: 0 | J78: 0 | K78: 0 | L78: 0 | M78: 0 | N78: =SUM(B78:M78) -> 0
A79: Andet | B79: 0 | C79: 0 | D79: 0 | E79: 0 | F79: 0 | G79: 0 | H79: 0 | I79: 0 | J79: 0 | K79: 0 | L79: 0 | M79: 0 | N79: =SUM(B79:M79) -> 0
A80: Diverse i alt | B80: =SUM(B77:B79) -> 0 | C80: =SUM(C77:C79) -> 0 | D80: =SUM(D77:D79) -> 0 | E80: =SUM(E77:E79) -> 0 | F80: =SUM(F77:F79) -> 0 | G80: =SUM(G77:G79) -> 0 | H80: =SUM(H77:H79) -> 0 | I80: =SUM(I77:I79) -> 0 | ... N80: =SUM(N77:N79) -> 0
A82: Udgifter i alt | B82: =B27+B36+B41+B49+B61+B69+B74+B80 -> #NUM! | C82: =C27+C36+C41+C49+C61+C69+C74+C80 -> #NUM! | D82: =D27+D36+D41+D49+D61+D69+D74+D80 -> #NUM! | E82: =E27+E36+E41+E49+E61+E69+E74+E80 -> #NUM! | F82: =F27+F36+F41+F49+F61+F69+F74+F80 -> #NUM! | G82: =G27+G36+G41+G49+G61+G69+G74+G80 -> #NUM! | H82: =H27+H36+H41+H49+H61+H69+H74+H80 -> #NUM! | I82: =I27+I36+I41+I49+I61+I69+I74+I80 -> #NUM! | ... N82: =N27+N36+N41+N49+N61+N69+N74+N80 -> #NUM!
A85: Oversigt | B85: =B3 -> jan | C85: =C3 -> feb | D85: =D3 -> mar | E85: =E3 -> apr | F85: =F3 -> maj | G85: =G3 -> juni | H85: =H3 -> juli | I85: =I3 -> aug | ... N85: =N3 -> TOTAL
A86: Overskud/underskud | B86: =SUM(B10-B82) -> #NUM! | C86: =SUM(C10-C82) -> #NUM! | D86: =SUM(D10-D82) -> #NUM! | E86: =SUM(E10-E82) -> #NUM! | F86: =SUM(F10-F82) -> #NUM! | G86: =SUM(G10-G82) -> #NUM! | H86: =SUM(H10-H82) -> #NUM! | I86: =SUM(I10-I82) -> #NUM! | ... N86: =SUM(N10-N82) -> #NUM!
A87: Årligt rådighedsbeløb | N87: =N86 -> #NUM!
A88: Månedligt rådighedsbeløb | B88: =B86 -> #NUM! | C88: =C86 -> #NUM! | D88: =D86 -> #NUM! | E88: =E86 -> #NUM! | F88: =F86 -> #NUM! | G88: =G86 -> #NUM! | H88: =H86 -> #NUM! | I88: =I86 -> #NUM! | ... M88: =M86 -> #NUM! | N88: =N87/12 -> #NUM!

Sheet Rådighedsbeløb og gældsfaktor
D1: Rådighedsbeløb før og efter køb | G1: Gældsfaktor ved køb
E3: kr.
D4: Rådighedsbeløb før køb af hus | E4: ='Budget før boligkøb'!N88 -> 26175.907 | G4: Gældsfaktor v/enlig | O4: =(Banklån!D6+'Realkredit finansiering'!E3)/'Enlig skat før boligkøb'!C20 -> 6.185567
D5: Rådighedsbeløb fastforrrentet MED afdrag | E5: ='Budget efter boligkøb'!N88 -> #NUM!
D6: Rådighedsbeløb F5 MED afdrag | E6: =E5+'Realkredit finansiering'!E28-'Realkredit finansiering'!F28 -> #NUM! | G6: Gældsfaktor v/par | O6: =(Banklån!D6+'Realkredit finansiering'!E3)/('Ægtepar skat før boligkøb'!C20+'Ægtepar skat før boligkøb'!D20) -> #DIV/0!
D7: Rådighedsbeløb fastforrentet UDEN afdrag | E7: =E5+'Realkredit finansiering'!E28-'Realkredit finansiering'!G28 -> #NUM!
D8: Rådighedsbeløb F1 UDEN afdrag | E8: =E5+'Realkredit finansiering'!E28-'Realkredit finansiering'!H28 -> #NUM!
G10: Hvilket lån skal jeg vælge?
G12: De skal kreditvurderes ud fra et fastforrentet realkreditlån MED afdrag!
G13: De kan IKKE blive kreditvurderet udfra andre realkreditlån!!!
G15: Vælger de efter den kreditvurdering at tage et andet lån skal
G16: de rådgives omkring fordele/ulemper vedr. fast vs. flex og afdrag vs. uden afdrag
G17: Afdragsfrihed på realkreditlånet kan være hensigtsmæssigt, hvis de har et dyrt banklån også
G19: Der er "frit valg" af realkreditlån hvis gældsfaktor er under 4 eller belåningsgrad er under 60%

Sheet Nedkonvertering
E1: NEDKONVERTERING
E2: Nuværende lån optaget for | F2: =H19 -> 0 | G2: år siden
E3: Du må ikke skrive her | G3: Hovedstol (oprindelig) | H3: 0
G4: Pålydende rente
G5: Bidrag | H5: 0.006812
G6: Pålydende rente+bidrag | H6: =H4+H5 -> 0.006812
G7: Kurs i dag | I7: Kursen bliver ikke brugt i beregningen her øverst, men den siger noget om hvorvidt vi skal indfri til markedskurs eller kurs 100 ved konverterbar obligationer
G8: Løbetid (oprindelig)
G9: Terminer pr. år | H9: 4
G10: Antal terminer i alt | H10: =H8*H9 -> 0
G12: Ydelse pr. termin | H12: =-PMT(H4/H9,H10,H3) -> #NUM!
G13: Ydelse i år | H13: =H12*H9 -> #NUM!
G14: Bidrag i år | H14: =($H$3+CUMPRINC($H$4/4,$H$10,$H$3,1,$F$2*$H$9,0))*$H$5/$H$9+($H$3+CUMPRINC($H$4/4,$H$10,$H$3,1,$F$2*$H$9+1,0))*$H$5/$H$9+($H$3+CUMPRINC($H$4/4,$H$10,$H$3,1,$F$2*$H$9+2,0))*$H$5/$H$9+($H$3+CUMPRINC($H$4/4,$H$10,$H$3,1,$F$2*$H$9+3,0))*$H$5/$H$9 -> #NUM!
G15: Bruttoydelse i år | H15: =SUM(H13:H14) -> #NUM!
G16: Akkumuleret rente i år | H16: =-CUMIPMT(H4/H9,H10,H3,H19*H9+1,H19*H9+4,0) -> #NUM!
G17: Nettoydelse i år | H17: =H15-1/3*(H14+H16) -> #NUM!
G19: Antal år hvor der er afdraget på lånet
G20: Afdrag på lånet "so far" | H20: =-CUMPRINC(H4/H9,H10,H3,1,H19*H9,0) -> #NUM!
G21: Obligationsrestgæld | H21: =H3-H20 -> #NUM!
E22: Skal de konvertere:
G24: Kunden kan nedkonvertere til et ? pct. konverterbart obligationslån
G25: => eksisterende høj rente lån indfries til kurs 100 da det er KONVERTERBART. NEDkonvertering
E27: Eksisterende lån:
G28: Obligationsrestgæld på eksisterende lån | H28: =H21 -> #NUM!
G29: Indfries til kurs 100(konverterbare oblig.) | H29: =H28 -> #NUM!
E31: Nyt lån: | G31: Låneomkostninger i forbindelse med konvertering | H31: =20000 -> 20000 | I31: Oven i låneomkostningerne kan du lægge en evt. belåning af friværdi, hvis der fx skal lånes til en bil eller sommerhus m.m. Husk max 80% realkreditlån i alt.
G32: Lånebehov | H32: =H29+H31 -> #NUM!
G33: Kurs på nyt lån
G34: Ny hovedstol | H34: =H32/(H33/100) -> #NUM!
G35: Pålydende rente
G36: Bidrag | H36: =H5 -> 0.006812
G37: Pålydende rente+bidrag | H37: =H35+H36 -> 0.006812
G38: Løbetid, år
G39: Antal terminer pr. år | H39: =H9 -> 4
G40: Antal terminer i alt | H40: =H39*H38 -> 0
G42: Ydelse pr. termin | H42: =-PMT(H35/H39,H40,H34) -> #NUM!
G43: Ydelse i år | H43: =H42*H39 -> #NUM!
G44: Bidrag i år | H44: =H34*H36/H39+(H34+CUMPRINC(H35/H39,H40,H34,1,H39,0))*H36/H39+(H34+CUMPRINC(H35/H39,H40,H34,1,H39+1,0))*H36/H39+(H34+CUMPRINC(H35/H39,H40,H34,1,H39+2,0))*H36/H39 -> #NUM!
G45: Bruttoydelse i år | H45: =SUM(H43:H44) -> #NUM!
G46: Akkumuleret rente i år | H46: =-CUMIPMT(H35/H39,H40,H34,1,H39,0) -> #NUM!
G47: Nettoydelse i år | H47: =H45-1/3*(H44+H46) -> #NUM!
G51: Ydelsesbesparelse FØR skat pr termin (kvartal) | H51: =(H15-H45)/H39 -> #NUM!
G52: Ydelsesbesparelse EFTER skat pr termin (kvartal) | H52: =(H17-H47)/H39 -> #NUM!
G53: Stigning i restgælden | H53: =H34-H28 -> #NUM!
G54: Stigning i løbetid (år) | H54: =H38-(H8-H19) -> 0
G55: Konklusion: Kunden skal nedkonvertere da ydelsen på lånet falder
G56: mærkbart også selv om obligationsgælden stiger pga. låneomkostninger og kurstab

Sheet Opkonvertering
E1: OPKONVERTERING
E2: Nuværende lån optaget for | F2: =H19 -> 0 | G2: år siden
E3: Du må ikke skrive her | G3: Hovedstol (oprindelig)
G4: Pålydende rente
G5: Bidrag | H5: 0.006812
G6: Pålydende rente+bidrag | H6: =H4+H5 -> 0.006812
G7: Kurs i dag
G8: Løbetid (oprindelig)
G9: Terminer pr. år | H9: 4
G10: Antal terminer i alt | H10: =H8*H9 -> 0
G12: Ydelse pr. termin | H12: =-PMT(H4/H9,H10,H3) -> #NUM!
G13: Ydelse i år | H13: =H12*H9 -> #NUM!
G14: Bidrag i år | H14: =($H$3+CUMPRINC($H$4/4,$H$10,$H$3,1,$F$2*$H$9,0))*$H$5/$H$9+($H$3+CUMPRINC($H$4/4,$H$10,$H$3,1,$F$2*$H$9+1,0))*$H$5/$H$9+($H$3+CUMPRINC($H$4/4,$H$10,$H$3,1,$F$2*$H$9+2,0))*$H$5/$H$9+($H$3+CUMPRINC($H$4/4,$H$10,$H$3,1,$F$2*$H$9+3,0))*$H$5/$H$9 -> #NUM!
G15: Bruttoydelse i år | H15: =SUM(H13:H14) -> #NUM!
G16: Akkumuleret rente i år | H16: =-CUMIPMT(H4/H9,H10,H3,H19*H9+1,H19*H9+4,0) -> #NUM!
G17: Nettoydelse i år | H17: =H15-1/3*(H14+H16) -> #NUM!
G19: Antal år hvor der er afdraget på lånet
G20: Afdrag på lånet "so far" | H20: =-CUMPRINC(H4/H9,H10,H3,1,H19*H9,0) -> #NUM!
G21: Obligationsrestgæld | H21: =H3-H20 -> #NUM!
E22: Skal de konvertere:
G24: Kunden kan OPkonvertere til et ? pct. konverterbart obligationslån
G25: => eksisterende lavrente-lån indfries til nuværende markedskurs
E27: Eksisterende lån:
G28: Obligationsrestgæld på eksisterende lån | H28: =H21 -> #NUM!
G29: Indfries til aktuelle markedskurs | H29: =H28*H7/100 -> #NUM!
E31: Nyt lån: | G31: Låneomkostninger i forbindelse med konvertering | H31: =20000 -> 20000 | I31: Oven i låneomkostningerne kan du lægge en evt. belåning af friværdi, hvis der fx skal lånes til en bil, indfries gæld eller køb af sommerhus m.m. Husk max 80% realkreditlån i alt.
G32: Lånebehov | H32: =H29+H31 -> #NUM!
G33: Kurs på nyt lån
G34: Ny hovedstol | H34: =H32/(H33/100) -> #NUM!
G35: Pålydende rente
G36: Bidrag | H36: =H5 -> 0.006812
G37: Pålydende rente+bidrag | H37: =H35+H36 -> 0.006812
G38: Løbetid, år
G39: Antal terminer pr. år | H39: =H9 -> 4
G40: Antal terminer i alt | H40: =H39*H38 -> 0
G42: Ydelse pr. termin | H42: =-PMT(H35/H39,H40,H34) -> #NUM!
G43: Ydelse i år | H43: =H42*H39 -> #NUM!
G44: Bidrag i år | H44: =H34*H36/H39+(H34+CUMPRINC(H35/H39,H40,H34,1,H39,0))*H36/H39+(H34+CUMPRINC(H35/H39,H40,H34,1,H39+1,0))*H36/H39+(H34+CUMPRINC(H35/H39,H40,H34,1,H39+2,0))*H36/H39 -> #NUM!
G45: Bruttoydelse i år | H45: =SUM(H43:H44) -> #NUM!
G46: Akkumuleret rente i år | H46: =-CUMIPMT(H35/H39,H40,H34,1,H39,0) -> #NUM!
G47: Nettoydelse i år | H47: =H45-1/3*(H44+H46) -> #NUM!
G51: Ydelsesstigning FØR skat pr termin (kvartal) | H51: =(H45-H15)/H39 -> #NUM!
G52: Ydelsesstigning EFTER skat pr termin (kvartal) | H52: =(H47-H17)/H39 -> #NUM! | I52: (hvis "ydelsesstigningen" er i minus, er der tale om en besparelse)
G53: Fald i restgælden | H53: =H21-H34 -> #NUM!
G54: Stigning i løbetid (år) | H54: =H38-(H8-H19) -> 0
G55: Konklusion: Kunden skal opkonvertere da ydelsen på lånet stiger lidt
G56: men obligationsgælden falder markant. De skal naturligvis tro at renten på et senere tidspunkt falder igen
G57: således at de kan nedkonvertere igen og dermed få ydelsen ned!

Sheet Byg realkredit beregn restgæld
A1: 3 | D1: Lånetype | E1: Fastforrentet med afdrag | G1: Termin (4= 1 år) | H1: Restgæld | I1: Rente | J1: Afdrag | K1: Ydelse | L1: Bidrag | S1: Brutto- ydelse | T1: Netto- ydelse
A2: Husets pris | B2: 4000000 | M2: Ydelse inkl. | N2: Fradrag | O2: Ydelse | V2: ÅOP
A3: 80 pct. belåning | B3: =0.8*B2 -> 3200000 | D3: Obligationshovedstol | E3: =E5*100/E4 -> 3232323.2 | G3: 0 | H3: =E3 -> 3232323.2 | K3: =-E5 -> -3200000 | S3: =-E7 -> -3134906.3 | V3: =-E7 -> -3134906.3
D4: kurs på obligation | E4: 99 | G4: 1 | H4: =H3-J4 -> 3227666 | I4: =$E$9/$E$13*H3 -> 10774.411 | J4: =K4-I4 -> 4657.1947 | K4: =IF(G4>$E$14,0,$E$16) -> 15431.606 | L4: =$E$10/$E$13*H3 -> 1834.8822 | S4: =K4+L4 -> 17266.488 | T4: =S4-1/3*(I4+L4) -> 13063.39 | V4: =S4 -> 17266.488
A5: Låneomkostninger ved optagelse af realkreditlån: | D5: Kursværdi | E5: =B3 -> 3200000 | G5: 2 | H5: =H4-J5 -> 3222993.3 | I5: =$E$9/$E$13*H4 -> 10758.887 | J5: =K5-I5 -> 4672.7187 | K5: =IF(G5>$E$14,0,$E$16) -> 15431.606 | L5: =$E$10/$E$13*H4 -> 1832.2384 | S5: =K5+L5 -> 17263.844 | T5: =S5-1/3*(I5+L5) -> 13066.802 | V5: =S5 -> 17263.844
A6: Tinglysning af pant | B6: =1.45%*E3+1825 -> 48693.687 | D6: - lånekostninger | E6: =B9 -> 65093.687 | G6: 3 | H6: =H5-J6 -> 3218305 | I6: =$E$9/$E$13*H5 -> 10743.311 | J6: =K6-I6 -> 4688.2944 | K6: =IF(G6>$E$14,0,$E$16) -> 15431.606 | L6: =$E$10/$E$13*H5 -> 1829.5859 | S6: =K6+L6 -> 17261.191 | T6: =S6-1/3*(I6+L6) -> 13070.226 | V6: =S6 -> 17261.191
A7: Etableringsomkostninger Realkreditinstitut | B7: 10000 | D7: Låneprovenu (det jeg får i hånden) | E7: =E5-E6 -> 3134906.3 | G7: 4 | H7: =H6-J7 -> 3213601.1 | I7: =$E$9/$E$13*H6 -> 10727.683 | J7: =K7-I7 -> 4703.9221 | K7: =IF(G7>$E$14,0,$E$16) -> 15431.606 | L7: =$E$10/$E$13*H6 -> 1826.9245 | S7: =K7+L7 -> 17258.53 | T7: =S7-1/3*(I7+L7) -> 13073.661
A8: Kurtage/kursskæring, 0,2 pct. | B8: =0.2%*B3 -> 6400 | G8: 5 | H8: =H7-J8 -> 3208881.5 | I8: =$E$9/$E$13*H7 -> 10712.004 | J8: =K8-I8 -> 4719.6018 | K8: =IF(G8>$E$14,0,$E$16) -> 15431.606 | L8: =$E$10/$E$13*H7 -> 1824.2542 | S8: =K8+L8 -> 17255.86 | T8: =S8-1/3*(I8+L8) -> 13077.107 | V8: =S8 -> 17255.86
A9: I alt | B9: =SUM(B6:B8) -> 65093.687 | D9: Pålydende rente | E9: 0.04 | G9: 6 | H9: =H8-J9 -> 3204146.2 | I9: =$E$9/$E$13*H8 -> 10696.272 | J9: =K9-I9 -> 4735.3338 | K9: =IF(G9>$E$14,0,$E$16) -> 15431.606 | L9: =$E$10/$E$13*H8 -> 1821.5751 | S9: =K9+L9 -> 17253.181 | T9: =S9-1/3*(I9+L9) -> 13080.565 | V9: =S9 -> 17253.181
D10: Bidragssats | E10: 0.006812 | G10: 7 | H10: =H9-J10 -> 3199395 | I10: =$E$9/$E$13*H9 -> 10680.487 | J10: =K10-I10 -> 4751.1183 | K10: =IF(G10>$E$14,0,$E$16) -> 15431.606 | L10: =$E$10/$E$13*H9 -> 1818.887 | S10: =K10+L10 -> 17250.492 | T10: =S10-1/3*(I10+L10) -> 13084.034 | V10: =S10 -> 17250.492
A11: Hvis du kender restgælden i dag: | D11: Rente + bidragssats | E11: =SUM(E9:E10) -> 0.046812 | G11: 8 | H11: =H10-J11 -> 3194628.1 | I11: =$E$9/$E$13*H10 -> 10664.65 | J11: =K11-I11 -> 4766.9553 | K11: =IF(G11>$E$14,0,$E$16) -> 15431.606 | L11: =$E$10/$E$13*H10 -> 1816.1899 | S11: =K11+L11 -> 17247.795 | T11: =S11-1/3*(I11+L11) -> 13087.515 | V11: =S11 -> 17247.795
A12: NB! Hvis du skal beregne restgælden på et eksisterende lån efter et antal terminer/år, skal restgælden på lånet i dag sættes ind i feltet "Kursværdi" og kursen skal sættes til 100. Låneomkostningerne skal sættes til 0 kr da der jo ikke er tale om oprettelse af et nyt lån ved fx hus køb. HUSK AT SKRIVE RESTLØBETIDEN PÅ LÅNET. FX HVIS LÅNET HAR LØBET I 4 ÅR SKRIVES 26 ÅR. | D12: Løbetid, år | E12: 30 | G12: 9 | H12: =H11-J12 -> 3189845.2 | I12: =$E$9/$E$13*H11 -> 10648.76 | J12: =K12-I12 -> 4782.8452 | K12: =IF(G12>$E$14,0,$E$16) -> 15431.606 | L12: =$E$10/$E$13*H11 -> 1813.4839 | S12: =K12+L12 -> 17245.089 | T12: =S12-1/3*(I12+L12) -> 13091.008 | V12: =S12 -> 17245.089
D13: Terminer pr. år | E13: 12 | G13: 10 | H13: =H12-J13 -> 3185046.5 | I13: =$E$9/$E$13*H12 -> 10632.817 | J13: =K13-I13 -> 4798.788 | K13: =IF(G13>$E$14,0,$E$16) -> 15431.606 | L13: =$E$10/$E$13*H12 -> 1810.7688 | S13: =K13+L13 -> 17242.374 | T13: =S13-1/3*(I13+L13) -> 13094.512 | V13: =S13 -> 17242.374
D14: Antal terminer i alt | E14: =E12*E13 -> 360 | G14: 11 | H14: =H13-J14 -> 3180231.7 | I14: =$E$9/$E$13*H13 -> 10616.822 | J14: =K14-I14 -> 4814.784 | K14: =IF(G14>$E$14,0,$E$16) -> 15431.606 | L14: =$E$10/$E$13*H13 -> 1808.0447 | S14: =K14+L14 -> 17239.65 | T14: =S14-1/3*(I14+L14) -> 13098.028 | V14: =S14 -> 17239.65
G15: 12 | H15: =H14-J15 -> 3175400.8 | I15: =$E$9/$E$13*H14 -> 10600.772 | J15: =K15-I15 -> 4830.8333 | K15: =IF(G15>$E$14,0,$E$16) -> 15431.606 | L15: =$E$10/$E$13*H14 -> 1805.3115 | S15: =K15+L15 -> 17236.917 | T15: =S15-1/3*(I15+L15) -> 13101.556 | V15: =S15 -> 17236.917
D16: Ydelse pr. termin | E16: =-PMT(E9/E13,E14,E3) -> 15431.606 | G16: 13 | H16: =H15-J16 -> 3170553.9 | I16: =$E$9/$E$13*H15 -> 10584.669 | J16: =K16-I16 -> 4846.936 | K16: =IF(G16>$E$14,0,$E$16) -> 15431.606 | L16: =$E$10/$E$13*H15 -> 1802.5692 | S16: =K16+L16 -> 17234.175 | T16: =S16-1/3*(I16+L16) -> 13105.095 | V16: =S16 -> 17234.175
D17: Ydelse pr. år | E17: =E16*E13 -> 185179.27 | G17: 14 | H17: =H16-J17 -> 3165690.8 | I17: =$E$9/$E$13*H16 -> 10568.513 | J17: =K17-I17 -> 4863.0925 | K17: =IF(G17>$E$14,0,$E$16) -> 15431.606 | L17: =$E$10/$E$13*H16 -> 1799.8178 | S17: =K17+L17 -> 17231.423 | T17: =S17-1/3*(I17+L17) -> 13108.646 | V17: =S17 -> 17231.423
D18: Bidrag 1.år | E18: =SUM(INDIRECT("L4"):INDIRECT("L"&3+E13)) -> 21842.146 | G18: 15 | H18: =H17-J18 -> 3160811.5 | I18: =$E$9/$E$13*H17 -> 10552.303 | J18: =K18-I18 -> 4879.3028 | K18: =IF(G18>$E$14,0,$E$16) -> 15431.606 | L18: =$E$10/$E$13*H17 -> 1797.0572 | S18: =K18+L18 -> 17228.663 | T18: =S18-1/3*(I18+L18) -> 13112.209 | V18: =S18 -> 17228.663
D19: Bruttoydelse 1.år | E19: =SUM(E17:E18) -> 207021.41 | G19: 16 | H19: =H18-J19 -> 3155915.9 | I19: =$E$9/$E$13*H18 -> 10536.038 | J19: =K19-I19 -> 4895.5671 | K19: =IF(G19>$E$14,0,$E$16) -> 15431.606 | L19: =$E$10/$E$13*H18 -> 1794.2873 | S19: =K19+L19 -> 17225.893 | T19: =S19-1/3*(I19+L19) -> 13115.784 | V19: =S19 -> 17225.893
G20: 17 | H20: =H19-J20 -> 3151004.1 | I20: =$E$9/$E$13*H19 -> 10519.72 | J20: =K20-I20 -> 4911.8857 | K20: =IF(G20>$E$14,0,$E$16) -> 15431.606 | L20: =$E$10/$E$13*H19 -> 1791.5083 | S20: =K20+L20 -> 17223.114 | T20: =S20-1/3*(I20+L20) -> 13119.371 | V20: =S20 -> 17223.114
A21: Hvis du kender den oprindelige hovedstol og hvor lang tid lånet har løbet: | D21: Akkumuleret rente 1.år | E21: =-CUMIPMT(E9/E13,E14,E3,1,E13,0) -> 128256.88 | G21: 18 | H21: =H20-J21 -> 3146075.8 | I21: =$E$9/$E$13*H20 -> 10503.347 | J21: =K21-I21 -> 4928.2586 | K21: =IF(G21>$E$14,0,$E$16) -> 15431.606 | L21: =$E$10/$E$13*H20 -> 1788.72 | S21: =K21+L21 -> 17220.325 | T21: =S21-1/3*(I21+L21) -> 13122.97 | V21: =S21 -> 17220.325
D22: Afdrag på gæld 1.år | E22: =-CUMPRINC(E9/E13,E14,E3,1,E13,0) -> 56922.39 | G22: 19 | H22: =H21-J22 -> 3141131.1 | I22: =$E$9/$E$13*H21 -> 10486.919 | J22: =K22-I22 -> 4944.6862 | K22: =IF(G22>$E$14,0,$E$16) -> 15431.606 | L22: =$E$10/$E$13*H21 -> 1785.9224 | S22: =K22+L22 -> 17217.528 | T22: =S22-1/3*(I22+L22) -> 13126.581 | V22: =S22 -> 17217.528
A23: Så sætter du bare den oprindelige hoved stol ind i feltet "Kursværdi" og kursen skal sættes til 100 og låneomkostninger til 0. Så kan du se hvad restgælden er i dag ud for hvor mange terminer der er løbet på lånet indtil i dag. Og du kan se restgælden i fremtiden. | G23: 20 | H23: =H22-J23 -> 3136169.9 | I23: =$E$9/$E$13*H22 -> 10470.437 | J23: =K23-I23 -> 4961.1685 | K23: =IF(G23>$E$14,0,$E$16) -> 15431.606 | L23: =$E$10/$E$13*H22 -> 1783.1154 | S23: =K23+L23 -> 17214.721 | T23: =S23-1/3*(I23+L23) -> 13130.203 | V23: =S23 -> 17214.721
D24: Nettoydelse 1.år | E24: =SUM(INDIRECT("T4"):INDIRECT("T"&3+E13)) -> 156988.4 | G24: 21 | H24: =H23-J24 -> 3131192.2 | I24: =$E$9/$E$13*H23 -> 10453.9 | J24: =K24-I24 -> 4977.7057 | K24: =IF(G24>$E$14,0,$E$16) -> 15431.606 | L24: =$E$10/$E$13*H23 -> 1780.2991 | S24: =K24+L24 -> 17211.905 | T24: =S24-1/3*(I24+L24) -> 13133.838 | V24: =S24 -> 17211.905
D25: Nettoydelse pr. termin (1.år) | E25: =E24/E13 -> 13082.367 | G25: 22 | H25: =H24-J25 -> 3126197.9 | I25: =$E$9/$E$13*H24 -> 10437.307 | J25: =K25-I25 -> 4994.298 | K25: =IF(G25>$E$14,0,$E$16) -> 15431.606 | L25: =$E$10/$E$13*H24 -> 1777.4735 | S25: =K25+L25 -> 17209.079 | T25: =S25-1/3*(I25+L25) -> 13137.485 | V25: =S25 -> 17209.079
G26: 23 | H26: =H25-J26 -> 3121187 | I26: =$E$9/$E$13*H25 -> 10420.66 | J26: =K26-I26 -> 5010.9457 | K26: =IF(G26>$E$14,0,$E$16) -> 15431.606 | L26: =$E$10/$E$13*H25 -> 1774.6384 | S26: =K26+L26 -> 17206.244 | T26: =S26-1/3*(I26+L26) -> 13141.144 | V26: =S26 -> 17206.244
D27: Bruttoydelse pr. måned (gnsn) | E27: =E19/12 -> 17251.784 | G27: 24 | H27: =H26-J27 -> 3116159.3 | I27: =$E$9/$E$13*H26 -> 10403.957 | J27: =K27-I27 -> 5027.6489 | K27: =IF(G27>$E$14,0,$E$16) -> 15431.606 | L27: =$E$10/$E$13*H26 -> 1771.7938 | S27: =K27+L27 -> 17203.399 | T27: =S27-1/3*(I27+L27) -> 13144.816 | V27: =S27 -> 17203.399
D28: Nettoydelse pr. måned (gnsn) | E28: =E24/12 -> 13082.367 | G28: 25 | H28: =H27-J28 -> 3111114.9 | I28: =$E$9/$E$13*H27 -> 10387.198 | J28: =K28-I28 -> 5044.4077 | K28: =IF(G28>$E$14,0,$E$16) -> 15431.606 | L28: =$E$10/$E$13*H27 -> 1768.9398 | S28: =K28+L28 -> 17200.545 | T28: =S28-1/3*(I28+L28) -> 13148.499 | V28: =S28 -> 17200.545
A29: Hvis der er tale om et helt nyt lån der skal hjemtages ifm boligkøb: | G29: 26 | H29: =H28-J29 -> 3106053.7 | I29: =$E$9/$E$13*H28 -> 10370.383 | J29: =K29-I29 -> 5061.2224 | K29: =IF(G29>$E$14,0,$E$16) -> 15431.606 | L29: =$E$10/$E$13*H28 -> 1766.0762 | S29: =K29+L29 -> 17197.682 | T29: =S29-1/3*(I29+L29) -> 13152.195 | V29: =S29 -> 17197.682
G30: 27 | H30: =H29-J30 -> 3100975.6 | I30: =$E$9/$E$13*H29 -> 10353.512 | J30: =K30-I30 -> 5078.0931 | K30: =IF(G30>$E$14,0,$E$16) -> 15431.606 | L30: =$E$10/$E$13*H29 -> 1763.2032 | S30: =K30+L30 -> 17194.809 | T30: =S30-1/3*(I30+L30) -> 13155.903 | V30: =S30 -> 17194.809
A31: Så må du ikke skrive i feltet "Kursværdi", men i stedet taste huset pris ind. Så beregner skabelonen selv de 80% belåning som sættes ind i feltet "Kursværdi". Låneomkostningerne skal også beregnes og sættes ind i feltet "låneomkostninger". HUSK at finde kursen på det nye lån som sættes ind. | D31: Effektiv rente (obligation) pr. termin | E31: =RATE(E14,-E16,E5) -> 0.0034028588 | G31: 28 | H31: =H30-J31 -> 3095880.6 | I31: =$E$9/$E$13*H30 -> 10336.585 | J31: =K31-I31 -> 5095.0201 | K31: =IF(G31>$E$14,0,$E$16) -> 15431.606 | L31: =$E$10/$E$13*H30 -> 1760.3205 | S31: =K31+L31 -> 17191.926 | T31: =S31-1/3*(I31+L31) -> 13159.624 | V31: =S31 -> 17191.926
D32: Effektiv rente (obligation) pr. år | E32: =(1+E31)^E13-1 -> 0.041607285 | G32: 29 | H32: =H31-J32 -> 3090768.6 | I32: =$E$9/$E$13*H31 -> 10319.602 | J32: =K32-I32 -> 5112.0035 | K32: =IF(G32>$E$14,0,$E$16) -> 15431.606 | L32: =$E$10/$E$13*H31 -> 1757.4282 | S32: =K32+L32 -> 17189.034 | T32: =S32-1/3*(I32+L32) -> 13163.357 | V32: =S32 -> 17189.034
G33: 30 | H33: =H32-J33 -> 3085639.6 | I33: =$E$9/$E$13*H32 -> 10302.562 | J33: =K33-I33 -> 5129.0435 | K33: =IF(G33>$E$14,0,$E$16) -> 15431.606 | L33: =$E$10/$E$13*H32 -> 1754.5263 | S33: =K33+L33 -> 17186.132 | T33: =S33-1/3*(I33+L33) -> 13167.102 | V33: =S33 -> 17186.132
D34: ÅOP pr. termin | E34: =IRR(S3:S363) -> 0.0041270354 | G34: 31 | H34: =H33-J34 -> 3080493.4 | I34: =$E$9/$E$13*H33 -> 10285.465 | J34: =K34-I34 -> 5146.1403 | K34: =IF(G34>$E$14,0,$E$16) -> 15431.606 | L34: =$E$10/$E$13*H33 -> 1751.6147 | S34: =K34+L34 -> 17183.22 | T34: =S34-1/3*(I34+L34) -> 13170.86 | V34: =S34 -> 17183.22
D35: ÅOP pr. år | E35: =(1+E34)^E13-1 -> 0.050664174 | G35: 32 | H35: =H34-J35 -> 3075330.1 | I35: =$E$9/$E$13*H34 -> 10268.311 | J35: =K35-I35 -> 5163.2941 | K35: =IF(G35>$E$14,0,$E$16) -> 15431.606 | L35: =$E$10/$E$13*H34 -> 1748.6934 | S35: =K35+L35 -> 17180.299 | T35: =S35-1/3*(I35+L35) -> 13174.631 | V35: =S35 -> 17180.299
G36: 33 | H36: =H35-J36 -> 3070149.6 | I36: =$E$9/$E$13*H35 -> 10251.1 | J36: =K36-I36 -> 5180.5051 | K36: =IF(G36>$E$14,0,$E$16) -> 15431.606 | L36: =$E$10/$E$13*H35 -> 1745.7624 | S36: =K36+L36 -> 17177.368 | T36: =S36-1/3*(I36+L36) -> 13178.414 | V36: =S36 -> 17177.368
G37: 34 | H37: =H36-J37 -> 3064951.8 | I37: =$E$9/$E$13*H36 -> 10233.832 | J37: =K37-I37 -> 5197.7735 | K37: =IF(G37>$E$14,0,$E$16) -> 15431.606 | L37: =$E$10/$E$13*H36 -> 1742.8216 | S37: =K37+L37 -> 17174.427 | T37: =S37-1/3*(I37+L37) -> 13182.209 | V37: =S37 -> 17174.427
G38: 35 | H38: =H37-J38 -> 3059736.7 | I38: =$E$9/$E$13*H37 -> 10216.506 | J38: =K38-I38 -> 5215.0994 | K38: =IF(G38>$E$14,0,$E$16) -> 15431.606 | L38: =$E$10/$E$13*H37 -> 1739.871 | S38: =K38+L38 -> 17171.477 | T38: =S38-1/3*(I38+L38) -> 13186.017 | V38: =S38 -> 17171.477
A39: NETTOYDELSEN PR. TERMIN FREMGÅR AF KOLONNE T | G39: 36 | H39: =H38-J39 -> 3054504.3 | I39: =$E$9/$E$13*H38 -> 10199.122 | J39: =K39-I39 -> 5232.483 | K39: =IF(G39>$E$14,0,$E$16) -> 15431.606 | L39: =$E$10/$E$13*H38 -> 1736.9106 | S39: =K39+L39 -> 17168.516 | T39: =S39-1/3*(I39+L39) -> 13189.838 | V39: =S39 -> 17168.516
G40: 37 | H40: =H39-J40 -> 3049254.3 | I40: =$E$9/$E$13*H39 -> 10181.681 | J40: =K40-I40 -> 5249.9246 | K40: =IF(G40>$E$14,0,$E$16) -> 15431.606 | L40: =$E$10/$E$13*H39 -> 1733.9403 | S40: =K40+L40 -> 17165.546 | T40: =S40-1/3*(I40+L40) -> 13193.672 | V40: =S40 -> 17165.546
G41: 38 | H41: =H40-J41 -> 3043986.9 | I41: =$E$9/$E$13*H40 -> 10164.181 | J41: =K41-I41 -> 5267.4244 | K41: =IF(G41>$E$14,0,$E$16) -> 15431.606 | L41: =$E$10/$E$13*H40 -> 1730.96 | S41: =K41+L41 -> 17162.566 | T41: =S41-1/3*(I41+L41) -> 13197.518 | V41: =S41 -> 17162.566
G42: 39 | H42: =H41-J42 -> 3038701.9 | I42: =$E$9/$E$13*H41 -> 10146.623 | J42: =K42-I42 -> 5284.9825 | K42: =IF(G42>$E$14,0,$E$16) -> 15431.606 | L42: =$E$10/$E$13*H41 -> 1727.9699 | S42: =K42+L42 -> 17159.575 | T42: =S42-1/3*(I42+L42) -> 13201.378 | V42: =S42 -> 17159.575
G43: 40 | H43: =H42-J43 -> 3033399.3 | I43: =$E$9/$E$13*H42 -> 10129.006 | J43: =K43-I43 -> 5302.5991 | K43: =IF(G43>$E$14,0,$E$16) -> 15431.606 | L43: =$E$10/$E$13*H42 -> 1724.9698 | S43: =K43+L43 -> 17156.575 | T43: =S43-1/3*(I43+L43) -> 13205.25 | V43: =S43 -> 17156.575
G44: 41 | H44: =H43-J44 -> 3028079.1 | I44: =$E$9/$E$13*H43 -> 10111.331 | J44: =K44-I44 -> 5320.2744 | K44: =IF(G44>$E$14,0,$E$16) -> 15431.606 | L44: =$E$10/$E$13*H43 -> 1721.9597 | S44: =K44+L44 -> 17153.565 | T44: =S44-1/3*(I44+L44) -> 13209.135 | V44: =S44 -> 17153.565
G45: 42 | H45: =H44-J45 -> 3022741 | I45: =$E$9/$E$13*H44 -> 10093.597 | J45: =K45-I45 -> 5338.0087 | K45: =IF(G45>$E$14,0,$E$16) -> 15431.606 | L45: =$E$10/$E$13*H44 -> 1718.9395 | S45: =K45+L45 -> 17150.545 | T45: =S45-1/3*(I45+L45) -> 13213.033 | V45: =S45 -> 17150.545
G46: 43 | H46: =H45-J46 -> 3017385.2 | I46: =$E$9/$E$13*H45 -> 10075.803 | J46: =K46-I46 -> 5355.802 | K46: =IF(G46>$E$14,0,$E$16) -> 15431.606 | L46: =$E$10/$E$13*H45 -> 1715.9093 | S46: =K46+L46 -> 17147.515 | T46: =S46-1/3*(I46+L46) -> 13216.944 | V46: =S46 -> 17147.515
G47: 44 | H47: =H46-J47 -> 3012011.6 | I47: =$E$9/$E$13*H46 -> 10057.951 | J47: =K47-I47 -> 5373.6547 | K47: =IF(G47>$E$14,0,$E$16) -> 15431.606 | L47: =$E$10/$E$13*H46 -> 1712.869 | S47: =K47+L47 -> 17144.475 | T47: =S47-1/3*(I47+L47) -> 13220.868 | V47: =S47 -> 17144.475
G48: 45 | H48: =H47-J48 -> 3006620 | I48: =$E$9/$E$13*H47 -> 10040.039 | J48: =K48-I48 -> 5391.5669 | K48: =IF(G48>$E$14,0,$E$16) -> 15431.606 | L48: =$E$10/$E$13*H47 -> 1709.8186 | S48: =K48+L48 -> 17141.424 | T48: =S48-1/3*(I48+L48) -> 13224.805 | V48: =S48 -> 17141.424
G49: 46 | H49: =H48-J49 -> 3001210.5 | I49: =$E$9/$E$13*H48 -> 10022.067 | J49: =K49-I49 -> 5409.5388 | K49: =IF(G49>$E$14,0,$E$16) -> 15431.606 | L49: =$E$10/$E$13*H48 -> 1706.758 | S49: =K49+L49 -> 17138.363 | T49: =S49-1/3*(I49+L49) -> 13228.755 | V49: =S49 -> 17138.363
G50: 47 | H50: =H49-J50 -> 2995782.9 | I50: =$E$9/$E$13*H49 -> 10004.035 | J50: =K50-I50 -> 5427.5706 | K50: =IF(G50>$E$14,0,$E$16) -> 15431.606 | L50: =$E$10/$E$13*H49 -> 1703.6872 | S50: =K50+L50 -> 17135.293 | T50: =S50-1/3*(I50+L50) -> 13232.719 | V50: =S50 -> 17135.293
G51: 48 | H51: =H50-J51 -> 2990337.3 | I51: =$E$9/$E$13*H50 -> 9985.943 | J51: =K51-I51 -> 5445.6625 | K51: =IF(G51>$E$14,0,$E$16) -> 15431.606 | L51: =$E$10/$E$13*H50 -> 1700.6061 | S51: =K51+L51 -> 17132.212 | T51: =S51-1/3*(I51+L51) -> 13236.695 | V51: =S51 -> 17132.212
... G123: 120 | H123: =H122-J123 -> 2546552.2 | I123: =$E$9/$E$13*H122 -> 8511.5742 | J123: =K123-I123 -> 6920.0313 | K123: =IF(G123>$E$14,0,$E$16) -> 15431.606 | L123: =$E$10/$E$13*H122 -> 1449.5211 | S123: =K123+L123 -> 16881.127 | T123: =S123-1/3*(I123+L123) -> 13560.762 | V123: =S123 -> 16881.127
G124: 121 | H124: =H123-J124 -> 2539609.1 | I124: =$E$9/$E$13*H123 -> 8488.5074 | J124: =K124-I124 -> 6943.0981 | K124: =IF(G124>$E$14,0,$E$16) -> 15431.606 | L124: =$E$10/$E$13*H123 -> 1445.5928 | S124: =K124+L124 -> 16877.198 | T124: =S124-1/3*(I124+L124) -> 13565.832
G125: 122 | H125: =H124-J125 -> 2532642.9 | I125: =$E$9/$E$13*H124 -> 8465.3637 | J125: =K125-I125 -> 6966.2418 | K125: =IF(G125>$E$14,0,$E$16) -> 15431.606 | L125: =$E$10/$E$13*H124 -> 1441.6514 | S125: =K125+L125 -> 16873.257 | T125: =S125-1/3*(I125+L125) -> 13570.919
G126: 123 | H126: =H125-J126 -> 2525653.4 | I126: =$E$9/$E$13*H125 -> 8442.1429 | J126: =K126-I126 -> 6989.4626 | K126: =IF(G126>$E$14,0,$E$16) -> 15431.606 | L126: =$E$10/$E$13*H125 -> 1437.6969 | S126: =K126+L126 -> 16869.302 | T126: =S126-1/3*(I126+L126) -> 13576.022
G127: 124 | H127: =H126-J127 -> 2518640.7 | I127: =$E$9/$E$13*H126 -> 8418.8447 | J127: =K127-I127 -> 7012.7608 | K127: =IF(G127>$E$14,0,$E$16) -> 15431.606 | L127: =$E$10/$E$13*H126 -> 1433.7293 | S127: =K127+L127 -> 16865.335 | T127: =S127-1/3*(I127+L127) -> 13581.143
G128: 125 | H128: =H127-J128 -> 2511604.5 | I128: =$E$9/$E$13*H127 -> 8395.4688 | J128: =K128-I128 -> 7036.1367 | K128: =IF(G128>$E$14,0,$E$16) -> 15431.606 | L128: =$E$10/$E$13*H127 -> 1429.7483 | S128: =K128+L128 -> 16861.354 | T128: =S128-1/3*(I128+L128) -> 13586.281
G129: 126 | H129: =H128-J129 -> 2504544.9 | I129: =$E$9/$E$13*H128 -> 8372.0151 | J129: =K129-I129 -> 7059.5905 | K129: =IF(G129>$E$14,0,$E$16) -> 15431.606 | L129: =$E$10/$E$13*H128 -> 1425.7542 | S129: =K129+L129 -> 16857.36 | T129: =S129-1/3*(I129+L129) -> 13591.437
G130: 127 | H130: =H129-J130 -> 2497461.8 | I130: =$E$9/$E$13*H129 -> 8348.4831 | J130: =K130-I130 -> 7083.1224 | K130: =IF(G130>$E$14,0,$E$16) -> 15431.606 | L130: =$E$10/$E$13*H129 -> 1421.7467 | S130: =K130+L130 -> 16853.352 | T130: =S130-1/3*(I130+L130) -> 13596.609
G131: 128 | H131: =H130-J131 -> 2490355.1 | I131: =$E$9/$E$13*H130 -> 8324.8727 | J131: =K131-I131 -> 7106.7328 | K131: =IF(G131>$E$14,0,$E$16) -> 15431.606 | L131: =$E$10/$E$13*H130 -> 1417.7258 | S131: =K131+L131 -> 16849.331 | T131: =S131-1/3*(I131+L131) -> 13601.798
G132: 129 | H132: =H131-J132 -> 2483224.6 | I132: =$E$9/$E$13*H131 -> 8301.1836 | J132: =K132-I132 -> 7130.4219 | K132: =IF(G132>$E$14,0,$E$16) -> 15431.606 | L132: =$E$10/$E$13*H131 -> 1413.6916 | S132: =K132+L132 -> 16845.297 | T132: =S132-1/3*(I132+L132) -> 13607.005
G133: 130 | H133: =H132-J133 -> 2476070.5 | I133: =$E$9/$E$13*H132 -> 8277.4155 | J133: =K133-I133 -> 7154.19 | K133: =IF(G133>$E$14,0,$E$16) -> 15431.606 | L133: =$E$10/$E$13*H132 -> 1409.6439 | S133: =K133+L133 -> 16841.249 | T133: =S133-1/3*(I133+L133) -> 13612.23
G134: 131 | H134: =H133-J134 -> 2468892.4 | I134: =$E$9/$E$13*H133 -> 8253.5682 | J134: =K134-I134 -> 7178.0373 | K134: =IF(G134>$E$14,0,$E$16) -> 15431.606 | L134: =$E$10/$E$13*H133 -> 1405.5827 | S134: =K134+L134 -> 16837.188 | T134: =S134-1/3*(I134+L134) -> 13617.471
G135: 132 | H135: =H134-J135 -> 2461690.5 | I135: =$E$9/$E$13*H134 -> 8229.6414 | J135: =K135-I135 -> 7201.9641 | K135: =IF(G135>$E$14,0,$E$16) -> 15431.606 | L135: =$E$10/$E$13*H134 -> 1401.5079 | S135: =K135+L135 -> 16833.113 | T135: =S135-1/3*(I135+L135) -> 13622.73
... G363: 360 | H363: =H362-J363 -> 1.7062121e-09 | I363: =$E$9/$E$13*H362 -> 51.267792 | J363: =K363-I363 -> 15380.338 | K363: =IF(G363>$E$14,0,$E$16) -> 15431.606 | L363: =$E$10/$E$13*H362 -> 8.730905 | S363: =K363+L363 -> 15440.336 | T363: =S363-1/3*(I363+L363) -> 15420.337

Sheet Andelsboliglån
B1: Skriv i de gule felter
B3: Lånets størrelse (hovedstolen) | E3: jf. J11 og D15 | G3: vi "sjusser os frem"
B4: Løbetid, år | D4: 30
B5: Antal terminer pr. år | D5: 12
B6: Rente pr år, (pålydende/nominel) | D6: 0.05 | E6: 4,5%-7,75% (var, mulighed for afdragsfirhed) - 7%-12% (fast op til 10 år) Løbetid op ti 30 år / Nordea
B7: Effektiv rente pr. år | D7: =EFFECT(D6,D5) -> 0.051161898
B9: Etableringsomkostninger: | H9: Andelspris
B10: Staten, tinglysning | D10: =1825+1.45%*D3 -> 1825 | H10: - opsparing
B11: Pengeinstitut, etablering | D11: 5000 | E11: anslået | H11: Lånebehov | J11: =J9-J10 -> 0
B13: Etableringsomkostninger i alt | D13: =SUM(D10:D12) -> 6825
B15: Provenu (hvad får jeg i hånden) | D15: =D3-D13 -> -6825 | E15: som passer meget godt med lånebehov + flyttemand og maling, jf. J11
B17: Omkostninger i procent pr. termin | D17: =RATE(D4*D5,-D21,D15) -> #NUM!
B18: ÅOP | D18: =(1+D17)^D5-1 -> #NUM!
B21: Ydelse pr. termin før skat | D21: =-PMT(D6/D5,D4*D5,D3) -> 0
B23: Renteudgifter år 1 | D23: =-CUMIPMT(D6/D5,D4*D5,D3,1,D5,0) -> #NUM!
B24: Skattefar betaler 1/3 | D24: =1/3*D23 -> #NUM!
B25: Skattebesparelse pr. termin | D25: =D24/D5 -> #NUM!
B27: Ydelse pr. termin efter skat | D27: =D21-D25 -> #NUM!

Sheet Andelsværdiberegner
B2: SKRIV KUN I DE GULE FELTER (medmindre man gør det bevidst)
B4: Beregn fordelingstal
B5: =B9 -> Andelsboligens andel af andelsforeningen (fordelingstal) | F5: = | G5: (Opr. bolig indskud) | I5: eller | J5: Bolig KVM | T5: Brug en af de tre forholdstal
G6: (Opr. samlede indskud) | J6: Samlede KVM | M6: Eller det forholdstal som står i salgsopstillingen
B9: Andelsboligens andel af andelsforeningen (fordelingstal) | F9: = | G9: 0 | I9: = | J9: =G9/G10 -> #DIV/0!
G10: 0 | T10: Fordelingstal bruges bl.a til at opgøre den enkeltes andelshavers andel af:
T11: 1) Foreningens gæld og formue, 2) andel af den samlede husleje
B14: Beregn andelsværdi og maksimalpris
B16: Ejendommens samlede værdi + øvrige aktiver | H16: 10000000 | K16: Forbedringer på boligen | M16: 0
B17: Heraf øvrige aktiver (hvis det er oplyst)
B19: Foreningens samlede gæld | H19: 0
B21: Boligens andelsværdi | H21: =(H16-H19)*J9 -> #DIV/0! | K21: Maksimalpris | M21: =H21+M16 -> #DIV/0! | T21: Maksimalpris er det du højst må sælge boligen for
B22: (Ejendommens samlede værdi + øvrige aktiver - foreningens samlede gæld * fordelingstal) | K22: Boligens andelsværdi + forbedringer
B26: Beregn teknisk pris
B27: Teknisk pris | D27: = | E27: Købspris = maksimal pris minus evt afslag | G27: + | H27: Boligens andel af foreningens gæld | J27: - | K27: Boligens andel af øvrige aktiver | M27: => | N27: =B27 -> Teknisk pris
E29: Evt. afslag: | F29: 0
B31: Teknisk pris | D31: = | E31: =M21-F29 -> #DIV/0! | G31: + | H31: =H19*J9 -> #DIV/0! | J31: - | K31: =H17*J9 -> #DIV/0! | M31: = | O31: =E31+H31-K31 -> #DIV/0! | T31: Bruges til at beregne udbetalingen på 5% af den tekniske pris
T32: Bruges også til at sammenligne andelsboligen med en ejerlejligheds kontant pris.
B36: Andelsværdi beregnet ud fra andelskronen (bare en anden måde at gøre det på)
B37: Andelskrone | C37: = | D37: Ejendommensværdi + øvrige aktiver - foreningens gæld | L37: => | M37: =H16-H19 -> 10000000 | P37: = | Q37: =M37/M38 -> #DIV/0! | T37: Andelskronen er et udtryk for værdien pr. kvm. eller pr. oprindeligt indskudt krone
D38: Opr. Samlet indskud eller Samlede KVM | M38: =G10 -> 0
B41: Boligens andelsværdi | D41: = | E41: Opr. bolig Indskud eller bolig kvm. | I41: * | J41: =B37 -> Andelskrone | L41: => | M41: =G9 -> 0 | N41: * | O41: =Q37 -> #DIV/0! | P41: = | Q41: =M41*O41 -> #DIV/0!

Sheet Forældrekøb
C3: Forudsætninger: | J3: Hvis der vælges et lån med afdrag skal afdraget også forstås som en indtægt, da det er opsparing i boligen.
J4: Hvis man også skal låne til banklånet (15%) så bliver udgifterne større. Også her kan renterne kun trækkes fra i kapitalindkomsten.
C5: - Begge forældre betaler topskat | J5: Brug evt følgende beregner til beregning af lån med både banklån og realkreditlån | N5: http://boligregner.dk/beregn
C6: - Forældrenes samlede renteudgifter inkl. forældrekøb er < 100.000
C7: - Familien er ikke medlem af folkekirken
C8: - Forældrene forudsættes at have til udbetaling/banklån og papirpenge svarende til 20% | J8: Der må kun skrives i de gule felter
C11: Finansieringen | J11: Barnet: | M11: Udeboende SU | N11: Hjemme SU
H12: Uden afdrag | I12: Med afdrag | J12: Mer SU for udeboende pr år: | L12: 0 | M12: 7086 | N12: 1101
C13: Lejlighedens pris | H13: 0 | I13: 0
J14: Forventet boligstøtte pr år: | L14: 0 | M14: 15% af markedshuslejen | N14: Beregn boligstøtte
C15: Udbetaling 20% | H15: 0 | I15: 0
C16: Papirpenge | H16: =0.6%*H13+1850+1.45%*H18+1825+10000+0.2%*H19+13000 -> #DIV/0! | I16: =0.6%*I13+1850+1.45%*I18+1825+10000+0.2%*I19+13000 -> #DIV/0! | J16: Besparelse transport pr år : | L16: 0 | M16: Tog kort: 663,00
C18: Hovedstol | H18: =H19/H20*100 -> #DIV/0! | I18: =I19/I20*100 -> #DIV/0!
C19: Realkredit 80% | H19: =H13*0.8 -> 0 | I19: =I13*0.8 -> 0 | J19: Marginalskatteprocent for PI | L19: =0.238+0.1211 -> 0.3591 | M19: Betaler ikke AM-bidrag som SU-modtager
C20: Realkreditlån, 30 år | G20: Kurs | H20: 0 | I20: 0
C21: Rentesats | H21: 0 | I21: 0
C22: Bidragssats | H22: 0.009564 | I22: 0.006812
C23: Terminer | H23: 4 | I23: 4 | J23: Forældrene:
C24: Terminer i alt | H24: =H23*30 -> 120 | I24: =I23*30 -> 120 | J24: Marginalskatteprocent for PI | L24: 0.56 | M24: incl AM-bidrag
C26: Årlig ydelse | H26: =H27+H28 -> #DIV/0! | I26: =-PMT(I21/4,120,I18,0)*4 -> #DIV/0! | J26: Fradrag i renteudgifter | L26: 0.33
C27: Årlig rente | H27: =H21*H18 -> #DIV/0! | I27: =-CUMIPMT(I21/4,I24,I18,1,4,0) -> #DIV/0!
C28: Årlig bidrag | H28: =H22*H18 -> #DIV/0! | I28: =I18*I22/I23+(I18+CUMPRINC(I21/I23,I24,I18,1,1,0))*I22/I23+(I18+CUMPRINC(I21/I23,I24,I18,1,2,0))*I22/I23+(I18+CUMPRINC(I21/I23,I24,I18,1,3,0))*I22/I23 -> #DIV/0!
C29: Årlig afdrag | H29: 0 | I29: =-CUMPRINC(I21/4,120,I18,1,4,0) -> #DIV/0!
C31: Markedshuslejen (årligt) | H31: 0 | I31: 0
C33: Ejerudgifter (årligt) | H33: 0 | I33: 0
C34: - heraf ejendomsværdiskat | H34: 0 | I34: 0 | J34: Man betaler ikke ejendomsværdiskat v/forældrekøb
C35: Udgifter eksl ejendsværdiskat | H35: =H33-H34 -> 0 | I35: =I33-I34 -> 0
C37: Forældrekøb eller køber selv | I37: Forældrekøb Virksomheds- skatteordning*) u/afdrag | J37: Forældrekøb Personskatte- ordning u/afdrag (løsning A) | K37: Forældrekøb Personskatte- ordning m/afdrag | L37: Barnet køber selv u/afdrag*) (løsning B)
C38: Forældre (ændringerne i forældrenes økonomi):
C39: Samlede Indtægter | I39: =H31 -> 0 | L39: 0 | M39: Hvad får forældrene ind af penge
C41: Samlede Udgifter | I41: =H26+H35 -> #DIV/0! | L41: 0 | M41: Hvad skal forældrene betale
C43: Netto udgift | I43: =I41-I39 -> #DIV/0! | J43: =J41-J39 -> 0 | K43: =K41-K39 -> 0 | L43: 0 | M43: Her regner vi ud hvad det koster forældrene
C45: Ændring i PI (Personlig indkomst) | I45: =H31-H35-H27-H28 -> #DIV/0! | L45: 0 | M45: Hvor meget ændrer den personlige indkomst sig
C47: Ændring i KI (Kapital indkomst) | I47: 0 | L47: 0 | M47: Hvor meget ændrer kapitalindkomsten sig
C49: Merskat (minus betyder sparet skat) | I49: =I45*L24 -> #DIV/0! | J49: =J45*$L$24+(J47)*$L$26 -> 0 | K49: =K45*$L$24+(K47)*$L$26 -> 0 | L49: 0 | M49: Her regner vi ud hvad de sparer i skat
C51: fratræk evt afdrag på lån (=opsparing i bolig) | I51: 0 | J51: 0 | L51: 0 | M51: Her gør vi udgifterne lavere, da afdrag på lån svarer til opsparing i boligen
C52: Netto udgift efter skat | I52: =I43+I49 -> #DIV/0! | J52: =J43+J49-J51 -> 0 | K52: =K43+K49-K51 -> 0 | L52: 0
C54: Barnet (ændringerne i barnets økonomi):
C55: Indtægter:
C56: - Mer SU | I56: =L12 -> 0 | M56: Forskellen på udeboende og hjemmeboende
C57: - Boligsikring/støtte | I57: =L14 -> 0
C58: - Sparet transport | I58: =L16 -> 0
C60: Indtægter i alt | I60: =SUM(I56:I59) -> 0 | J60: =SUM(J56:J59) -> 0 | K60: =SUM(K56:K59) -> 0 | L60: =SUM(L56:L59) -> 0
C62: Udgifter
C63: - husleje | I63: =I31 -> 0 | M63: køber man selv betaler man også ejemdomsværdiskat
C64: - forbrugsudgifter | I64: 10000 | J64: 10000 | K64: =J64 -> 10000 | L64: =J64 -> 10000
C66: Udgifter i alt | I66: =SUM(I63:I65) -> 10000 | J66: =SUM(J63:J65) -> 10000 | K66: =K63+K64 -> 10000 | L66: =SUM(L63:L65) -> 10000
C68: Skat af mer SU | I68: =((I56)-(48000-12000))*$L$19 -> -12927.6 | J68: =((J56)-(48000-12000))*$L$19 -> -12927.6 | K68: =((K56)-(48000-12000))*$L$19 -> -12927.6 | L68: =((L56)-(48000-12000))*$L$19 -> -12927.6
C69: Skattefradrag renteudgifter + bidrag | I69: 0 | J69: 0 | K69: 0 | L69: =0.33*-(H26) -> #DIV/0!
C71: Netto indtægt efter skat | I71: =I60-I66-I68 -> 2927.6 | J71: =J60-J66-J68 -> 2927.6 | K71: =K60-K66-K68 -> 2927.6 | L71: =L60-L66-L68-L69 -> #DIV/0!
C73: Familiens samlede påvirkning på økonomien | I73: =I71-I52 -> #DIV/0! | J73: =J71-J52 -> 2927.6 | K73: =K71-K52 -> 2927.6 | L73: =L52+L71 -> #DIV/0!
I74: *Er ikke relevant | L74: * får udbetaling og papirpenge som "gave" - fx nul procent anfordringsfrit familielån (dvs 20%+papirpenge)
I75: pr 1. jan 2021 | L75: Hvis barnet ikke kan kreditvurderes til realkreditlånet kan forældrene enten kautionere elle stå som meddebitor på realkreditlånet i stedet for kaution. Afdrag på lånet kan ske med afgiftsfrie gave fra forældrene
L76: Man kan også oprette et anfordringsfrit familielån til barnet til køb af hele lejligheden kontant- så er der ingen renteudgifter
C77: Herudover skal huskes: | L77: Afdrag på lånet kan tilbagebetales med de skattefrie gaver man må give sit barn - så er der ingen afdrag
C78: - der kan også fratrækkes op til 25% af huslejen i istandssættelsesudifter i de første 3 år.
C79: - der er mulighed for både tab/gevinst ved efterfølgende salg af lejlighed.

Sheet Investering
H1: Investering (Skriv kun i de gule felter)
G2: 100000 kr
G4: Link til Nasdaq (obligationer): | H4: https://www.nasdaqomxnordic.com/obligationer/danmark/?languageId=5
M5: Hvis DKK skriv 1
G7: Skriv navn på obligationerne | H7: Købskurs | I7: Salgskurs | J7: Antal | K7: Termin | M7: Valutakurs køb | N7: Valutakurs salg | O7: Købssum | P7: Salgssum | Q7: Fordeling | R7: Gevinst/tab | S7: Aktieindkomst | T7: Kapitalindkomst
H8: 100 | I8: 98 | J8: 10 | M8: 1 | N8: 1 | O8: =H8*J8*M8 -> 1000 | P8: =I8*J8*N8 -> 980 | Q8: =P8/$P$27 -> 0.03817686 | R8: =P8-O8 -> -20 | T8: =R8 -> -20
H9: 85 | I9: 99 | J9: 10 | M9: 1 | N9: 1 | O9: =H9*J9*M9 -> 850 | P9: =I9*J9*N9 -> 990 | Q9: =P9/$P$27 -> 0.03856642 | R9: =P9-O9 -> 140 | T9: =R9 -> 140
O10: =H10*J10*M10 -> 0 | P10: =I10*J10*N10 -> 0 | Q10: =P10/$P$27 -> 0 | R10: =P10-O10 -> 0 | T10: =R10 -> 0
O11: =H11*J11*M11 -> 0 | P11: =I11*J11*N11 -> 0 | Q11: =P11/$P$27 -> 0 | R11: =P11-O11 -> 0 | T11: =R11 -> 0
O12: =H12*J12*M12 -> 0 | P12: =I12*J12*N12 -> 0 | Q12: =P12/$P$27 -> 0 | R12: =P12-O12 -> 0 | T12: =R12 -> 0
C13: Ydelse | D13: Disk.faktor | E13: NV | O13: =H13*J13*M13 -> 0 | P13: =I13*J13*N13 -> 0 | Q13: =P13/$P$27 -> 0 | R13: =P13-O13 -> 0 | T13: =R13 -> 0
G14: Obligationer i alt | O14: =SUM(O8:O13) -> 1850 | P14: =SUM(P8:P13) -> 1970 | Q14: =P14/$P$27 -> 0.07674328 | R14: =P14-O14 -> 120
G16: Skriv navn på aktierne
C17: yt | D17: dt | E17: yt*(1+i)-t | H17: 200 | I17: 300 | J17: 4 | M17: 1 | N17: 1 | O17: =H17*J17*M17 -> 800 | P17: =I17*J17*N17 -> 1200 | Q17: =P17/$P$27 -> 0.046747176 | R17: =P17-O17 -> 400 | S17: =R17 -> 400
H18: 150 | I18: 225 | J18: 100 | M18: 1 | N18: 1 | O18: =H18*J18*M18 -> 15000 | P18: =I18*J18*N18 -> 22500 | Q18: =P18/$P$27 -> 0.87650954 | R18: =P18-O18 -> 7500 | S18: =R18 -> 7500
C19: 4 | D19: =(1+$E$32)^-#REF! -> #REF! | E19: =D19*C19 -> #REF! | O19: =H19*J19*M19 -> 0 | P19: =I19*J19*N19 -> 0 | Q19: =P19/$P$27 -> 0 | R19: =P19-O19 -> 0 | S19: =R19 -> 0
C20: 4 | D20: =(1+$E$32)^-#REF! -> #REF! | E20: =D20*C20 -> #REF! | O20: =H20*J20*M20 -> 0 | P20: =I20*J20*N20 -> 0 | Q20: =P20/$P$27 -> 0 | R20: =P20-O20 -> 0 | S20: =R20 -> 0
C21: 4 | D21: =(1+$E$32)^-#REF! -> #REF! | E21: =D21*C21 -> #REF! | O21: =H21*J21*M21 -> 0 | P21: =I21*J21*N21 -> 0 | Q21: =P21/$P$27 -> 0 | R21: =P21-O21 -> 0 | S21: =R21 -> 0
C22: 4 | D22: =(1+$E$32)^-#REF! -> #REF! | E22: =D22*C22 -> #REF! | O22: =H22*J22*M22 -> 0 | P22: =I22*J22*N22 -> 0 | Q22: =P22/$P$27 -> 0 | R22: =P22-O22 -> 0 | S22: =R22 -> 0
C23: 4 | D23: =(1+$E$32)^-#REF! -> #REF! | E23: =D23*C23 -> #REF! | O23: =H23*J23*M23 -> 0 | P23: =I23*J23*N23 -> 0 | Q23: =P23/$P$27 -> 0 | R23: =P23-O23 -> 0 | S23: =R23 -> 0
C24: 4 | D24: =(1+$E$32)^-#REF! -> #REF! | E24: =D24*C24 -> #REF!
C25: 4 | D25: =(1+$E$32)^-#REF! -> #REF! | E25: =D25*C25 -> #REF! | G25: Aktier i alt | O25: =SUM(O17:O24) -> 15800 | P25: =SUM(P17:P24) -> 23700 | Q25: =P25/$P$27 -> 0.92325672 | R25: =P25-O25 -> 7900
C27: 4 | D27: =(1+$E$32)^-#REF! -> #REF! | E27: =D27*C27 -> #REF! | G27: Samlet portefølje | O27: =O14+O25 -> 17650 | P27: =P14+P25 -> 25670 | Q27: =P27/$P$27 -> 1 | R27: =R14+R25 -> 8020
C28: 4 | D28: =(1+$E$32)^-#REF! -> #REF! | E28: =D28*C28 -> #REF!
C29: 4 | D29: =(1+$E$32)^-#REF! -> #REF! | E29: =D29*C29 -> #REF! | G29: Vedhængende rente | T29: =J85 -> 0
C30: 104 | D30: =(1+$E$32)^-#REF! -> #REF! | E30: =D30*C30 -> #REF!
D31: ∑ | E31: =SUM(E18:E30) -> #REF! | G31: Skattegrundlag | S31: =SUM(S17:S30) -> 7900 | T31: =SUM(T8:T29) -> 120
E32: 0.036604446 | G32: Skattebetaling | S32: =J37+J38+L37+L38 -> 0 | T32: =J35+J36+L35+L36 -> 0 | U32: Skat i alt | V32: =S32+T32 -> 0
G34: SKAT | H34: SATS | I34: Grænse ægtepar | J34: Skat ægtepar | K34: Grænse single | L34: Skat single
G35: Kapitalindkomst under grænsen | H35: 0.37 | I35: =KItilTopskatPar -> 104800 | K35: =KItilTopskatEnlig -> 52400
G36: Kapitalindkomst over grænsen hvis man også er topskatte betaler. Ellers 37% | H36: 0.42 | I36: =I35 -> 104800 | K36: =K35 -> 52400
G37: Aktieindkomst under grænsen | H37: 0.27 | I37: =2*K37 -> 126600 | K37: 63300
G38: Aktieindkomst over grænsen | H38: 0.42 | I38: =I37 -> 126600 | K38: =K37 -> 63300
G40: "I hånden"
G41: Salgssum | H41: =P27 -> 25670
G42: + vedhængende rente | H42: =T29 -> 0
G43: - skat | H43: =V32 -> 0
G44: I hånden efter skat" | H44: =H41+H42-H43 -> 25670
G46: Vedhængende renter: | K46: Husk at gange rente betalingen med valutakursen hvis det er udenlandske obligationer
G47: Obligationens navn
G48: Angiv kuponrente men IKKE i procent | H48: 0 | I48: fx 3
C52: =#REF! -> #REF! | G52: Valør | H52: 45061 | I52: skriv dags dato
C53: 39767 | G53: Forringe termin | H53: 44880 | I53: skriv hvornår der senest blev tilskrevet renter
C54: =C52-C53 -> #REF! | G54: Dage | H54: =H52-H53 -> 181
I55: Antal obligationer | J55: Rente betaling
C56: =(4*C54)/(365*1) -> #REF! | G56: Vedhængende rente | H56: =H48*H54/365 -> 0 | I56: =J8 -> 10 | J56: =I56*H56 -> 0
G59: Obligationens nvan
G60: Angiv kuponrente men IKKE i procent | H60: 0
G61: Valør | H61: 45061
G62: Forrige termin | H62: 45017
G63: Dage | H63: =H61-H62 -> 44
G65: Vedhængende rente | H65: =H60*H63/365 -> 0 | I65: =J9 -> 10 | J65: =I65*H65 -> 0
G68: Obligationens nvan
G69: Angiv kuponrente men IKKE i procent
G70: Valør
G71: Forrige termin
G72: Dage | H72: =H70-H71 -> 0
G74: Vedhængende rente | H74: =H69*H72/365 -> 0 | I74: =J10 -> 0 | J74: =I74*H74 -> 0
G77: Obligationens nvan
G78: Angiv kuponrente men IKKE i procent
G79: Valør
G80: Forrige termin
G81: Dage | H81: =H79-H80 -> 0
G83: Vedhængende rente | H83: =H78*H81/365 -> 0 | I83: =J11 -> 0 | J83: =I83*H83 -> 0
G85: Samlet vedhængende rente | J85: =J74+J65+J56+J83 -> 0

Sheet Hvor meget har jeg at leve for
B1: Formue fordelt ud på år
B4: Formue i alt | C4: 0
B6: Inv.rente efter skat | C6: 0 | D6: (hvad kan jeg få i afkast om året)
B7: Antal år | C7: 40 | D7: (hvor mange år skal jeg leve af min forme)
B8: Penge tilbage efter perioden | C8: 0 | D8: (hvor mange penge skal der stå tilbage på kontoen til sidst - f.eks. til arvinger eller lign.)
B10: Hvor meget kan jeg leve for pr. år | C10: =-PMT(C6,C7,C4,-C8) -> 0

Sheet Pensionsberegner 2025
C2: indbetaling før omk. | D2: =D4/0.8 -> 0 | E2: =D2/12 -> 0 | F2: pr. mdr
B3: helårlig rentetilskrivning i opsparingsperioden | F3: 2025 | G3: helårlig rentetilskrivning
C4: indbetaling efter omk. | D4: 0 | E4: nuv. pensionsformue | F4: 0 | G4: I udbetalingsperioden
C5: inflation | D5: 0.015 | E5: til forrentning i antal år | F5: 0 | H5: inflation | I5: 0.015 | M5: 1 | N5: Friværdi i bolig bør også indgå i det samlede overblik
C6: afkast | D6: 0.05 | E6: =(1+$D$6/2)^2-1 -> 0.050625 | H6: afkast | I6: 0.03 | K6: friværdi + anden formue | M6: 2 | N6: Omkostninger =Forsikringer, adm & AMB udgør i gns. Ca 20 % af indbetalingerne
C7: pal skat | D7: 0.153 | E7: FV af pensionsformue | F7: =FV($D$6*(1-$D$7),$F$5,0,-$F$4) -> 0 | H7: pal skat | I7: 0.153 | K7: 0 | M7: 3 | N7: Anden formue (kapitalpension, værdipapir, frie midler osv)
E8: NV af pensionsformue | F8: =PV($D$5,$F$5,0,-$F$7) -> 0 | G8: tidspunkt | H8: udbetaling | I8: pensionsformue | K8: =K7/20 -> 0 | L8: netto | M8: 4 | N8: Husk at skrive ind hvad du mener er afkastprocenten og inflationsprocenten. Både under indb og udb perioderne
B9: primo | C9: årlig indbetaling | D9: Rente | E9: ultimo | F9: nutidsværdi | G9: 0 | I9: =VLOOKUP(F5,B3:F59,5,FALSE)+F8 -> #N/A | K9: =K8/0.63 -> 0 | L9: brutto ***
B10: 1 | C10: =D4 -> 0 | D10: =C10/2*(1-$D$7)*$D$6 -> 0 | E10: =C10+D10 -> 0 | F10: =PV($D$5,B10,0,-E10) -> 0 | G10: =G9+1 -> 1 | H10: 0 | I10: =(I9-H10/2)*$I$6*(1-$I$7)+I9-H10 -> #N/A
B11: =B10+1 -> 2 | C11: =D4*(1+$D$5) -> 0 | D11: =(E10+C11/2)*(1-$D$7)*$D$6 -> 0 | E11: =E10+C11+D11 -> 0 | F11: =PV($D$5,B11,0,-E11) -> 0 | G11: =G10+1 -> 2 | H11: =H10*(1+$I$5) -> 0 | I11: =(I10-H11/2)*$I$6*(1-$I$7)+I10-H11 -> #N/A | J11: Målsøgning findes under :DATA-Hvad hvis- analyse
B12: =B11+1 -> 3 | C12: =C11*(1+$D$5) -> 0 | D12: =(E11+C12/2)*(1-$D$7)*$D$6 -> 0 | E12: =E11+C12+D12 -> 0 | F12: =PV($D$5,B12,0,-E12) -> 0 | G12: =G11+1 -> 3 | H12: =H11*(1+$I$5) -> 0 | I12: =(I11-H12/2)*$I$6*(1-$I$7)+I11-H12 -> #N/A | O12: Folkepension 2025 | Q12: pr. mdr | R12: pr. år
B13: =B12+1 -> 4 | C13: =C12*(1+$D$5) -> 0 | D13: =(E12+C13/2)*(1-$D$7)*$D$6 -> 0 | E13: =E12+C13+D13 -> 0 | F13: =PV($D$5,B13,0,-E13) -> 0 | G13: =G12+1 -> 4 | H13: =H12*(1+$I$5) -> 0 | I13: =(I12-H13/2)*$I$6*(1-$I$7)+I12-H13 -> #N/A | J13: What if analyse kan også laves på indbetalingerne | P13: Grundbeløb | Q13: 7198 | R13: =Q13*12 -> 86376
B14: =B13+1 -> 5 | C14: =C13*(1+$D$5) -> 0 | D14: =(E13+C14/2)*(1-$D$7)*$D$6 -> 0 | E14: =E13+C14+D14 -> 0 | F14: =PV($D$5,B14,0,-E14) -> 0 | G14: =G13+1 -> 5 | H14: =H13*(1+$I$5) -> 0 | I14: =(I13-H14/2)*$I$6*(1-$I$7)+I13-H14 -> #N/A | J14: samt alle de gule felter (husk ingen formler) | P14: tillæg enlig | Q14: 8329 | R14: =Q14*12 -> 99948
B15: =B14+1 -> 6 | C15: =C14*(1+$D$5) -> 0 | D15: =(E14+C15/2)*(1-$D$7)*$D$6 -> 0 | E15: =E14+C15+D15 -> 0 | F15: =PV($D$5,B15,0,-E15) -> 0 | G15: =G14+1 -> 6 | H15: =H14*(1+$I$5) -> 0 | I15: =(I14-H15/2)*$I$6*(1-$I$7)+I14-H15 -> #N/A | P15: tillæg par | Q15: 4262 | R15: =Q15*12 -> 51144
B16: =B15+1 -> 7 | C16: =C15*(1+$D$5) -> 0 | D16: =(E15+C16/2)*(1-$D$7)*$D$6 -> 0 | E16: =E15+C16+D16 -> 0 | F16: =PV($D$5,B16,0,-E16) -> 0 | G16: =G15+1 -> 7 | H16: =H15*(1+$I$5) -> 0 | I16: =(I15-H16/2)*$I$6*(1-$I$7)+I15-H16 -> #N/A
B17: =B16+1 -> 8 | C17: =C16*(1+$D$5) -> 0 | D17: =(E16+C17/2)*(1-$D$7)*$D$6 -> 0 | E17: =E16+C17+D17 -> 0 | F17: =PV($D$5,B17,0,-E17) -> 0 | G17: =G16+1 -> 8 | H17: =H16*(1+$I$5) -> 0 | I17: =(I16-H17/2)*$I$6*(1-$I$7)+I16-H17 -> #N/A | P17: ATP | Q17: pr. mdr | R17: pr. år
B18: =B17+1 -> 9 | C18: =C17*(1+$D$5) -> 0 | D18: =(E17+C18/2)*(1-$D$7)*$D$6 -> 0 | E18: =E17+C18+D18 -> 0 | F18: =PV($D$5,B18,0,-E18) -> 0 | G18: =G17+1 -> 9 | H18: =H17*(1+$I$5) -> 0 | I18: =(I17-H18/2)*$I$6*(1-$I$7)+I17-H18 -> #N/A | P18: Max udbetaling | Q18: =R18/12 -> 2343.25 | R18: 28119
B19: =B18+1 -> 10 | C19: =C18*(1+$D$5) -> 0 | D19: =(E18+C19/2)*(1-$D$7)*$D$6 -> 0 | E19: =E18+C19+D19 -> 0 | F19: =PV($D$5,B19,0,-E19) -> 0 | G19: =G18+1 -> 10 | H19: =H18*(1+$I$5) -> 0 | I19: =(I18-H19/2)*$I$6*(1-$I$7)+I18-H19 -> #N/A
B20: =B19+1 -> 11 | C20: =C19*(1+$D$5) -> 0 | D20: =(E19+C20/2)*(1-$D$7)*$D$6 -> 0 | E20: =E19+C20+D20 -> 0 | F20: =PV($D$5,B20,0,-E20) -> 0 | G20: =G19+1 -> 11 | H20: =H19*(1+$I$5) -> 0 | I20: =(I19-H20/2)*$I$6*(1-$I$7)+I19-H20 -> #N/A | P20: Årsløn før skat | R20: 0
B21: =B20+1 -> 12 | C21: =C20*(1+$D$5) -> 0 | D21: =(E20+C21/2)*(1-$D$7)*$D$6 -> 0 | E21: =E20+C21+D21 -> 0 | F21: =PV($D$5,B21,0,-E21) -> 0 | G21: =G20+1 -> 12 | H21: =H20*(1+$I$5) -> 0 | I21: =(I20-H21/2)*$I$6*(1-$I$7)+I20-H21 -> #N/A | P21: 75%/80% af løn | Q21: 0.8 | R21: =R20*Q21 -> 0
B22: =B21+1 -> 13 | C22: =C21*(1+$D$5) -> 0 | D22: =(E21+C22/2)*(1-$D$7)*$D$6 -> 0 | E22: =E21+C22+D22 -> 0 | F22: =PV($D$5,B22,0,-E22) -> 0 | G22: =G21+1 -> 13 | H22: =H21*(1+$I$5) -> 0 | I22: =(I21-H22/2)*$I$6*(1-$I$7)+I21-H22 -> #N/A | P22: Folkepension | R22: =R13 -> 86376 | S22: juster så det passer
B23: =B22+1 -> 14 | C23: =C22*(1+$D$5) -> 0 | D23: =(E22+C23/2)*(1-$D$7)*$D$6 -> 0 | E23: =E22+C23+D23 -> 0 | F23: =PV($D$5,B23,0,-E23) -> 0 | G23: =G22+1 -> 14 | H23: =H22*(1+$I$5) -> 0 | I23: =(I22-H23/2)*$I$6*(1-$I$7)+I22-H23 -> #N/A | P23: Atp | R23: =R18 -> 28119 | S23: =S22 -> juster så det passer
B24: =B23+1 -> 15 | C24: =C23*(1+$D$5) -> 0 | D24: =(E23+C24/2)*(1-$D$7)*$D$6 -> 0 | E24: =E23+C24+D24 -> 0 | F24: =PV($D$5,B24,0,-E24) -> 0 | G24: =G23+1 -> 15 | H24: =H23*(1+$I$5) -> 0 | I24: =(I23-H24/2)*$I$6*(1-$I$7)+I23-H24 -> #N/A | P24: Forventet udb. Pension | R24: =H10 -> 0 | S24: evt. pensionsinfo
B25: =B24+1 -> 16 | C25: =C24*(1+$D$5) -> 0 | D25: =(E24+C25/2)*(1-$D$7)*$D$6 -> 0 | E25: =E24+C25+D25 -> 0 | F25: =PV($D$5,B25,0,-E25) -> 0 | G25: =G24+1 -> 16 | H25: =H24*(1+$I$5) -> 0 | I25: =(I24-H25/2)*$I$6*(1-$I$7)+I24-H25 -> #N/A | P25: Friværdi + anden formue | R25: =K9 -> 0
B26: =B25+1 -> 17 | C26: =C25*(1+$D$5) -> 0 | D26: =(E25+C26/2)*(1-$D$7)*$D$6 -> 0 | E26: =E25+C26+D26 -> 0 | F26: =PV($D$5,B26,0,-E26) -> 0 | G26: =G25+1 -> 17 | H26: =H25*(1+$I$5) -> 0 | I26: =(I25-H26/2)*$I$6*(1-$I$7)+I25-H26 -> #N/A | P26: Mangler hvert år | R26: =R21-R22-R23-R24-R25 -> -114495
B27: =B26+1 -> 18 | C27: =C26*(1+$D$5) -> 0 | D27: =(E26+C27/2)*(1-$D$7)*$D$6 -> 0 | E27: =E26+C27+D27 -> 0 | F27: =PV($D$5,B27,0,-E27) -> 0 | G27: =G26+1 -> 18 | H27: =H26*(1+$I$5) -> 0 | I27: =(I26-H27/2)*$I$6*(1-$I$7)+I26-H27 -> #N/A
B28: =B27+1 -> 19 | C28: =C27*(1+$D$5) -> 0 | D28: =(E27+C28/2)*(1-$D$7)*$D$6 -> 0 | E28: =E27+C28+D28 -> 0 | F28: =PV($D$5,B28,0,-E28) -> 0 | G28: =G27+1 -> 19 | H28: =H27*(1+$I$5) -> 0 | I28: =(I27-H28/2)*$I$6*(1-$I$7)+I27-H28 -> #N/A | P28: Udbetalt pr. år | R28: =R22+R23+R24+R25 -> 114495
B29: =B28+1 -> 20 | C29: =C28*(1+$D$5) -> 0 | D29: =(E28+C29/2)*(1-$D$7)*$D$6 -> 0 | E29: =E28+C29+D29 -> 0 | F29: =PV($D$5,B29,0,-E29) -> 0 | G29: =G28+1 -> 20 | H29: =H28*(1+$I$5) -> 0 | I29: =(I28-H29/2)*$I$6*(1-$I$7)+I28-H29 -> #N/A | P29: Udbetalt i % | R29: =R28/R20 -> #DIV/0!
B30: =B29+1 -> 21 | C30: =C29*(1+$D$5) -> 0 | D30: =(E29+C30/2)*(1-$D$7)*$D$6 -> 0 | E30: =E29+C30+D30 -> 0 | F30: =PV($D$5,B30,0,-E30) -> 0 | G30: =G29+1 -> 21 | H30: =H29*(1+$I$5) -> 0 | I30: =(I29-H30/2)*$I$6*(1-$I$7)+I29-H30 -> #N/A
B31: =B30+1 -> 22 | C31: =C30*(1+$D$5) -> 0 | D31: =(E30+C31/2)*(1-$D$7)*$D$6 -> 0 | E31: =E30+C31+D31 -> 0 | F31: =PV($D$5,B31,0,-E31) -> 0 | G31: =G30+1 -> 22 | H31: =H30*(1+$I$5) -> 0 | I31: =(I30-H31/2)*$I$6*(1-$I$7)+I30-H31 -> #N/A
B32: =B31+1 -> 23 | C32: =C31*(1+$D$5) -> 0 | D32: =(E31+C32/2)*(1-$D$7)*$D$6 -> 0 | E32: =E31+C32+D32 -> 0 | F32: =PV($D$5,B32,0,-E32) -> 0 | G32: =G31+1 -> 23 | H32: =H31*(1+$I$5) -> 0 | I32: =(I31-H32/2)*$I$6*(1-$I$7)+I31-H32 -> #N/A
B33: =B32+1 -> 24 | C33: =C32*(1+$D$5) -> 0 | D33: =(E32+C33/2)*(1-$D$7)*$D$6 -> 0 | E33: =E32+C33+D33 -> 0 | F33: =PV($D$5,B33,0,-E33) -> 0 | G33: =G32+1 -> 24 | H33: =H32*(1+$I$5) -> 0 | I33: =(I32-H33/2)*$I$6*(1-$I$7)+I32-H33 -> #N/A | K33: Antag at pensionsalderes efter 2030 fortsat er 68 år
B34: =B33+1 -> 25 | C34: =C33*(1+$D$5) -> 0 | D34: =(E33+C34/2)*(1-$D$7)*$D$6 -> 0 | E34: =E33+C34+D34 -> 0 | F34: =PV($D$5,B34,0,-E34) -> 0 | G34: =G33+1 -> 25 | H34: =H33*(1+$I$5) -> 0 | I34: =(I33-H34/2)*$I$6*(1-$I$7)+I33-H34 -> #N/A | K34: Dette er en meget forenklet billede af folkepensionsalderen - vi har bestemt at det kun er disse I skal kende​
B35: =B34+1 -> 26 | C35: =C34*(1+$D$5) -> 0 | D35: =(E34+C35/2)*(1-$D$7)*$D$6 -> 0 | E35: =E34+C35+D35 -> 0 | F35: =PV($D$5,B35,0,-E35) -> 0 | G35: =G34+1 -> 26 | H35: =H34*(1+$I$5) -> 0 | I35: =(I34-H35/2)*$I$6*(1-$I$7)+I34-H35 -> #N/A | K35: Kilde: https://star.dk/ydelser/pension-og-efterloen/folkepension-og-foertidspension/folkepension/folkepensionsalderen-nu-og-fremover/​
B36: =B35+1 -> 27 | C36: =C35*(1+$D$5) -> 0 | D36: =(E35+C36/2)*(1-$D$7)*$D$6 -> 0 | E36: =E35+C36+D36 -> 0 | F36: =PV($D$5,B36,0,-E36) -> 0 | G36: =G35+1 -> 27 | H36: =H35*(1+$I$5) -> 0 | I36: =(I35-H36/2)*$I$6*(1-$I$7)+I35-H36 -> #N/A
B37: =B36+1 -> 28 | C37: =C36*(1+$D$5) -> 0 | D37: =(E36+C37/2)*(1-$D$7)*$D$6 -> 0 | E37: =E36+C37+D37 -> 0 | F37: =PV($D$5,B37,0,-E37) -> 0 | G37: =G36+1 -> 28 | H37: =H36*(1+$I$5) -> 0 | I37: =(I36-H37/2)*$I$6*(1-$I$7)+I36-H37 -> #N/A | K37: I vores beregning forudsætter vi at der ikke kan opnås tillæg til folkepensionen.
B38: =B37+1 -> 29 | C38: =C37*(1+$D$5) -> 0 | D38: =(E37+C38/2)*(1-$D$7)*$D$6 -> 0 | E38: =E37+C38+D38 -> 0 | F38: =PV($D$5,B38,0,-E38) -> 0 | G38: =G37+1 -> 29 | H38: =H37*(1+$I$5) -> 0 | I38: =(I37-H38/2)*$I$6*(1-$I$7)+I37-H38 -> #N/A
B39: =B38+1 -> 30 | C39: =C38*(1+$D$5) -> 0 | D39: =(E38+C39/2)*(1-$D$7)*$D$6 -> 0 | E39: =E38+C39+D39 -> 0 | F39: =PV($D$5,B39,0,-E39) -> 0 | G39: =G38+1 -> 30 | H39: =H38*(1+$I$5) -> 0 | I39: =(I38-H39/2)*$I$6*(1-$I$7)+I38-H39 -> #N/A
B40: =B39+1 -> 31 | C40: =C39*(1+$D$5) -> 0 | D40: =(E39+C40/2)*(1-$D$7)*$D$6 -> 0 | E40: =E39+C40+D40 -> 0 | F40: =PV($D$5,B40,0,-E40) -> 0 | G40: =G39+1 -> 31 | H40: =H39*(1+$I$5) -> 0 | I40: =(I39-H40/2)*$I$6*(1-$I$7)+I39-H40 -> #N/A
B41: =B40+1 -> 32 | C41: =C40*(1+$D$5) -> 0 | D41: =(E40+C41/2)*(1-$D$7)*$D$6 -> 0 | E41: =E40+C41+D41 -> 0 | F41: =PV($D$5,B41,0,-E41) -> 0 | G41: =G40+1 -> 32 | H41: =H40*(1+$I$5) -> 0 | I41: =(I40-H41/2)*$I$6*(1-$I$7)+I40-H41 -> #N/A
B42: =B41+1 -> 33 | C42: =C41*(1+$D$5) -> 0 | D42: =(E41+C42/2)*(1-$D$7)*$D$6 -> 0 | E42: =E41+C42+D42 -> 0 | F42: =PV($D$5,B42,0,-E42) -> 0 | G42: =G41+1 -> 33 | H42: =H41*(1+$I$5) -> 0 | I42: =(I41-H42/2)*$I$6*(1-$I$7)+I41-H42 -> #N/A
B43: =B42+1 -> 34 | C43: =C42*(1+$D$5) -> 0 | D43: =(E42+C43/2)*(1-$D$7)*$D$6 -> 0 | E43: =E42+C43+D43 -> 0 | F43: =PV($D$5,B43,0,-E43) -> 0 | G43: =G42+1 -> 34 | H43: =H42*(1+$I$5) -> 0 | I43: =(I42-H43/2)*$I$6*(1-$I$7)+I42-H43 -> #N/A
B44: =B43+1 -> 35 | C44: =C43*(1+$D$5) -> 0 | D44: =(E43+C44/2)*(1-$D$7)*$D$6 -> 0 | E44: =E43+C44+D44 -> 0 | F44: =PV($D$5,B44,0,-E44) -> 0 | G44: =G43+1 -> 35 | H44: =H43*(1+$I$5) -> 0 | I44: =(I43-H44/2)*$I$6*(1-$I$7)+I43-H44 -> #N/A
B45: =B44+1 -> 36 | C45: =C44*(1+$D$5) -> 0 | D45: =(E44+C45/2)*(1-$D$7)*$D$6 -> 0 | E45: =E44+C45+D45 -> 0 | F45: =PV($D$5,B45,0,-E45) -> 0 | G45: =G44+1 -> 36 | H45: =H44*(1+$I$5) -> 0 | I45: =(I44-H45/2)*$I$6*(1-$I$7)+I44-H45 -> #N/A
B46: =B45+1 -> 37 | C46: =C45*(1+$D$5) -> 0 | D46: =(E45+C46/2)*(1-$D$7)*$D$6 -> 0 | E46: =E45+C46+D46 -> 0 | F46: =PV($D$5,B46,0,-E46) -> 0 | G46: =G45+1 -> 37 | H46: =H45*(1+$I$5) -> 0 | I46: =(I45-H46/2)*$I$6*(1-$I$7)+I45-H46 -> #N/A
B47: =B46+1 -> 38 | C47: =C46*(1+$D$5) -> 0 | D47: =(E46+C47/2)*(1-$D$7)*$D$6 -> 0 | E47: =E46+C47+D47 -> 0 | F47: =PV($D$5,B47,0,-E47) -> 0 | G47: =G46+1 -> 38 | H47: =H46*(1+$I$5) -> 0 | I47: =(I46-H47/2)*$I$6*(1-$I$7)+I46-H47 -> #N/A
B48: =B47+1 -> 39 | C48: =C47*(1+$D$5) -> 0 | D48: =(E47+C48/2)*(1-$D$7)*$D$6 -> 0 | E48: =E47+C48+D48 -> 0 | F48: =PV($D$5,B48,0,-E48) -> 0 | G48: =G47+1 -> 39 | H48: =H47*(1+$I$5) -> 0 | I48: =(I47-H48/2)*$I$6*(1-$I$7)+I47-H48 -> #N/A
B49: =B48+1 -> 40 | C49: =C48*(1+$D$5) -> 0 | D49: =(E48+C49/2)*(1-$D$7)*$D$6 -> 0 | E49: =E48+C49+D49 -> 0 | F49: =PV($D$5,B49,0,-E49) -> 0 | G49: =G48+1 -> 40 | H49: =H48*(1+$I$5) -> 0 | I49: =(I48-H49/2)*$I$6*(1-$I$7)+I48-H49 -> #N/A
... B59: =B58+1 -> 50 | C59: =C58*(1+$D$5) -> 0 | D59: =(E58+C59/2)*(1-$D$7)*$D$6 -> 0 | E59: =E58+C59+D59 -> 0 | F59: =PV($D$5,B59,0,-E59) -> 0 | G59: =G58+1 -> 50 | H59: =H58*(1+$I$5) -> 0 | I59: =(I58-H59/2)*$I$6*(1-$I$7)+I58-H59 -> #N/A

Sheet Låneskabelon
B2: Lånets størrelse (hovedstolen)
B3: Løbetid, år
B4: Antal terminer pr. år
B5: Rente pr år, (pålydende/nominel)
B6: Effektiv rente pr. år | C6: =(1+C5/C4)^C4-1 -> #DIV/0!
B8: Etableringsomkostninger:
B9: Staten, tinglysning | C9: =1850+1.5%*C2 -> 1850 | D9: Og ja, man skal vurdere om der skal være omkostninger på 1,45 pct. eller 1,5 pct. og 1.825 kr. eller 1.850 kr., jf. slide 16 i powerpoint Præsentation "Udlån og kreditvurdering"
B10: Pengeinstitut, etablering | C10: =2%*C2+1000+950 -> 1950 | D10: anslået
B11: Andet | C11: 0
B12: Etableringsomkostninger i alt | C12: =SUM(C9:C11) -> 3800
B14: Provenu (hvad får jeg i hånden) | C14: =C2-C12 -> -3800
B16: Omkostninger i procent pr. termin | C16: =RATE(C3*C4,C20,C14) -> #DIV/0!
B17: ÅOP | C17: =(1+C16)^C4-1 -> #DIV/0!
C19: Pr. termin | D19: Pr.år
B20: Ydelse pr. termin før skat | C20: =PMT(C5/C4,C3*C4,C2) -> #DIV/0! | D20: =C4*C20 -> #DIV/0!
B21: Renteudgifter år 1 | C21: =D21/C4 -> #DIV/0! | D21: =CUMIPMT(C5/C4,C3*C4,C2,1,C4,0) -> #DIV/0!
B22: Skattefar betaler 1/3 | C22: =D22/C4 -> #DIV/0! | D22: =1/3*D21 -> #DIV/0!
B23: Ydelse pr. termin efter skat | C23: =C20-C22 -> #DIV/0! | D23: =D20-D22 -> #DIV/0!

Sheet Ark1
